Workbook
Name A1_billable_hours: '[1]1.0 Pricing & Role Selection'!$J$31
Name A1_nonbillable_hours: '[1]1.0 Pricing & Role Selection'!$K$31
Name A10_billable_hours: '[1]1.0 Pricing & Role Selection'!$J$40
Name A10_nonbillable_hours: '[1]1.0 Pricing & Role Selection'!$K$40
Name A11_billable_hours: '[1]1.0 Pricing & Role Selection'!$J$41
Name A11_nonbillable_hours: '[1]1.0 Pricing & Role Selection'!$K$41
Name A12_billable_hours: '[1]1.0 Pricing & Role Selection'!$J$42
Name A12_nonbillable_hours: '[1]1.0 Pricing & Role Selection'!$K$42
Name A13_billable_hours: '[1]1.0 Pricing & Role Selection'!$J$43
Name A13_nonbillable_hours: '[1]1.0 Pricing & Role Selection'!$K$43
Name A14_billable_hours: '[1]1.0 Pricing & Role Selection'!$J$44
Name A14_nonbillable_hours: '[1]1.0 Pricing & Role Selection'!$K$44
Name A15_billable_hours: '[1]1.0 Pricing & Role Selection'!$J$45
Name A15_nonbillable_hours: '[1]1.0 Pricing & Role Selection'!$K$45
Name A2_billable_hours: '[1]1.0 Pricing & Role Selection'!$J$32
Name A2_nonbillable_hours: '[1]1.0 Pricing & Role Selection'!$K$32
Name A3_billable_hours: '[1]1.0 Pricing & Role Selection'!$J$33
Name A3_nonbillable_hours: '[1]1.0 Pricing & Role Selection'!$K$33
Name A4_billable_hours: '[1]1.0 Pricing & Role Selection'!$J$34
Name A4_nonbillable_hours: '[1]1.0 Pricing & Role Selection'!$K$34
Name A5_billable_hours: '[1]1.0 Pricing & Role Selection'!$J$35
Name A5_nonbillable_hours: '[1]1.0 Pricing & Role Selection'!$K$35
Name A6_billable_hours: '[1]1.0 Pricing & Role Selection'!$J$36
Name A6_nonbillable_hours: '[1]1.0 Pricing & Role Selection'!$K$36
Name A7_billable_hours: '[1]1.0 Pricing & Role Selection'!$J$37
Name A7_nonbillable_hours: '[1]1.0 Pricing & Role Selection'!$K$37
Name A8_billable_hours: '[1]1.0 Pricing & Role Selection'!$J$38
Name A8_nonbillable_hours: '[1]1.0 Pricing & Role Selection'!$K$38
Name A9_billable_hours: '[1]1.0 Pricing & Role Selection'!$J$39
Name A9_nonbillable_hours: '[1]1.0 Pricing & Role Selection'!$K$39
Name Agile_Tax: '[1]Opportunity Details'!$F$16
Name Agile_Tax: 'Opportunity Details'!$F$16
Name Applications_In_Scope: '[1]2.0 Scoping'!$C$2:$D$19
Name B1_billable_hours: '[1]1.0 Pricing & Role Selection'!$J$47
Name B1_nonbillable_hours: '[1]1.0 Pricing & Role Selection'!$K$47
Name B10_billable_hours: '[1]1.0 Pricing & Role Selection'!$J$56
Name B10_nonbillable_hours: '[1]1.0 Pricing & Role Selection'!$K$56
Name B11_billable_hours: '[1]1.0 Pricing & Role Selection'!$J$57
Name B11_nonbillable_hours: '[1]1.0 Pricing & Role Selection'!$K$57
Name B12_billable_hours: '[1]1.0 Pricing & Role Selection'!$J$58
Name B12_nonbillable_hours: '[1]1.0 Pricing & Role Selection'!$K$58
Name B13_billable_hours: '[1]1.0 Pricing & Role Selection'!$J$59
Name B13_nonbillable_hours: '[1]1.0 Pricing & Role Selection'!$K$59
Name B14_billable_hours: '[1]1.0 Pricing & Role Selection'!$J$60
Name B14_nonbillable_hours: '[1]1.0 Pricing & Role Selection'!$K$60
Name B15_billable_hours: '[1]1.0 Pricing & Role Selection'!$J$61
Name B15_nonbillable_hours: '[1]1.0 Pricing & Role Selection'!$K$61
Name B2_billable_hours: '[1]1.0 Pricing & Role Selection'!$J$48
Name B2_nonbillable_hours: '[1]1.0 Pricing & Role Selection'!$K$48
Name B3_billable_hours: '[1]1.0 Pricing & Role Selection'!$J$49
Name B3_nonbillable_hours: '[1]1.0 Pricing & Role Selection'!$K$49
Name B4_billable_hours: '[1]1.0 Pricing & Role Selection'!$J$50
Name B4_nonbillable_hours: '[1]1.0 Pricing & Role Selection'!$K$50
Name B5_billable_hours: '[1]1.0 Pricing & Role Selection'!$J$51
Name B5_nonbillable_hours: '[1]1.0 Pricing & Role Selection'!$K$51
Name B6_billable_hours: '[1]1.0 Pricing & Role Selection'!$J$52
Name B6_nonbillable_hours: '[1]1.0 Pricing & Role Selection'!$K$52
Name B7_billable_hours: '[1]1.0 Pricing & Role Selection'!$J$53
Name B7_nonbillable_hours: '[1]1.0 Pricing & Role Selection'!$K$53
Name B8_billable_hours: '[1]1.0 Pricing & Role Selection'!$J$54

Sheet Estimate - Master (2)
B2: ='Opportunity Details'!A3 -> Salesforce Opportunity Number | C2: =IF(ISBLANK('Opportunity Details'!C3), "Populate Sales Force ID on Opportunity Details Sheet", 'Opportunity Details'!C3) -> Populate Sales Force ID on Opportunity Details Sheet
B3: ='Opportunity Details'!A4 -> Opportunity Name | C3: =IF(ISBLANK('Opportunity Details'!C4),"Populate Engagement Title on Opportunity Details Sheet",'Opportunity Details'!C4) -> Acme Opportunity
B4: ='Opportunity Details'!A7 -> Account Name | C4: =IF(ISBLANK('Opportunity Details'!C7),"Populate Client on Opportunity Details Sheet",'Opportunity Details'!C7) -> Boeing ITSM Now Assist AI POC
B5: Use Case: | C5: Replace ITSM System
B6: Product Line | C6: IT Workflows
O7: IT Workflows | AB7: Customer and Employee Workflows | AP7: IRM / SecOps
O8: US | AB8: US | AP8: US
O9: =#REF! -> #REF! | P9: =#REF! -> #REF! | Q9: =#REF! -> #REF! | R9: =#REF! -> #REF! | S9: =#REF! -> #REF! | T9: =#REF! -> #REF! | U9: =#REF! -> #REF! | V9: =#REF! -> #REF! | ... Y9: =#REF! -> #REF! | AB9: =#REF! -> #REF! | AC9: =#REF! -> #REF! | AD9: =#REF! -> #REF! | AE9: =#REF! -> #REF! | AF9: =#REF! -> #REF! | AG9: =#REF! -> #REF! | AH9: =#REF! -> #REF! | AI9: =#REF! -> #REF! | ... AM9: =#REF! -> #REF! | AP9: =#REF! -> #REF! | AQ9: =#REF! -> #REF! | AR9: =#REF! -> #REF! | AS9: =#REF! -> #REF! | AT9: =#REF! -> #REF! | AU9: =#REF! -> #REF! | AV9: =#REF! -> #REF! | AW9: =#REF! -> #REF! | ... BA9: =#REF! -> #REF!
B10: STAGE | C10: Phase | D10: Task | E10: Description | F10: Assumption | G10: Project Role | H10: Billable/ Non-Billable | I10: Hours | J10: Rate / HR | K10: Estimated Cost | L10: Additional PM Oversight | M10: Additional BA Oversight | N10: Additional SA Oversight | O10: Program Director (IT Workflow - US) | P10: Engagement Manager (IT Workflow - US) | Q10: Project Coordinator (IT Workflow - US) | R10: Chief Business Process Architect (IT Workflow - US) | S10: Business Process Architect (IT Workflow - US) | T10: Business Analyst (IT Workflow - US) | U10: Chief Architect (IT Workflow - US) | V10: Solution Architect (IT Workflow - US) | W10: Platform Architect (IT Workflow - US) | X10: Chief Engineer (IT Workflow - US) | Y10: Lead Engineer (IT Workflow - US) | Z10: Engineer (IT Workflow - US) | AA10: TOTAL (IT Workflow - US) | AB10: Notes (IT Workflow - US) | AC10: Program Director (Customer and Employee Workflow - US) | AD10: Engagement Manager (Customer and Employee Workflow - US) | AE10: Project Coordinator (Customer and Employee Workflow - US) | AF10: Chief Business Process Architect (Customer and Employee Workflow - US) | AG10: Business Process Architect (Customer and Employee Workflow - US) | AH10: Business Analyst (Customer and Employee Workflow - US) | AI10: Chief Architect (Customer and Employee Workflow - US) | AJ10: Solution Architect (Customer and Employee Workflow - US) | AK10: Platform Architect (Customer and Employee Workflow - US) | AL10: Chief Engineer (Customer and Employee Workflow - US) | AM10: Lead Engineer (Customer and Employee Workflow - US) | AN10: Engineer (Customer and Employee Workflow - US) | AO10: TOTAL (Customer and Employee Workflow - US) | AP10: Notes (Customer and Employee Workflow - US) | AQ10: Program Director (IRM / SecOps - US) | AR10: Engagement Manager (IRM / SecOps - US) | AS10: Project Coordinator (IRM / SecOps - US) | AT10: Chief Business Process Architect (IRM / SecOps - US) | AU10: Business Process Architect (IRM / SecOps - US) | AV10: Business Analyst (IRM / SecOps - US) | AW10: Chief Architect (IRM / SecOps - US) | AX10: Solution Architect (IRM / SecOps - US) | AY10: Platform Architect (IRM / SecOps - US) | AZ10: Chief Engineer (IRM / SecOps - US) | BA10: Lead Engineer (IRM / SecOps - US) | BB10: Engineer (IRM / SecOps - US) | BC10: TOTAL (IRM / SecOps - US) | BD10: Notes (Customer and Employee Workflow - US)
B11: INITIATE | AA11: =SUM(Table1456[[#This Row],[Program Director (IT Workflow - US)]:[Engineer (IT Workflow - US)]]) -> 0 | AO11: =SUM(Table1456[[#This Row],[Program Director (Customer and Employee Workflow - US)]:[Engineer (Customer and Employee Workflow - US)]]) -> 0
C12: Initate | D12: Project Set-up | E12: Initial PM introductions, project set-up, and sales to delivery handover. | G12: Chief Architect | H12: Billable - Offshore | I12: 4 | J12: {=INDEX('Client Rates and Roles'!$F$2:$F$433,MATCH(1,COUNTIFS('Opportunity Details'!$C$14,'Client Rates and Roles'!$D$2:$D$433,G12,'Client Rates and Roles'!$B$2:$B$433,H12,'Client Rates and Roles'!$C$2:$C$433,$C$6,'Client Rates and Roles'!$A$2:$A$433),0))} -> #N/A | K12: =I12*J12 -> #N/A | L12: 0 | M12: 20 | N12: 2 | AA12: =SUM(Table1456[[#This Row],[Program Director (IT Workflow - US)]:[Engineer (IT Workflow - US)]]) -> 0 | AO12: =SUM(Table1456[[#This Row],[Program Director (Customer and Employee Workflow - US)]:[Engineer (Customer and Employee Workflow - US)]]) -> 0 | BC12: =SUM(Table1456[[#This Row],[Program Director (IT Workflow - US)]:[Chief Architect (IT Workflow - US)]]) -> 0
C13: Initate | D13: Pre-Engagement Questionnaire | E13: NewRocket will prepare a pre-engagement questionnaire regarding current state of <client>'s platform and vulnerability response program. | F13: • <Client> will be responsible for responding to the pre-engagement questionnaire prior to resource assignment and project kick-off. • <Client> will be responsible for locating the service account owners with access to credentials for any integrations (ex. Scanner). | G13: Architect | H13: Billable - Onshore | I13: 4 | J13: {=INDEX('Client Rates and Roles'!$F$2:$F$433,MATCH(1,COUNTIFS('Opportunity Details'!$C$14,'Client Rates and Roles'!$D$2:$D$433,G13,'Client Rates and Roles'!$B$2:$B$433,H13,'Client Rates and Roles'!$C$2:$C$433,$C$6,'Client Rates and Roles'!$A$2:$A$433),0))} -> #N/A | K13: =I13*J13 -> #N/A | L13: 0 | N13: 2 | AA13: =SUM(Table1456[[#This Row],[Program Director (IT Workflow - US)]:[Engineer (IT Workflow - US)]]) -> 0 | AO13: =SUM(Table1456[[#This Row],[Program Director (Customer and Employee Workflow - US)]:[Engineer (Customer and Employee Workflow - US)]]) -> 0 | BC13: =SUM(Table1456[[#This Row],[Program Director (IT Workflow - US)]:[Chief Architect (IT Workflow - US)]]) -> 0
C14: Initate | D14: Onboard Resources | E14: Project team assigned and coordination with <client> PM to arrange NewRocket access to client's ServiceNow environment(s). | F14: • NewRocket will access Customer’s ServiceNow instance directly from their NewRocket-provided laptops. • NewRocket will not be required to complete any <Client> mandated training. | G14: Practice lead | H14: Billable - Onshore | I14: 4 | J14: {=INDEX('Client Rates and Roles'!$F$2:$F$433,MATCH(1,COUNTIFS('Opportunity Details'!$C$14,'Client Rates and Roles'!$D$2:$D$433,G14,'Client Rates and Roles'!$B$2:$B$433,H14,'Client Rates and Roles'!$C$2:$C$433,$C$6,'Client Rates and Roles'!$A$2:$A$433),0))} -> #N/A | K14: =I14*J14 -> #N/A | L14: 0 | N14: 2 | AA14: =SUM(Table1456[[#This Row],[Program Director (IT Workflow - US)]:[Engineer (IT Workflow - US)]]) -> 0 | AO14: =SUM(Table1456[[#This Row],[Program Director (Customer and Employee Workflow - US)]:[Engineer (Customer and Employee Workflow - US)]]) -> 0 | BC14: =SUM(Table1456[[#This Row],[Program Director (IT Workflow - US)]:[Chief Architect (IT Workflow - US)]]) -> 0
C15: Initate | D15: Project Planning | E15: Co-develop draft project plan between NewRocket and <Client> PM, including review of NewRocket governance process that will be used for project delivery. | G15: Practice lead | H15: Billable - Onshore | I15: 4 | J15: {=INDEX('Client Rates and Roles'!$F$2:$F$433,MATCH(1,COUNTIFS('Opportunity Details'!$C$14,'Client Rates and Roles'!$D$2:$D$433,G15,'Client Rates and Roles'!$B$2:$B$433,H15,'Client Rates and Roles'!$C$2:$C$433,$C$6,'Client Rates and Roles'!$A$2:$A$433),0))} -> #N/A | K15: =I15*J15 -> #N/A | L15: 0 | N15: 2 | AA15: =SUM(Table1456[[#This Row],[Program Director (IT Workflow - US)]:[Engineer (IT Workflow - US)]]) -> 0 | AO15: =SUM(Table1456[[#This Row],[Program Director (Customer and Employee Workflow - US)]:[Engineer (Customer and Employee Workflow - US)]]) -> 0 | BC15: =SUM(Table1456[[#This Row],[Program Director (IT Workflow - US)]:[Chief Architect (IT Workflow - US)]]) -> 0
C16: Initate | D16: Project Kick-Off | E16: Prepare for and conduct formal one (1) hour project kickoff meeting to review goals and objectives, scope, engagement team and initial timeline. | G16: Practice lead | H16: Billable - Onshore | I16: 4 | J16: {=INDEX('Client Rates and Roles'!$F$2:$F$433,MATCH(1,COUNTIFS('Opportunity Details'!$C$14,'Client Rates and Roles'!$D$2:$D$433,G16,'Client Rates and Roles'!$B$2:$B$433,H16,'Client Rates and Roles'!$C$2:$C$433,$C$6,'Client Rates and Roles'!$A$2:$A$433),0))} -> #N/A | K16: =I16*J16 -> #N/A | L16: 0 | N16: 2 | AA16: =SUM(Table1456[[#This Row],[Program Director (IT Workflow - US)]:[Engineer (IT Workflow - US)]]) -> 0 | AO16: =SUM(Table1456[[#This Row],[Program Director (Customer and Employee Workflow - US)]:[Engineer (Customer and Employee Workflow - US)]]) -> 0 | BC16: =SUM(Table1456[[#This Row],[Program Director (IT Workflow - US)]:[Chief Architect (IT Workflow - US)]]) -> 0
B17: PREPARE | AA17: =SUM(Table1456[[#This Row],[Program Director (IT Workflow - US)]:[Engineer (IT Workflow - US)]]) -> 0 | AO17: =SUM(Table1456[[#This Row],[Program Director (Customer and Employee Workflow - US)]:[Engineer (Customer and Employee Workflow - US)]]) -> 0
C18: Prepare | D18: Workshop A | E18: Review of <client>'s response to pre-engagement questionnaire and any processes/artifacts provided as part of the response. | G18: Business Analyst | H18: Billable - Onshore | I18: 40 | J18: {=INDEX('Client Rates and Roles'!$F$2:$F$433,MATCH(1,COUNTIFS('Opportunity Details'!$C$14,'Client Rates and Roles'!$D$2:$D$433,G18,'Client Rates and Roles'!$B$2:$B$433,H18,'Client Rates and Roles'!$C$2:$C$433,$C$6,'Client Rates and Roles'!$A$2:$A$433),0))} -> #N/A | K18: =I18*J18 -> #N/A | L18: 0 | N18: 40 | AA18: =SUM(Table1456[[#This Row],[Program Director (IT Workflow - US)]:[Engineer (IT Workflow - US)]]) -> 0 | AO18: =SUM(Table1456[[#This Row],[Program Director (Customer and Employee Workflow - US)]:[Engineer (Customer and Employee Workflow - US)]]) -> 0 | BC18: =SUM(Table1456[[#This Row],[Program Director (IT Workflow - US)]:[Chief Architect (IT Workflow - US)]]) -> 0
C19: Prepare | D19: Workshop B | E19: Up to a four (4) hour workshop session to review RDSO methodology, current state, and art of the possible focusing on OOTB ServiceNow objects that will be used as part of rapid deployment. | G19: Chief architect | H19: Billable - Offshore | I19: 4 | J19: {=INDEX('Client Rates and Roles'!$F$2:$F$433,MATCH(1,COUNTIFS('Opportunity Details'!$C$14,'Client Rates and Roles'!$D$2:$D$433,G19,'Client Rates and Roles'!$B$2:$B$433,H19,'Client Rates and Roles'!$C$2:$C$433,$C$6,'Client Rates and Roles'!$A$2:$A$433),0))} -> #N/A | K19: =I19*J19 -> #N/A | L19: 0 | N19: 2 | AA19: =SUM(Table1456[[#This Row],[Program Director (IT Workflow - US)]:[Engineer (IT Workflow - US)]]) -> 0 | AO19: =SUM(Table1456[[#This Row],[Program Director (Customer and Employee Workflow - US)]:[Engineer (Customer and Employee Workflow - US)]]) -> 0 | BC19: =SUM(Table1456[[#This Row],[Program Director (IT Workflow - US)]:[Chief Architect (IT Workflow - US)]]) -> 0
C20: Prepare | D20: Workshop C | E20: Develop high-level design approach outlining: • Project outcomes; • Solution assumptions; • ServiceNow objects that will be used to meet the project outcomes; and • Sprint plan to refine detailed requirements. | G20: Consultant | H20: Billable - Offshore | I20: 4 | J20: {=INDEX('Client Rates and Roles'!$F$2:$F$433,MATCH(1,COUNTIFS('Opportunity Details'!$C$14,'Client Rates and Roles'!$D$2:$D$433,G20,'Client Rates and Roles'!$B$2:$B$433,H20,'Client Rates and Roles'!$C$2:$C$433,$C$6,'Client Rates and Roles'!$A$2:$A$433),0))} -> #N/A | K20: =I20*J20 -> #N/A | L20: 0 | N20: 2 | AA20: =SUM(Table1456[[#This Row],[Program Director (IT Workflow - US)]:[Engineer (IT Workflow - US)]]) -> 0 | AO20: =SUM(Table1456[[#This Row],[Program Director (Customer and Employee Workflow - US)]:[Engineer (Customer and Employee Workflow - US)]]) -> 0 | BC20: =SUM(Table1456[[#This Row],[Program Director (IT Workflow - US)]:[Chief Architect (IT Workflow - US)]]) -> 0
C21: Prepare | D21: Finalize Project Plan | E21: Finalize project plan outlining project phases, sprints, and testing timelines. | G21: Consultant | H21: Billable - Onshore | I21: 4 | J21: {=INDEX('Client Rates and Roles'!$F$2:$F$433,MATCH(1,COUNTIFS('Opportunity Details'!$C$14,'Client Rates and Roles'!$D$2:$D$433,G21,'Client Rates and Roles'!$B$2:$B$433,H21,'Client Rates and Roles'!$C$2:$C$433,$C$6,'Client Rates and Roles'!$A$2:$A$433),0))} -> #N/A | K21: =I21*J21 -> #N/A | L21: 0 | N21: 2 | AA21: =SUM(Table1456[[#This Row],[Program Director (IT Workflow - US)]:[Engineer (IT Workflow - US)]]) -> 0 | AO21: =SUM(Table1456[[#This Row],[Program Director (Customer and Employee Workflow - US)]:[Engineer (Customer and Employee Workflow - US)]]) -> 0 | BC21: =SUM(Table1456[[#This Row],[Program Director (IT Workflow - US)]:[Chief Architect (IT Workflow - US)]]) -> 0
C22: Prepare | D22: Develop User Stories/ Story Grooming | E22: Conduct up to meetings to develop user stories and document acceptance criteria. Meetings will run concurrent to the Create stage and topics will be based on sprint plan. | F22: • User Stories and Grooming sessions will follow a pre-defined process and set of draft user stories. There will be up to ten (10) requirements gathering meetings held throughout the sprints focusing on specific topic areas. Each meeting will run between thirty (30) minutes to sixty (60) minutes in duration depending on topic area. <Client> will be expected to ensure appropriate decision makers are including in the meetings to provide requirements. | G22: Consultant | H22: Billable - Onshore | I22: 4 | J22: {=INDEX('Client Rates and Roles'!$F$2:$F$433,MATCH(1,COUNTIFS('Opportunity Details'!$C$14,'Client Rates and Roles'!$D$2:$D$433,G22,'Client Rates and Roles'!$B$2:$B$433,H22,'Client Rates and Roles'!$C$2:$C$433,$C$6,'Client Rates and Roles'!$A$2:$A$433),0))} -> #N/A | K22: =I22*J22 -> #N/A | L22: 0 | N22: 2 | AA22: =SUM(Table1456[[#This Row],[Program Director (IT Workflow - US)]:[Engineer (IT Workflow - US)]]) -> 0 | AO22: =SUM(Table1456[[#This Row],[Program Director (Customer and Employee Workflow - US)]:[Engineer (Customer and Employee Workflow - US)]]) -> 0 | BC22: =SUM(Table1456[[#This Row],[Program Director (IT Workflow - US)]:[Chief Architect (IT Workflow - US)]]) -> 0
B23: EXECUTE | AA23: =SUM(Table1456[[#This Row],[Program Director (IT Workflow - US)]:[Engineer (IT Workflow - US)]]) -> 0 | AO23: =SUM(Table1456[[#This Row],[Program Director (Customer and Employee Workflow - US)]:[Engineer (Customer and Employee Workflow - US)]]) -> 0
C24: Execute | D24: Install Plugins | E24: Install and enable OOTB Security Operations and Vulnerability Response plugin applications in all environments. | F24: • This implementation assumes that all VR configuration will be completed using OOTB configuration options and no scripted solutions will be developed. • <Client> is responsible for ensuring platform and solution plugins versions are the same in all environments. | G24: Consultant | H24: Billable - Offshore | I24: 4 | J24: {=INDEX('Client Rates and Roles'!$F$2:$F$433,MATCH(1,COUNTIFS('Opportunity Details'!$C$14,'Client Rates and Roles'!$D$2:$D$433,G24,'Client Rates and Roles'!$B$2:$B$433,H24,'Client Rates and Roles'!$C$2:$C$433,$C$6,'Client Rates and Roles'!$A$2:$A$433),0))} -> #N/A | K24: =I24*J24 -> #N/A | L24: 0 | N24: 2 | AA24: =SUM(Table1456[[#This Row],[Program Director (IT Workflow - US)]:[Engineer (IT Workflow - US)]]) -> 0 | AO24: =SUM(Table1456[[#This Row],[Program Director (Customer and Employee Workflow - US)]:[Engineer (Customer and Employee Workflow - US)]]) -> 0 | BC24: =SUM(Table1456[[#This Row],[Program Director (IT Workflow - US)]:[Chief Architect (IT Workflow - US)]]) -> 0
C25: Execute | D25: TBC (Scanner) Integration | E25: Document and perform default installation and configuration for TBC (Scanner) integration available from ServiceNow Store. Review scanned assets to ensure proper connection to ServiceNow. | F25: • Integration will be a Store provided Scanner integration with no customization. If MID servers are required for integrations, then they will be provided and managed by <Client>. • <Client> is responsible for owning and managing the Scanner. NewRocket is not responsible for troubleshooting any issues with the Scanner and ServiceNow. • To map vulnerabilities in lower environments, <Client> will be responsible for ensuring sample vulnerabilities are available in lower environments by either setting up a DEV/TEST instance of the Scanner or bringing sample PROD events to the lower environments. • <Client> will be responsible for ensuring DEV/TEST is populated with scannable CIs related to the scanner that will be connected to each environment. | G25: Consultant | H25: Billable - Onshore | I25: 4 | J25: {=INDEX('Client Rates and Roles'!$F$2:$F$433,MATCH(1,COUNTIFS('Opportunity Details'!$C$14,'Client Rates and Roles'!$D$2:$D$433,G25,'Client Rates and Roles'!$B$2:$B$433,H25,'Client Rates and Roles'!$C$2:$C$433,$C$6,'Client Rates and Roles'!$A$2:$A$433),0))} -> #N/A | K25: =I25*J25 -> #N/A | L25: 0 | N25: 2 | AA25: =SUM(Table1456[[#This Row],[Program Director (IT Workflow - US)]:[Engineer (IT Workflow - US)]]) -> 0 | AO25: =SUM(Table1456[[#This Row],[Program Director (Customer and Employee Workflow - US)]:[Engineer (Customer and Employee Workflow - US)]]) -> 0 | BC25: =SUM(Table1456[[#This Row],[Program Director (IT Workflow - US)]:[Chief Architect (IT Workflow - US)]]) -> 0
C26: Execute | D26: CMDB Attribute / CI Matching | E26: Review CMDB attributes for availability. Document and configure CI Matching/Look-up Rules. | F26: • FQDN and/or IP Address and/or NetBIOS and/or Name is populated in the CMDB and can be matched with scanner results for all scannable assets. NewRocket is not responsible for populating or updating the CMDB. • <Client> is responsible for identifying the attributes that will be used to support CI matching and look up. NewRocket is not responsible for analysing assets to increase match rate or advising or providing reccomendations on how to improve it. • Active IP management is out of scope for this engagement. If <Client> is using DHCP then additional effort will be required. **ANYTHING ELSE WE WANT TO INCLUDE TO PROTECT US???***** | G26: Architect | H26: Billable - Onshore | I26: 4 | J26: {=INDEX('Client Rates and Roles'!$F$2:$F$433,MATCH(1,COUNTIFS('Opportunity Details'!$C$14,'Client Rates and Roles'!$D$2:$D$433,G26,'Client Rates and Roles'!$B$2:$B$433,H26,'Client Rates and Roles'!$C$2:$C$433,$C$6,'Client Rates and Roles'!$A$2:$A$433),0))} -> #N/A | K26: =I26*J26 -> #N/A | L26: 0 | N26: 2 | AA26: =SUM(Table1456[[#This Row],[Program Director (IT Workflow - US)]:[Engineer (IT Workflow - US)]]) -> 0 | AO26: =SUM(Table1456[[#This Row],[Program Director (Customer and Employee Workflow - US)]:[Engineer (Customer and Employee Workflow - US)]]) -> 0 | BC26: =SUM(Table1456[[#This Row],[Program Director (IT Workflow - US)]:[Chief Architect (IT Workflow - US)]]) -> 0
C27: Execute | D27: Permissions, Roles and Groups | E27: Review and document OOTB roles and permissions that will be used to populate <client> defined groups. | F27: • OOTB roles will be leveraged to populate client defined groups with no permission changes or custom access model. | G27: Consultant | H27: Billable - Onshore | I27: 4 | J27: {=INDEX('Client Rates and Roles'!$F$2:$F$433,MATCH(1,COUNTIFS('Opportunity Details'!$C$14,'Client Rates and Roles'!$D$2:$D$433,G27,'Client Rates and Roles'!$B$2:$B$433,H27,'Client Rates and Roles'!$C$2:$C$433,$C$6,'Client Rates and Roles'!$A$2:$A$433),0))} -> #N/A | K27: =I27*J27 -> #N/A | L27: 0 | N27: 2 | AA27: =SUM(Table1456[[#This Row],[Program Director (IT Workflow - US)]:[Engineer (IT Workflow - US)]]) -> 0 | AO27: =SUM(Table1456[[#This Row],[Program Director (Customer and Employee Workflow - US)]:[Engineer (Customer and Employee Workflow - US)]]) -> 0 | BC27: =SUM(Table1456[[#This Row],[Program Director (IT Workflow - US)]:[Chief Architect (IT Workflow - US)]]) -> 0
C28: Execute | D28: Vulnerability Assignment Rules | E28: Document and configure vulnerability assignment rules. | F28: • <Client> understands their internal RACI matrix required to support their vulnerability response program including assignment and grouping. • Up to three (3) assignment rules will be configured. | G28: Consultant | H28: Billable - Onshore | I28: 4 | J28: {=INDEX('Client Rates and Roles'!$F$2:$F$433,MATCH(1,COUNTIFS('Opportunity Details'!$C$14,'Client Rates and Roles'!$D$2:$D$433,G28,'Client Rates and Roles'!$B$2:$B$433,H28,'Client Rates and Roles'!$C$2:$C$433,$C$6,'Client Rates and Roles'!$A$2:$A$433),0))} -> #N/A | K28: =I28*J28 -> #N/A | L28: 0 | N28: 2 | AA28: =SUM(Table1456[[#This Row],[Program Director (IT Workflow - US)]:[Engineer (IT Workflow - US)]]) -> 0 | AO28: =SUM(Table1456[[#This Row],[Program Director (Customer and Employee Workflow - US)]:[Engineer (Customer and Employee Workflow - US)]]) -> 0 | BC28: =SUM(Table1456[[#This Row],[Program Director (IT Workflow - US)]:[Chief Architect (IT Workflow - US)]]) -> 0
C29: Execute | D29: Vulnerability Grouping | E29: Document and configure vulnerability grouping rules. | F29: • Up to three (3) grouping rules will be configured. | G29: Consultant | H29: Billable - Onshore | I29: 4 | J29: {=INDEX('Client Rates and Roles'!$F$2:$F$433,MATCH(1,COUNTIFS('Opportunity Details'!$C$14,'Client Rates and Roles'!$D$2:$D$433,G29,'Client Rates and Roles'!$B$2:$B$433,H29,'Client Rates and Roles'!$C$2:$C$433,$C$6,'Client Rates and Roles'!$A$2:$A$433),0))} -> #N/A | K29: =I29*J29 -> #N/A | L29: 0 | N29: 2 | AA29: =SUM(Table1456[[#This Row],[Program Director (IT Workflow - US)]:[Engineer (IT Workflow - US)]]) -> 0 | AO29: =SUM(Table1456[[#This Row],[Program Director (Customer and Employee Workflow - US)]:[Engineer (Customer and Employee Workflow - US)]]) -> 0 | BC29: =SUM(Table1456[[#This Row],[Program Director (IT Workflow - US)]:[Chief Architect (IT Workflow - US)]]) -> 0
C30: Execute | D30: Vulnerability Risk Scoring | E30: Document CMDB and Scanner fields to be leveraged as part of risk scoring calculation. Utilize OOB functionality to develop risk score calculation. | F30: • <Client> will provide parameters that will be used for risk score calculation and ensure values are available within ServiceNow. • One (1) risk score calculation will be configured using available values using drop down configuration (non-scripted). Up to five (5) variables will be considered in the scoring logic. • CVSS environmental or temporal scoring is not used as part of the risk score calculation. | G30: Consultant | H30: Billable - Onshore | I30: 4 | J30: {=INDEX('Client Rates and Roles'!$F$2:$F$433,MATCH(1,COUNTIFS('Opportunity Details'!$C$14,'Client Rates and Roles'!$D$2:$D$433,G30,'Client Rates and Roles'!$B$2:$B$433,H30,'Client Rates and Roles'!$C$2:$C$433,$C$6,'Client Rates and Roles'!$A$2:$A$433),0))} -> #N/A | K30: =I30*J30 -> #N/A | L30: 0 | N30: 2 | AA30: =SUM(Table1456[[#This Row],[Program Director (IT Workflow - US)]:[Engineer (IT Workflow - US)]]) -> 0 | AO30: =SUM(Table1456[[#This Row],[Program Director (Customer and Employee Workflow - US)]:[Engineer (Customer and Employee Workflow - US)]]) -> 0 | BC30: =SUM(Table1456[[#This Row],[Program Director (IT Workflow - US)]:[Chief Architect (IT Workflow - US)]]) -> 0
C31: Execute | D31: Exceptions and Deferral Management | E31: Document and utilize OOTB VR exception management process. | F31: • OOTB VR exception management process using two levels of approvals will be utilized. • The Exception approval process uses the VR solution version of exception management not IRM. | G31: Consultant | H31: Billable - Onshore | I31: 4 | J31: {=INDEX('Client Rates and Roles'!$F$2:$F$433,MATCH(1,COUNTIFS('Opportunity Details'!$C$14,'Client Rates and Roles'!$D$2:$D$433,G31,'Client Rates and Roles'!$B$2:$B$433,H31,'Client Rates and Roles'!$C$2:$C$433,$C$6,'Client Rates and Roles'!$A$2:$A$433),0))} -> #N/A | K31: =I31*J31 -> #N/A | L31: 0 | N31: 2 | AA31: =SUM(Table1456[[#This Row],[Program Director (IT Workflow - US)]:[Engineer (IT Workflow - US)]]) -> 0 | AO31: =SUM(Table1456[[#This Row],[Program Director (Customer and Employee Workflow - US)]:[Engineer (Customer and Employee Workflow - US)]]) -> 0 | BC31: =SUM(Table1456[[#This Row],[Program Director (IT Workflow - US)]:[Chief Architect (IT Workflow - US)]]) -> 0
C32: Execute | D32: Change Management | E32: Document and utilize OOTB change management process. | F32: • No changes will be made to ServiceNow Change management solution. • If <Client>is currently utilizing or has made changes to the change management solution it is assumed that any changes will work with the OOTB VR solution.<Client> will be responsible for troubleshooting and resolving and issues. | G32: Consultant | H32: Billable - Onshore | I32: 4 | J32: {=INDEX('Client Rates and Roles'!$F$2:$F$433,MATCH(1,COUNTIFS('Opportunity Details'!$C$14,'Client Rates and Roles'!$D$2:$D$433,G32,'Client Rates and Roles'!$B$2:$B$433,H32,'Client Rates and Roles'!$C$2:$C$433,$C$6,'Client Rates and Roles'!$A$2:$A$433),0))} -> #N/A | K32: =I32*J32 -> #N/A | L32: 0 | N32: 2 | AA32: =SUM(Table1456[[#This Row],[Program Director (IT Workflow - US)]:[Engineer (IT Workflow - US)]]) -> 0 | AO32: =SUM(Table1456[[#This Row],[Program Director (Customer and Employee Workflow - US)]:[Engineer (Customer and Employee Workflow - US)]]) -> 0 | BC32: =SUM(Table1456[[#This Row],[Program Director (IT Workflow - US)]:[Chief Architect (IT Workflow - US)]]) -> 0
C33: Execute | D33: Notifications and SLA's | E33: Document and configure notifications and SLA's | F33: • Up to three (3) new notifications will be configured using OOTB configuration options (no scripted solution) and no custom email templates. • Up to two (2) SLA will be configured using OOTB configuration options (no scripted solution). | G33: Consultant | H33: Billable - Offshore | I33: 800 | J33: {=INDEX('Client Rates and Roles'!$F$2:$F$433,MATCH(1,COUNTIFS('Opportunity Details'!$C$14,'Client Rates and Roles'!$D$2:$D$433,G33,'Client Rates and Roles'!$B$2:$B$433,H33,'Client Rates and Roles'!$C$2:$C$433,$C$6,'Client Rates and Roles'!$A$2:$A$433),0))} -> #N/A | K33: =I33*J33 -> #N/A | L33: 0 | N33: 2 | AA33: =SUM(Table1456[[#This Row],[Program Director (IT Workflow - US)]:[Engineer (IT Workflow - US)]]) -> 0 | AO33: =SUM(Table1456[[#This Row],[Program Director (Customer and Employee Workflow - US)]:[Engineer (Customer and Employee Workflow - US)]]) -> 0 | BC33: =SUM(Table1456[[#This Row],[Program Director (IT Workflow - US)]:[Chief Architect (IT Workflow - US)]]) -> 0
C34: Execute | D34: Dashboards and Reports | E34: Review the OOB dashboards and complete minor updates to filters for the standard dashboards, as well as enable the Performance Analytics dashboards. | F34: • No new dashboards and reports will be created as part of the SIR implementation. <Client> will leverage the OOB dashboards and reports with minor tuning of filters. If licensing permits, NewRocket will enable the OOB Performance Analytics dashboards without changes. | G34: Consultant | H34: Billable - Onshore | I34: 400 | J34: {=INDEX('Client Rates and Roles'!$F$2:$F$433,MATCH(1,COUNTIFS('Opportunity Details'!$C$14,'Client Rates and Roles'!$D$2:$D$433,G34,'Client Rates and Roles'!$B$2:$B$433,H34,'Client Rates and Roles'!$C$2:$C$433,$C$6,'Client Rates and Roles'!$A$2:$A$433),0))} -> #N/A | K34: =I34*J34 -> #N/A | L34: 0 | N34: 2 | AA34: =SUM(Table1456[[#This Row],[Program Director (IT Workflow - US)]:[Engineer (IT Workflow - US)]]) -> 0 | AO34: =SUM(Table1456[[#This Row],[Program Director (Customer and Employee Workflow - US)]:[Engineer (Customer and Employee Workflow - US)]]) -> 0 | BC34: =SUM(Table1456[[#This Row],[Program Director (IT Workflow - US)]:[Chief Architect (IT Workflow - US)]]) -> 0
C35: Execute | D35: Sprint Demos | E35: Conduct end of sprint demos to show functionality. | F35: •There will be up to four (4) sprint demos and will be one (1) hour in duration per demo. | G35: Consultant | H35: Billable - Onshore | I35: 4 | J35: {=INDEX('Client Rates and Roles'!$F$2:$F$433,MATCH(1,COUNTIFS('Opportunity Details'!$C$14,'Client Rates and Roles'!$D$2:$D$433,G35,'Client Rates and Roles'!$B$2:$B$433,H35,'Client Rates and Roles'!$C$2:$C$433,$C$6,'Client Rates and Roles'!$A$2:$A$433),0))} -> #N/A | K35: =I35*J35 -> #N/A | L35: 0 | N35: 2 | AA35: =SUM(Table1456[[#This Row],[Program Director (IT Workflow - US)]:[Engineer (IT Workflow - US)]]) -> 0 | AO35: =SUM(Table1456[[#This Row],[Program Director (Customer and Employee Workflow - US)]:[Engineer (Customer and Employee Workflow - US)]]) -> 0 | BC35: =SUM(Table1456[[#This Row],[Program Director (IT Workflow - US)]:[Chief Architect (IT Workflow - US)]]) -> 0
C36: Execute | D36: Unit Testing | E36: Complete unit testing against NewRocket configured items. | G36: Consultant | H36: Billable - Onshore | I36: 4 | J36: {=INDEX('Client Rates and Roles'!$F$2:$F$433,MATCH(1,COUNTIFS('Opportunity Details'!$C$14,'Client Rates and Roles'!$D$2:$D$433,G36,'Client Rates and Roles'!$B$2:$B$433,H36,'Client Rates and Roles'!$C$2:$C$433,$C$6,'Client Rates and Roles'!$A$2:$A$433),0))} -> #N/A | K36: =I36*J36 -> #N/A | L36: 0 | N36: 2 | AA36: =SUM(Table1456[[#This Row],[Program Director (IT Workflow - US)]:[Engineer (IT Workflow - US)]]) -> 0 | AO36: =SUM(Table1456[[#This Row],[Program Director (Customer and Employee Workflow - US)]:[Engineer (Customer and Employee Workflow - US)]]) -> 0 | BC36: =SUM(Table1456[[#This Row],[Program Director (IT Workflow - US)]:[Chief Architect (IT Workflow - US)]]) -> 0
B37: DELIVER | AA37: =SUM(Table1456[[#This Row],[Program Director (IT Workflow - US)]:[Engineer (IT Workflow - US)]]) -> 0 | AO37: =SUM(Table1456[[#This Row],[Program Director (Customer and Employee Workflow - US)]:[Engineer (Customer and Employee Workflow - US)]]) -> 0
C38: Deliver | D38: UAT Environment deployment | E38: Develop a system deployment plan and support the migration of five (5) releases to the UAT environment. | F38: • NewRocket will release configured solution to the UAT environment at the end of each sprint and once at the end of UAT. • <Client> will be responsible for QA and UAT testing during the sprint cycles and provide any feedback within one (1) week of deployment to UAT. • NewRocket assumes UAT will be staffed by one resource. Additional resources will decrease the duration of UAT or will result in a Change Request. | G38: Consultant | H38: Billable - Onshore | I38: 4 | J38: {=INDEX('Client Rates and Roles'!$F$2:$F$433,MATCH(1,COUNTIFS('Opportunity Details'!$C$14,'Client Rates and Roles'!$D$2:$D$433,G38,'Client Rates and Roles'!$B$2:$B$433,H38,'Client Rates and Roles'!$C$2:$C$433,$C$6,'Client Rates and Roles'!$A$2:$A$433),0))} -> #N/A | K38: =I38*J38 -> #N/A | L38: 0 | N38: 2 | AA38: =SUM(Table1456[[#This Row],[Program Director (IT Workflow - US)]:[Engineer (IT Workflow - US)]]) -> 0 | AO38: =SUM(Table1456[[#This Row],[Program Director (Customer and Employee Workflow - US)]:[Engineer (Customer and Employee Workflow - US)]]) -> 0 | BC38: =SUM(Table1456[[#This Row],[Program Director (IT Workflow - US)]:[Chief Architect (IT Workflow - US)]]) -> 0
C39: Deliver | D39: UAT Support - Onshore | E39: Review and resolve NewRocket configuration defects during UAT testing. | F39: • NewRocket is not responsible for reviewing and resolving platform related defects. <Client>'s platform team will be responsible for raising and resolving ServiceNow defects directly with ServiceNow. | G39: Consultant - UAT | H39: Billable - Onshore | I39: =MROUND(SUMIFS(Table1456[Hours],Table1456[Project Role],"Consultant",Table1456[Billable/ Non-Billable],"Billable - Onshore",Table1456[Task],"<>UAT Support - Onshore")*0.2,4) -> 108 | J39: {=INDEX('Client Rates and Roles'!$F$2:$F$433,MATCH(1,COUNTIFS('Opportunity Details'!$C$14,'Client Rates and Roles'!$D$2:$D$433,G39,'Client Rates and Roles'!$B$2:$B$433,H39,'Client Rates and Roles'!$C$2:$C$433,$C$6,'Client Rates and Roles'!$A$2:$A$433),0))} -> #N/A | K39: =I39*J39 -> #N/A | M39: 40 | AA39: =SUM(Table1456[[#This Row],[Program Director (IT Workflow - US)]:[Engineer (IT Workflow - US)]]) -> 0 | AO39: =SUM(Table1456[[#This Row],[Program Director (Customer and Employee Workflow - US)]:[Engineer (Customer and Employee Workflow - US)]]) -> 0
C40: Deliver | D40: UAT Support - Offshore | E40: Review and resolve NewRocket configuration defects during UAT testing. | F40: • NewRocket is not responsible for reviewing and resolving platform related defects. <Client>'s platform team will be responsible for raising and resolving ServiceNow defects directly with ServiceNow. | G40: Consultant - UAT | H40: Billable - Offshore | I40: =MROUND(SUMIFS(Table1456[Hours],Table1456[Project Role],"Consultant",Table1456[Billable/ Non-Billable],"Billable - Offshore",Table1456[Task],"<>UAT Support - Onshore")*0.2,4) -> 164 | J40: {=INDEX('Client Rates and Roles'!$F$2:$F$433,MATCH(1,COUNTIFS('Opportunity Details'!$C$14,'Client Rates and Roles'!$D$2:$D$433,G40,'Client Rates and Roles'!$B$2:$B$433,H40,'Client Rates and Roles'!$C$2:$C$433,$C$6,'Client Rates and Roles'!$A$2:$A$433),0))} -> #N/A | K40: =I40*J40 -> #N/A | L40: 2 | M40: 3 | N40: 2 | AA40: =SUM(Table1456[[#This Row],[Program Director (IT Workflow - US)]:[Engineer (IT Workflow - US)]]) -> 0 | AO40: =SUM(Table1456[[#This Row],[Program Director (Customer and Employee Workflow - US)]:[Engineer (Customer and Employee Workflow - US)]]) -> 0 | BC40: =SUM(Table1456[[#This Row],[Program Director (IT Workflow - US)]:[Chief Architect (IT Workflow - US)]]) -> 0
C41: Deliver | D41: Production deployment | E41: Update the system deployment plan and support the migration of one (1) release to the Production environment. | G41: Consultant | H41: Billable - Onshore | I41: 4 | J41: {=INDEX('Client Rates and Roles'!$F$2:$F$433,MATCH(1,COUNTIFS('Opportunity Details'!$C$14,'Client Rates and Roles'!$D$2:$D$433,G41,'Client Rates and Roles'!$B$2:$B$433,H41,'Client Rates and Roles'!$C$2:$C$433,$C$6,'Client Rates and Roles'!$A$2:$A$433),0))} -> #N/A | K41: =I41*J41 -> #N/A | L41: 0 | AA41: =SUM(Table1456[[#This Row],[Program Director (IT Workflow - US)]:[Engineer (IT Workflow - US)]]) -> 0 | AO41: =SUM(Table1456[[#This Row],[Program Director (Customer and Employee Workflow - US)]:[Engineer (Customer and Employee Workflow - US)]]) -> 0 | BC41: =SUM(Table1456[[#This Row],[Program Director (IT Workflow - US)]:[Chief Architect (IT Workflow - US)]]) -> 0
C42: Deliver | D42: Documentation Updates | E42: Update the Design Approach document to capture the configured solution. | G42: Consultant | H42: Billable - Offshore | I42: 4 | J42: {=INDEX('Client Rates and Roles'!$F$2:$F$433,MATCH(1,COUNTIFS('Opportunity Details'!$C$14,'Client Rates and Roles'!$D$2:$D$433,G42,'Client Rates and Roles'!$B$2:$B$433,H42,'Client Rates and Roles'!$C$2:$C$433,$C$6,'Client Rates and Roles'!$A$2:$A$433),0))} -> #N/A | K42: =I42*J42 -> #N/A | L42: 0 | N42: 2 | AA42: =SUM(Table1456[[#This Row],[Program Director (IT Workflow - US)]:[Engineer (IT Workflow - US)]]) -> 0 | AO42: =SUM(Table1456[[#This Row],[Program Director (Customer and Employee Workflow - US)]:[Engineer (Customer and Employee Workflow - US)]]) -> 0 | BC42: =SUM(Table1456[[#This Row],[Program Director (IT Workflow - US)]:[Chief Architect (IT Workflow - US)]]) -> 0
B43: CLOSE | AA43: =SUM(Table1456[[#This Row],[Program Director (IT Workflow - US)]:[Engineer (IT Workflow - US)]]) -> 0 | AO43: =SUM(Table1456[[#This Row],[Program Director (Customer and Employee Workflow - US)]:[Engineer (Customer and Employee Workflow - US)]]) -> 0
C44: Close | D44: Technical Knowledge Transfer | E44: Conduct one (1) technical knowledge transfer session to Client's platform team prior to production deployment. This knowledge transfer session will leverage the Design Approach document, as well as the configured solution. | G44: Consultant | H44: Billable - Onshore | I44: 4 | J44: {=INDEX('Client Rates and Roles'!$F$2:$F$433,MATCH(1,COUNTIFS('Opportunity Details'!$C$14,'Client Rates and Roles'!$D$2:$D$433,G44,'Client Rates and Roles'!$B$2:$B$433,H44,'Client Rates and Roles'!$C$2:$C$433,$C$6,'Client Rates and Roles'!$A$2:$A$433),0))} -> #N/A | K44: =I44*J44 -> #N/A | L44: 0 | N44: 2 | AA44: =SUM(Table1456[[#This Row],[Program Director (IT Workflow - US)]:[Engineer (IT Workflow - US)]]) -> 0 | AO44: =SUM(Table1456[[#This Row],[Program Director (Customer and Employee Workflow - US)]:[Engineer (Customer and Employee Workflow - US)]]) -> 0 | BC44: =SUM(Table1456[[#This Row],[Program Director (IT Workflow - US)]:[Chief Architect (IT Workflow - US)]]) -> 0
C45: Close | D45: Post production support | E45: Support for two (2) weeks post-release to resolve any defects associated with NewRocket configuration. | G45: Consultant | H45: Billable - Onshore | I45: 80 | J45: {=INDEX('Client Rates and Roles'!$F$2:$F$433,MATCH(1,COUNTIFS('Opportunity Details'!$C$14,'Client Rates and Roles'!$D$2:$D$433,G45,'Client Rates and Roles'!$B$2:$B$433,H45,'Client Rates and Roles'!$C$2:$C$433,$C$6,'Client Rates and Roles'!$A$2:$A$433),0))} -> #N/A | K45: =I45*J45 -> #N/A | N45: 2 | AA45: =SUM(Table1456[[#This Row],[Program Director (IT Workflow - US)]:[Engineer (IT Workflow - US)]]) -> 0 | AO45: =SUM(Table1456[[#This Row],[Program Director (Customer and Employee Workflow - US)]:[Engineer (Customer and Employee Workflow - US)]]) -> 0 | BC45: =SUM(Table1456[[#This Row],[Program Director (IT Workflow - US)]:[Chief Architect (IT Workflow - US)]]) -> 0
C46: Close | D46: Closeout Meeting | E46: Conduct closeout meeting. Discuss feedback and next steps. | G46: Project Manager | H46: Billable - Onshore | I46: 8 | J46: {=INDEX('Client Rates and Roles'!$F$2:$F$433,MATCH(1,COUNTIFS('Opportunity Details'!$C$14,'Client Rates and Roles'!$D$2:$D$433,G46,'Client Rates and Roles'!$B$2:$B$433,H46,'Client Rates and Roles'!$C$2:$C$433,$C$6,'Client Rates and Roles'!$A$2:$A$433),0))} -> #N/A | K46: =I46*J46 -> #N/A | L46: 0 | N46: 2 | AA46: =SUM(Table1456[[#This Row],[Program Director (IT Workflow - US)]:[Engineer (IT Workflow - US)]]) -> 0 | AO46: =SUM(Table1456[[#This Row],[Program Director (Customer and Employee Workflow - US)]:[Engineer (Customer and Employee Workflow - US)]]) -> 0 | BC46: =SUM(Table1456[[#This Row],[Program Director (IT Workflow - US)]:[Chief Architect (IT Workflow - US)]]) -> 0
C47: Close | D47: CSAT Survey | E47: Send CSAT Survey | G47: Project Manager | H47: Billable - Onshore | I47: 4 | J47: {=INDEX('Client Rates and Roles'!$F$2:$F$433,MATCH(1,COUNTIFS('Opportunity Details'!$C$14,'Client Rates and Roles'!$D$2:$D$433,G47,'Client Rates and Roles'!$B$2:$B$433,H47,'Client Rates and Roles'!$C$2:$C$433,$C$6,'Client Rates and Roles'!$A$2:$A$433),0))} -> #N/A | K47: =I47*J47 -> #N/A | L47: 4 | N47: 2 | AA47: =SUM(Table1456[[#This Row],[Program Director (IT Workflow - US)]:[Engineer (IT Workflow - US)]]) -> 0 | AO47: =SUM(Table1456[[#This Row],[Program Director (Customer and Employee Workflow - US)]:[Engineer (Customer and Employee Workflow - US)]]) -> 0 | BC47: =SUM(Table1456[[#This Row],[Program Director (IT Workflow - US)]:[Chief Architect (IT Workflow - US)]]) -> 0
C48: Project Indirects | D48: Engagement Manager | E48: Ongoing program/ project oversight from an Engagement manager to report on project status, risks, issues and actions. | G48: Practice lead | H48: Billable - Onshore | I48: 4 | J48: {=INDEX('Client Rates and Roles'!$F$2:$F$433,MATCH(1,COUNTIFS('Opportunity Details'!$C$14,'Client Rates and Roles'!$D$2:$D$433,G48,'Client Rates and Roles'!$B$2:$B$433,H48,'Client Rates and Roles'!$C$2:$C$433,$C$6,'Client Rates and Roles'!$A$2:$A$433),0))} -> #N/A | K48: =I48*J48 -> #N/A | AA48: =SUM(Table1456[[#This Row],[Program Director (IT Workflow - US)]:[Engineer (IT Workflow - US)]]) -> 0 | AO48: =SUM(Table1456[[#This Row],[Program Director (Customer and Employee Workflow - US)]:[Engineer (Customer and Employee Workflow - US)]]) -> 0 | BC48: =SUM(Table1456[[#This Row],[Program Director (IT Workflow - US)]:[Chief Architect (IT Workflow - US)]]) -> 0
C49: Project Indirects | D49: Project Management | E49: Manage oversight of the project | G49: Project Manager | H49: Billable - Onshore | I49: {=MROUND(SUM((SUMIFS(Table1456[Hours],Table1456[Phase],{"Execute","Deliver","Close"}))*List!$B$25,Table1456[Additional PM Oversight]),4)} -> 412 | J49: {=INDEX('Client Rates and Roles'!$F$2:$F$433,MATCH(1,COUNTIFS('Opportunity Details'!$C$14,'Client Rates and Roles'!$D$2:$D$433,G49,'Client Rates and Roles'!$B$2:$B$433,H49,'Client Rates and Roles'!$C$2:$C$433,$C$6,'Client Rates and Roles'!$A$2:$A$433),0))} -> #N/A | K49: =I49*J49 -> #N/A | AA49: =SUM(Table1456[[#This Row],[Program Director (IT Workflow - US)]:[Engineer (IT Workflow - US)]]) -> 0 | AO49: =SUM(Table1456[[#This Row],[Program Director (Customer and Employee Workflow - US)]:[Engineer (Customer and Employee Workflow - US)]]) -> 0
C50: Project Indirects | D50: Business Analyst | E50: Business Analyst Oversight | G50: Business Analyst | H50: Billable - Onshore | I50: {=MROUND(SUM((SUMIFS(Table1456[Hours],Table1456[Phase],{"Execute","Deliver","Close"}))*List!$B$25,Table1456[Additional BA Oversight]),4)} -> 468 | J50: {=INDEX('Client Rates and Roles'!$F$2:$F$433,MATCH(1,COUNTIFS('Opportunity Details'!$C$14,'Client Rates and Roles'!$D$2:$D$433,G50,'Client Rates and Roles'!$B$2:$B$433,H50,'Client Rates and Roles'!$C$2:$C$433,$C$6,'Client Rates and Roles'!$A$2:$A$433),0))} -> #N/A | K50: =I50*J50 -> #N/A | AA50: =SUM(Table1456[[#This Row],[Program Director (IT Workflow - US)]:[Engineer (IT Workflow - US)]]) -> 0 | AO50: =SUM(Table1456[[#This Row],[Program Director (Customer and Employee Workflow - US)]:[Engineer (Customer and Employee Workflow - US)]]) -> 0
C51: Project Indirects | D51: Solution Architect | E51: Solution Architect Oversight | G51: Architect | H51: Billable - Onshore | I51: {=SUM((SUMIFS(Table1456[Hours],Table1456[Phase],{"Execute","Deliver","Close"}))*List!$B$27,Table1456[Additional SA Oversight])} -> 260.4 | J51: {=INDEX('Client Rates and Roles'!$F$2:$F$433,MATCH(1,COUNTIFS('Opportunity Details'!$C$14,'Client Rates and Roles'!$D$2:$D$433,G51,'Client Rates and Roles'!$B$2:$B$433,H51,'Client Rates and Roles'!$C$2:$C$433,$C$6,'Client Rates and Roles'!$A$2:$A$433),0))} -> #N/A | K51: =I51*J51 -> #N/A | AA51: =SUM(Table1456[[#This Row],[Program Director (IT Workflow - US)]:[Engineer (IT Workflow - US)]]) -> 0 | AO51: =SUM(Table1456[[#This Row],[Program Director (Customer and Employee Workflow - US)]:[Engineer (Customer and Employee Workflow - US)]]) -> 0 | BC51: =SUM(Table1456[[#This Row],[Program Director (IT Workflow - US)]:[Chief Architect (IT Workflow - US)]]) -> 0
C53: TOTAL HOURS | I53: =SUM(Table1456[[#All],[Hours]]) -> 2844.4
C54: TOTAL | K54: =SUM(Table1456[[#All],[Estimated Cost]]) -> #N/A
C55: ONE TIME DISCOUNT | K55: 50
C56: GRAND TOTAL | K56: =SUM(K54-K55) -> #N/A

Sheet Candace Working Notes
A1: To Do, Working Notes and Ideas:
B2: Instructions Tab - To be completed at the end.
B3: Opportunity Details - Need to review with SalesForce to avoid duplication of effort - Access Pending
B4: Opportunity Details - Need to validate currencies
B5: Opportunity Details - Need to validate contract types
B6: Opportunity Details - Need to validate if we have a select group of approved partners. Do we need a process for partner approvals?
B7: Opportunity Details - Need to confirm the list of use cases/ offerings - Validate against sales force.
B8: Opportunity Details - Review risk assessment process - Do we want to add in controls that indicate minimum requirements for mark up, governance review etc.
B9: Estimate - Add estimate for each use case once final template is agreed to
B10: Estimate - Finalize client facing roles
B11: Estimate - How do we want to handle PM, BA and Admin - Standard % that gets applied at the end?
B12: Pricing Tool - Review opportinity to integrate the pricing tool into this spreadsheet. Lock down sheet for only certain users.

Sheet INSTRUCTIONS
A1: Instructions
A2: Version 2.07
A3: Release Date: 2025-08-29
A5: 1. There are 3 quoting files in this template (Managed Services, Staff Aug/Change Order, Manticore for PS quoting with tasks), choose which one you are using.
A6: 2. If you are not using the Managed Services file, go to the MS Pricing sheet and put 0 for "Number of hours per month" and then hide the pink sheets. This will ensure the Deal review dashboard doesn't pull in the template's financials.
A7: 3. If you are not using the Staff Aug/Change Order tab, hide those purple tabs.
A8: 4. If you are not using the manticore for PS quoting with tasks, hide all blue tabs and clear out the hours in the sheets.
A9: 5. In the end, you should have the tabs visible for which you are quoting, this will help ensure Deal review reviews the correct data.
A10: 6. Now go to the respective sections and follow the instructions on the home page (1st tab) of each color coded section.

Sheet Managed Services -->
A1: Instructions
A2: Version 2.0
A3: Release Date: 2024-06-10
A5: 1. Copy this file from SharePoint and place in the Customer's Client Focus folder for this respective Opportunity/Project.
A6: 2. Select the Managed Services options and enter the # of hours per month and term, this will automatically set the resource locations.
A7: 3. Fill out the role locations on the Pricing tab.

Sheet MS - Deal Review Guidance
B6: Strategists are accountable for ensuring the deal can be delivered as written and the delivery model and scope aligns to effort and roles required. ​
B7: Standard SOW template used ​
B8: Supported modules listed​
B9: Beneficial rate and hours in table and description of services ​
B10: Check for any changes to subscription management understandings​
B11: Pricing file matches offering (roles, location, beneficial rate, margin)​
B12: Evolve entitlement sufficient to delivery project work – 300 + hrs. per/month ​
B13: Evolve scope includes initial focus and/or advisory/roadmap to initiate service ​
B14: ​
B15: Deal Desk is accountable for:​
B16: Pricing file, term, invoice schedule ++.​
B17: MSA date being added to SOW​
... B30: ​

Sheet MS Pricing
B2: NewRocket Managed Services Pricing Tool
B3: Internal Use Only
B6: Engagement Overview | O6: ="Financial Dashboard (" &G17& ")" -> Financial Dashboard (GBP)
B7: Date | P7: Total | Q7: Onsite | R7: India
B8: Preparer's Name | O8: Revenue | P8: =AL58 -> 238800 | Q8: =AM58 -> 124176 | R8: =AN58 -> 114624
B9: Practice | G9: Managed Services | O9: Cost | P9: =AO58 -> 78088.67 | Q9: =AP58 -> 68499.73 | R9: =AQ58 -> 9588.9406
B10: Capability | G10: Technology: Platform | O10: GM/GP | P10: =P8-P9 -> 160711.33 | Q10: =Q8-Q9 -> 55676.27 | R10: =R8-R9 -> 105035.06 | AA10: Minimum total CM% based on India leverage
B11: Account Name | O11: GM% | P11: =IFERROR(P10/P8,"") -> 0.67299552 | Q11: =IFERROR(Q10/Q8,"") -> 0.44836579 | R11: =IFERROR(R10/R8,"") -> 0.91634439 | AA11: =0.3125*R13^5-0.4276*R13^4+0.3734*R13^3-0.1274*R13^2+0.0669*R13+0.5 -> 0.52931793
B12: Partner | O12: Hours | P12: =IFERROR(J61,0) -> 1200 | Q12: =IFERROR(AS58+AU58,"") -> 624 | R12: =IFERROR(AT58+AV58,"") -> 576
B13: Opportunity Name | O13: Hours % | P13: =IFERROR(P12/P12,"") -> 1 | Q13: =IFERROR(Q12/P12,"") -> 0.52 | R13: =IFERROR(R12/P12,"") -> 0.48
B14: Opportunity Owner | O14: Avg Rate | P14: =IFERROR(P8/P12,"") -> 199 | Q14: =IFERROR(Q8/Q12,"") -> 199 | R14: =IFERROR(R8/R12,"") -> 199
B15: Salesforce Opportunity Number | O15: Avg Rack | P15: =IFERROR(AF58/AR58,"") -> 110.5 | Q15: =IFERROR(AG58/AS58,"") -> 154.57692 | R15: =IFERROR(AH58/AT58,"") -> 62.75
B16: Client Location | G16: UK | O16: Variance | P16: =IFERROR(P14-P15,"") -> 88.5 | Q16: =IFERROR(Q14-Q15,"") -> 44.423077 | R16: =IFERROR(R14-R15,"") -> 136.25 | AA16: Percentage for CM calculation
B17: Opportunity Currency | G17: =IFERROR(VLOOKUP(G16,'Lists (2)'!C2:D6,2),"") -> GBP | O17: Variance % | P17: =IFERROR(P16/P15,"") -> 0.80090498 | Q17: =IFERROR(Q16/Q15,"") -> 0.28738492 | R17: =IFERROR(R16/R15,"") -> 2.1713147 | AA17: 0.25
B18: Contract Type | G18: Fixed Price | O18: CM% | P18: =IFERROR(P10/P8-($AA$17),"") -> 0.42299552 | Q18: =IFERROR(Q10/Q8-($AA$17),"") -> 0.19836579 | R18: =IFERROR(R10/R8-($AA$17),"") -> 0.66634439
B19: Change Order | G19: No | AA19: Location of Resource Ration Lookup
B20: Contract Details | O20: CodeWorks Cost | R20: =IF($G$25="Yes",IF(1*($P$58*0.01)>2000,(-1*($P$58*0.01)),-2000),"0") -> -2388 | AA20: {=_xlfn.IFS($G$24="Operate",1,$G$24="Enhance",2,$G$24="Operate & Enhance",3,$G$24="Hypercare",4)} -> 3
B21: Number of Hours per month | G21: 100 | O21: Total Margin after CodeWorks | R21: =IFERROR(SUM(P10,R20)/R22,"") -> 0.66969244
B22: Number of Months | G22: 12 | O22: Total Revenue after CodeWorks | R22: =SUM(P58,R20) -> 236412
B23: Beneficial Rate | G23: 199
B24: Offering being Sold | G24: Operate & Enhance
B25: Price in CodeWorks? (override by changing value) | G25: {=_xlfn.IFS($G$24="Enhance","Yes",$G$24="Operate & Enhance","Yes",$G$24="Operate","No",$G$24="Hypercare","No")} -> Yes | O25: Guidance
B26: Notes | O26: Scott will fill this in when identified rules for margin/thresholds For Resource locations, leave as-is unless approval from Veronica to offshore more resources. If client cannot accommodate Global resourcing, you can onshore all roles if you have a necessity to do so but this will likely have a higher benefical rate requirement. For Hypercare, change the engineer to where the engineer is located on the project sold.
B27: If there are any staffing restrictions, enter them here:
B28: Notes
B31: Roles and Rates
B32: Bill Rate: Onshore/ Offshore | C32: Billing Location | D32: Resource Location (Margin) | E32: Role Name | J32: Hours | L32: Rack Bill Rate | M32: Discount or Premium | N32: Bill Rate | O32: Cost Rate | P32: Revenue | Q32: Cost | R32: GM/GP | S32: GM% | T32: Practice | U32: Skill #1 | V32: Skill #2 | W32: Skill #3 | X32: % of hours for MS | Y32: Note | AA32: India? | AB32: Advisory? | AC32: Role | AD32: Rack Bill Rate | AE32: Cost Rate | AF32: Total Revenue at Rack Rate | AG32: Onsite Revenue at Rack Rate | AH32: India Revenue at Rack Rate | AI32: Revenue w/ Contingency | AJ32: Cost w/ Contingency | AK32: One-Time Discount | AL32: Total Revenue | AM32: Onsite Revenue | AN32: India Revenue | AO32: Total Cost | AP32: Onsite Cost | AQ32: India Cost | AR32: Total Hours | AS32: Onsite Hours | AT32: India Hours | AU32: Onsite Contingency Hours | AV32: India Contingency Hours
B33: Onshore | C33: {=IFERROR(_xlfn.IFS(B33="Onshore",$G$16,B33="Offshore","India"),"")} -> UK | D33: UK | E33: MS - Architect | J33: =ROUND($G$21*$G$22*X33,0) -> 180 | L33: =IFERROR(INDEX(Bill_Rates!$L:$L,MATCH('MS Pricing'!$AD33,Bill_Rates!$J:$J,0)),"") -> 169 | M33: =$G$23-L33 -> 30 | N33: =IFERROR(L33+M33,"") -> 199 | O33: =IFERROR(INDEX(Bill_Rates!$O:$O,MATCH($AE33,Bill_Rates!$J:$J,0)),"") -> 106 | P33: =IFERROR(N33*J33,"") -> 35820 | Q33: =IFERROR((J33+K33)*O33,"") -> 19080 | R33: =IFERROR(P33-Q33,"") -> 16740 | S33: =IFERROR(R33/P33,"") -> 0.46733668 | T33: Managed Services | X33: {=INDEX('MS Lookups'!B1:E20,2,'MS Pricing'!AA20)} -> 0.15 | AB33: =IF(OR(G33="Change Management",G33="Enablement",G33="Strategy"),G33,"") | AC33: =E33 -> MS - Architect | AD33: =G$16&C33&AA33&F33&AB33&H33&E33 -> UKUKMS - Architect | AE33: =G$16&D33&H33&E33 -> UKUKMS - Architect | AF33: =IFERROR(L33*J33,"") -> 30420 | AG33: =IFERROR(AF33-AH33,"") -> 30420 | AH33: =IF(D33="India",AF33,0) -> 0 | AI33: =IFERROR(P33+P33/$P$58*$P$59,"") -> 35820 | AJ33: =IFERROR(Q33+Q33/$Q$58*$Q$59,"") -> 19080 | AK33: =IFERROR(P33/$P$58*$P$60,"") -> 0 | AL33: =IFERROR(AI33+AK33,"") -> 35820 | AM33: =IFERROR(AL33-AN33,"") -> 35820 | AN33: =IF(D33="India",AL33,0) -> 0 | AO33: =AJ33 -> 19080 | AP33: =IFERROR(AO33-AQ33,"") -> 19080 | AQ33: =IF(D33="India",AO33,0) -> 0
B34: Onshore | C34: {=IFERROR(_xlfn.IFS(B34="Onshore",$G$16,B34="Offshore","India"),"")} -> UK | D34: USA | E34: MS - Engineer | J34: =ROUND($G$21*$G$22*X34,0) -> 300 | L34: =IFERROR(INDEX(Bill_Rates!$L:$L,MATCH('MS Pricing'!$AD34,Bill_Rates!$J:$J,0)),"") -> 139 | M34: =$G$23-L34 -> 60 | N34: =IFERROR(L34+M34,"") -> 199 | O34: =IFERROR(INDEX(Bill_Rates!$O:$O,MATCH($AE34,Bill_Rates!$J:$J,0)),"") -> 107.2436 | P34: =IFERROR(N34*J34,"") -> 59700 | Q34: =IFERROR((J34+K34)*O34,"") -> 32173.08 | R34: =IFERROR(P34-Q34,"") -> 27526.92 | S34: =IFERROR(R34/P34,"") -> 0.46108744 | T34: Managed Services | X34: {=INDEX('MS Lookups'!B1:E20,3,'MS Pricing'!AA20)} -> 0.25 | AB34: =IF(OR(G34="Change Management",G34="Enablement",G34="Strategy"),G34,"") | AC34: =E34 -> MS - Engineer | AD34: =G$16&C34&AA34&F34&AB34&H34&E34 -> UKUKMS - Engineer | AE34: =G$16&D34&H34&E34 -> UKUSAMS - Engineer | AF34: =IFERROR(L34*J34,"") -> 41700 | AG34: =IFERROR(AF34-AH34,"") -> 41700 | AH34: =IF(D34="India",AF34,0) -> 0 | AI34: =IFERROR(P34+P34/$P$58*$P$59,"") -> 59700 | AJ34: =IFERROR(Q34+Q34/$Q$58*$Q$59,"") -> 32173.08 | AK34: =IFERROR(P34/$P$58*$P$60,"") -> 0 | AL34: =IFERROR(AI34+AK34,"") -> 59700 | AM34: =IFERROR(AL34-AN34,"") -> 59700 | AN34: =IF(D34="India",AL34,0) -> 0 | AO34: =AJ34 -> 32173.08 | AP34: =IFERROR(AO34-AQ34,"") -> 32173.08 | AQ34: =IF(D34="India",AO34,0) -> 0
B35: Offshore | C35: {=IFERROR(_xlfn.IFS(B35="Onshore",$G$16,B35="Offshore","India"),"")} -> India | D35: India | E35: MS - Engineer | J35: =ROUND($G$21*$G$22*X35,0) -> 360 | L35: =IFERROR(INDEX(Bill_Rates!$L:$L,MATCH('MS Pricing'!$AD35,Bill_Rates!$J:$J,0)),"") -> 65 | M35: =$G$23-L35 -> 134 | N35: =IFERROR(L35+M35,"") -> 199 | O35: =IFERROR(INDEX(Bill_Rates!$O:$O,MATCH($AE35,Bill_Rates!$J:$J,0)),"") -> 19.93979 | P35: =IFERROR(N35*J35,"") -> 71640 | Q35: =IFERROR((J35+K35)*O35,"") -> 7178.3244 | R35: =IFERROR(P35-Q35,"") -> 64461.676 | S35: =IFERROR(R35/P35,"") -> 0.89980005 | T35: Managed Services | X35: {=INDEX('MS Lookups'!B1:E20,4,'MS Pricing'!AA20)} -> 0.3 | AB35: =IF(OR(G35="Change Management",G35="Enablement",G35="Strategy"),G35,"") | AC35: =E35 -> MS - Engineer | AD35: =G$16&C35&AA35&F35&AB35&H35&E35 -> UKIndiaMS - Engineer | AE35: =G$16&D35&H35&E35 -> UKIndiaMS - Engineer | AF35: =IFERROR(L35*J35,"") -> 23400 | AG35: =IFERROR(AF35-AH35,"") -> 0 | AH35: =IF(D35="India",AF35,0) -> 23400 | AI35: =IFERROR(P35+P35/$P$58*$P$59,"") -> 71640 | AJ35: =IFERROR(Q35+Q35/$Q$58*$Q$59,"") -> 7178.3244 | AK35: =IFERROR(P35/$P$58*$P$60,"") -> 0 | AL35: =IFERROR(AI35+AK35,"") -> 71640 | AM35: =IFERROR(AL35-AN35,"") -> 0 | AN35: =IF(D35="India",AL35,0) -> 71640 | AO35: =AJ35 -> 7178.3244 | AP35: =IFERROR(AO35-AQ35,"") -> 0 | AQ35: =IF(D35="India",AO35,0) -> 7178.3244
C36: {=IFERROR(_xlfn.IFS(B36="Onshore",$G$16,B36="Offshore","India"),"")} | J36: =ROUND($G$21*$G$22*X36,0) -> 0 | L36: =IFERROR(INDEX(Bill_Rates!$L:$L,MATCH('MS Pricing'!$AD36,Bill_Rates!$J:$J,0)),"") | N36: =IFERROR(L36+M36,"") | O36: =IFERROR(INDEX(Bill_Rates!$O:$O,MATCH($AE36,Bill_Rates!$J:$J,0)),"") | P36: =IFERROR(N36*J36,"") | Q36: =IFERROR((J36+K36)*O36,"") | R36: =IFERROR(P36-Q36,"") | S36: =IFERROR(R36/P36,"") | X36: {=INDEX('MS Lookups'!B1:E20,5,'MS Pricing'!AA20)} -> 0 | AB36: =IF(OR(G36="Change Management",G36="Enablement",G36="Strategy"),G36,"") | AC36: =E36 -> 0 | AD36: =G$16&C36&AA36&F36&AB36&H36&E36 -> UK | AE36: =G$16&D36&H36&E36 -> UK | AF36: =IFERROR(L36*J36,"") | AG36: =IFERROR(AF36-AH36,"") | AH36: =IF(D36="India",AF36,0) -> 0 | AI36: =IFERROR(P36+P36/$P$58*$P$59,"") | AJ36: =IFERROR(Q36+Q36/$Q$58*$Q$59,"") | AK36: =IFERROR(P36/$P$58*$P$60,"") | AL36: =IFERROR(AI36+AK36,"") | AM36: =IFERROR(AL36-AN36,"") | AN36: =IF(D36="India",AL36,0) -> 0 | AO36: =AJ36 | AP36: =IFERROR(AO36-AQ36,"") | AQ36: =IF(D36="India",AO36,0) -> 0
B37: Onshore | C37: {=IFERROR(_xlfn.IFS(B37="Onshore",$G$16,B37="Offshore","India"),"")} -> UK | D37: USA | E37: Project Manager | J37: =ROUND($G$21*$G$22*X37,0) -> 0 | L37: =IFERROR(INDEX(Bill_Rates!$L:$L,MATCH('MS Pricing'!$AD37,Bill_Rates!$J:$J,0)),"") -> 139 | M37: =$G$23-L37 -> 60 | N37: =IFERROR(L37+M37,"") -> 199 | O37: =IFERROR(INDEX(Bill_Rates!$O:$O,MATCH($AE37,Bill_Rates!$J:$J,0)),"") -> 96.2844 | P37: =IFERROR(N37*J37,"") -> 0 | Q37: =IFERROR((J37+K37)*O37,"") -> 0 | R37: =IFERROR(P37-Q37,"") -> 0 | S37: =IFERROR(R37/P37,"") | T37: Managed Services | X37: {=INDEX('MS Lookups'!B1:E20,6,'MS Pricing'!AA20)} -> 0 | AB37: =IF(OR(G37="Change Management",G37="Enablement",G37="Strategy"),G37,"") | AC37: =E37 -> Project Manager | AD37: =G$16&C37&AA37&F37&AB37&H37&E37 -> UKUKProject Manager | AE37: =G$16&D37&H37&E37 -> UKUSAProject Manager | AF37: =IFERROR(L37*J37,"") -> 0 | AG37: =IFERROR(AF37-AH37,"") -> 0 | AH37: =IF(D37="India",AF37,0) -> 0 | AI37: =IFERROR(P37+P37/$P$58*$P$59,"") -> 0 | AJ37: =IFERROR(Q37+Q37/$Q$58*$Q$59,"") -> 0 | AK37: =IFERROR(P37/$P$58*$P$60,"") -> 0 | AL37: =IFERROR(AI37+AK37,"") -> 0 | AM37: =IFERROR(AL37-AN37,"") -> 0 | AN37: =IF(D37="India",AL37,0) -> 0 | AO37: =AJ37 -> 0 | AP37: =IFERROR(AO37-AQ37,"") -> 0 | AQ37: =IF(D37="India",AO37,0) -> 0
B38: Onshore | C38: {=IFERROR(_xlfn.IFS(B38="Onshore",$G$16,B38="Offshore","India"),"")} -> UK | D38: USA | E38: Senior Project Manager or Program Manager | J38: =ROUND($G$21*$G$22*X38,0) -> 144 | L38: =IFERROR(INDEX(Bill_Rates!$L:$L,MATCH('MS Pricing'!$AD38,Bill_Rates!$J:$J,0)),"") -> 169 | M38: =$G$23-L38 -> 30 | N38: =IFERROR(L38+M38,"") -> 199 | O38: =IFERROR(INDEX(Bill_Rates!$O:$O,MATCH($AE38,Bill_Rates!$J:$J,0)),"") -> 119.7684 | P38: =IFERROR(N38*J38,"") -> 28656 | Q38: =IFERROR((J38+K38)*O38,"") -> 17246.65 | R38: =IFERROR(P38-Q38,"") -> 11409.35 | S38: =IFERROR(R38/P38,"") -> 0.39814874 | T38: Managed Services | X38: {=INDEX('MS Lookups'!B1:E20,7,'MS Pricing'!AA20)} -> 0.12 | AB38: =IF(OR(G38="Change Management",G38="Enablement",G38="Strategy"),G38,"") | AC38: =E38 -> Senior Project Manager or Program Manager | AD38: =G$16&C38&AA38&F38&AB38&H38&E38 -> UKUKSenior Project Manager or Program Manager | AE38: =G$16&D38&H38&E38 -> UKUSASenior Project Manager or Program Manager | AF38: =IFERROR(L38*J38,"") -> 24336 | AG38: =IFERROR(AF38-AH38,"") -> 24336 | AH38: =IF(D38="India",AF38,0) -> 0 | AI38: =IFERROR(P38+P38/$P$58*$P$59,"") -> 28656 | AJ38: =IFERROR(Q38+Q38/$Q$58*$Q$59,"") -> 17246.65 | AK38: =IFERROR(P38/$P$58*$P$60,"") -> 0 | AL38: =IFERROR(AI38+AK38,"") -> 28656 | AM38: =IFERROR(AL38-AN38,"") -> 28656 | AN38: =IF(D38="India",AL38,0) -> 0 | AO38: =AJ38 -> 17246.65 | AP38: =IFERROR(AO38-AQ38,"") -> 17246.65 | AQ38: =IF(D38="India",AO38,0) -> 0
C39: {=IFERROR(_xlfn.IFS(B39="Onshore",$G$16,B39="Offshore","India"),"")} | J39: =ROUND($G$21*$G$22*X39,0) -> 0 | L39: =IFERROR(INDEX(Bill_Rates!$L:$L,MATCH('MS Pricing'!$AD39,Bill_Rates!$J:$J,0)),"") | N39: =IFERROR(L39+M39,"") | O39: =IFERROR(INDEX(Bill_Rates!$O:$O,MATCH($AE39,Bill_Rates!$J:$J,0)),"") | P39: =IFERROR(N39*J39,"") | Q39: =IFERROR((J39+K39)*O39,"") | R39: =IFERROR(P39-Q39,"") | S39: =IFERROR(R39/P39,"") | X39: {=INDEX('MS Lookups'!B1:E20,8,'MS Pricing'!AA20)} -> 0 | AB39: =IF(OR(G39="Change Management",G39="Enablement",G39="Strategy"),G39,"") | AC39: =E39 -> 0 | AD39: =G$16&C39&AA39&F39&AB39&H39&E39 -> UK | AE39: =G$16&D39&H39&E39 -> UK | AF39: =IFERROR(L39*J39,"") | AG39: =IFERROR(AF39-AH39,"") | AH39: =IF(D39="India",AF39,0) -> 0 | AI39: =IFERROR(P39+P39/$P$58*$P$59,"") | AJ39: =IFERROR(Q39+Q39/$Q$58*$Q$59,"") | AK39: =IFERROR(P39/$P$58*$P$60,"") | AL39: =IFERROR(AI39+AK39,"") | AM39: =IFERROR(AL39-AN39,"") | AN39: =IF(D39="India",AL39,0) -> 0 | AO39: =AJ39 | AP39: =IFERROR(AO39-AQ39,"") | AQ39: =IF(D39="India",AO39,0) -> 0
B40: Offshore | C40: {=IFERROR(_xlfn.IFS(B40="Onshore",$G$16,B40="Offshore","India"),"")} -> India | D40: India | E40: MS - Platform Analyst | J40: =ROUND($G$21*$G$22*X40,0) -> 216 | L40: =IFERROR(INDEX(Bill_Rates!$L:$L,MATCH('MS Pricing'!$AD40,Bill_Rates!$J:$J,0)),"") -> 59 | M40: =$G$23-L40 -> 140 | N40: =IFERROR(L40+M40,"") -> 199 | O40: =IFERROR(INDEX(Bill_Rates!$O:$O,MATCH($AE40,Bill_Rates!$J:$J,0)),"") -> 11.16026 | P40: =IFERROR(N40*J40,"") -> 42984 | Q40: =IFERROR((J40+K40)*O40,"") -> 2410.6162 | R40: =IFERROR(P40-Q40,"") -> 40573.384 | S40: =IFERROR(R40/P40,"") -> 0.94391829 | T40: Managed Services | X40: {=INDEX('MS Lookups'!B1:E20,9,'MS Pricing'!AA20)} -> 0.18 | AB40: =IF(OR(G40="Change Management",G40="Enablement",G40="Strategy"),G40,"") | AC40: =E40 -> MS - Platform Analyst | AD40: =G$16&C40&AA40&F40&AB40&H40&E40 -> UKIndiaMS - Platform Analyst | AE40: =G$16&D40&H40&E40 -> UKIndiaMS - Platform Analyst | AF40: =IFERROR(L40*J40,"") -> 12744 | AG40: =IFERROR(AF40-AH40,"") -> 0 | AH40: =IF(D40="India",AF40,0) -> 12744 | AI40: =IFERROR(P40+P40/$P$58*$P$59,"") -> 42984 | AJ40: =IFERROR(Q40+Q40/$Q$58*$Q$59,"") -> 2410.6162 | AK40: =IFERROR(P40/$P$58*$P$60,"") -> 0 | AL40: =IFERROR(AI40+AK40,"") -> 42984 | AM40: =IFERROR(AL40-AN40,"") -> 0 | AN40: =IF(D40="India",AL40,0) -> 42984 | AO40: =AJ40 -> 2410.6162 | AP40: =IFERROR(AO40-AQ40,"") -> 0 | AQ40: =IF(D40="India",AO40,0) -> 2410.6162
C41: {=IFERROR(_xlfn.IFS(B41="Onshore",$G$16,B41="Offshore","India"),"")} | L41: =IFERROR(INDEX(Bill_Rates!$L:$L,MATCH('MS Pricing'!$AD41,Bill_Rates!$J:$J,0)),"") | N41: =IFERROR(L41+M41,"") | O41: =IFERROR(INDEX(Bill_Rates!$O:$O,MATCH($AE41,Bill_Rates!$J:$J,0)),"") | P41: =IFERROR(N41*J41,"") | Q41: =IFERROR((J41+K41)*O41,"") | R41: =IFERROR(P41-Q41,"") | S41: =IFERROR(R41/P41,"") | AB41: =IF(OR(G41="Change Management",G41="Enablement",G41="Strategy"),G41,"") | AC41: =E41 -> 0 | AD41: =G$16&C41&AA41&F41&AB41&H41&E41 -> UK | AE41: =G$16&D41&H41&E41 -> UK | AF41: =IFERROR(L41*J41,"") | AG41: =IFERROR(AF41-AH41,"") | AH41: =IF(D41="India",AF41,0) -> 0 | AI41: =IFERROR(P41+P41/$P$58*$P$59,"") | AJ41: =IFERROR(Q41+Q41/$Q$58*$Q$59,"") | AK41: =IFERROR(P41/$P$58*$P$60,"") | AL41: =IFERROR(AI41+AK41,"") | AM41: =IFERROR(AL41-AN41,"") | AN41: =IF(D41="India",AL41,0) -> 0 | AO41: =AJ41 | AP41: =IFERROR(AO41-AQ41,"") | AQ41: =IF(D41="India",AO41,0) -> 0
C42: {=IFERROR(_xlfn.IFS(B42="Onshore",$G$16,B42="Offshore","India"),"")} | L42: =IFERROR(INDEX(Bill_Rates!$L:$L,MATCH('MS Pricing'!$AD42,Bill_Rates!$J:$J,0)),"") | N42: =IFERROR(L42+M42,"") | O42: =IFERROR(INDEX(Bill_Rates!$O:$O,MATCH($AE42,Bill_Rates!$J:$J,0)),"") | P42: =IFERROR(N42*J42,"") | Q42: =IFERROR((J42+K42)*O42,"") | R42: =IFERROR(P42-Q42,"") | S42: =IFERROR(R42/P42,"") | AB42: =IF(OR(G42="Change Management",G42="Enablement",G42="Strategy"),G42,"") | AC42: =E42 -> 0 | AD42: =G$16&C42&AA42&F42&AB42&H42&E42 -> UK | AE42: =G$16&D42&H42&E42 -> UK | AF42: =IFERROR(L42*J42,"") | AG42: =IFERROR(AF42-AH42,"") | AH42: =IF(D42="India",AF42,0) -> 0 | AI42: =IFERROR(P42+P42/$P$58*$P$59,"") | AJ42: =IFERROR(Q42+Q42/$Q$58*$Q$59,"") | AK42: =IFERROR(P42/$P$58*$P$60,"") | AL42: =IFERROR(AI42+AK42,"") | AM42: =IFERROR(AL42-AN42,"") | AN42: =IF(D42="India",AL42,0) -> 0 | AO42: =AJ42 | AP42: =IFERROR(AO42-AQ42,"") | AQ42: =IF(D42="India",AO42,0) -> 0
C43: {=IFERROR(_xlfn.IFS(B43="Onshore",$G$16,B43="Offshore","India"),"")} | L43: =IFERROR(INDEX(Bill_Rates!$L:$L,MATCH('MS Pricing'!$AD43,Bill_Rates!$J:$J,0)),"") | N43: =IFERROR(L43+M43,"") | O43: =IFERROR(INDEX(Bill_Rates!$O:$O,MATCH($AE43,Bill_Rates!$J:$J,0)),"") | P43: =IFERROR(N43*J43,"") | Q43: =IFERROR((J43+K43)*O43,"") | R43: =IFERROR(P43-Q43,"") | S43: =IFERROR(R43/P43,"") | AB43: =IF(OR(G43="Change Management",G43="Enablement",G43="Strategy"),G43,"") | AC43: =E43 -> 0 | AD43: =G$16&C43&AA43&F43&AB43&H43&E43 -> UK | AE43: =G$16&D43&H43&E43 -> UK | AF43: =IFERROR(L43*J43,"") | AG43: =IFERROR(AF43-AH43,"") | AH43: =IF(D43="India",AF43,0) -> 0 | AI43: =IFERROR(P43+P43/$P$58*$P$59,"") | AJ43: =IFERROR(Q43+Q43/$Q$58*$Q$59,"") | AK43: =IFERROR(P43/$P$58*$P$60,"") | AL43: =IFERROR(AI43+AK43,"") | AM43: =IFERROR(AL43-AN43,"") | AN43: =IF(D43="India",AL43,0) -> 0 | AO43: =AJ43 | AP43: =IFERROR(AO43-AQ43,"") | AQ43: =IF(D43="India",AO43,0) -> 0
C44: {=IFERROR(_xlfn.IFS(B44="Onshore",$G$16,B44="Offshore","India"),"")} | L44: =IFERROR(INDEX(Bill_Rates!$L:$L,MATCH('MS Pricing'!$AD44,Bill_Rates!$J:$J,0)),"") | N44: =IFERROR(L44+M44,"") | O44: =IFERROR(INDEX(Bill_Rates!$O:$O,MATCH($AE44,Bill_Rates!$J:$J,0)),"") | P44: =IFERROR(N44*J44,"") | Q44: =IFERROR((J44+K44)*O44,"") | R44: =IFERROR(P44-Q44,"") | S44: =IFERROR(R44/P44,"") | AB44: =IF(OR(G44="Change Management",G44="Enablement",G44="Strategy"),G44,"") | AC44: =E44 -> 0 | AD44: =G$16&C44&AA44&F44&AB44&H44&E44 -> UK | AE44: =G$16&D44&H44&E44 -> UK | AF44: =IFERROR(L44*J44,"") | AG44: =IFERROR(AF44-AH44,"") | AH44: =IF(D44="India",AF44,0) -> 0 | AI44: =IFERROR(P44+P44/$P$58*$P$59,"") | AJ44: =IFERROR(Q44+Q44/$Q$58*$Q$59,"") | AK44: =IFERROR(P44/$P$58*$P$60,"") | AL44: =IFERROR(AI44+AK44,"") | AM44: =IFERROR(AL44-AN44,"") | AN44: =IF(D44="India",AL44,0) -> 0 | AO44: =AJ44 | AP44: =IFERROR(AO44-AQ44,"") | AQ44: =IF(D44="India",AO44,0) -> 0
C45: {=IFERROR(_xlfn.IFS(B45="Onshore",$G$16,B45="Offshore","India"),"")} | L45: =IFERROR(INDEX(Bill_Rates!$L:$L,MATCH('MS Pricing'!$AD45,Bill_Rates!$J:$J,0)),"") | N45: =IFERROR(L45+M45,"") | O45: =IFERROR(INDEX(Bill_Rates!$O:$O,MATCH($AE45,Bill_Rates!$J:$J,0)),"") | P45: =IFERROR(N45*J45,"") | Q45: =IFERROR((J45+K45)*O45,"") | R45: =IFERROR(P45-Q45,"") | S45: =IFERROR(R45/P45,"") | AB45: =IF(OR(G45="Change Management",G45="Enablement",G45="Strategy"),G45,"") | AC45: =E45 -> 0 | AD45: =G$16&C45&AA45&F45&AB45&H45&E45 -> UK | AE45: =G$16&D45&H45&E45 -> UK | AF45: =IFERROR(L45*J45,"") | AG45: =IFERROR(AF45-AH45,"") | AH45: =IF(D45="India",AF45,0) -> 0 | AI45: =IFERROR(P45+P45/$P$58*$P$59,"") | AJ45: =IFERROR(Q45+Q45/$Q$58*$Q$59,"") | AK45: =IFERROR(P45/$P$58*$P$60,"") | AL45: =IFERROR(AI45+AK45,"") | AM45: =IFERROR(AL45-AN45,"") | AN45: =IF(D45="India",AL45,0) -> 0 | AO45: =AJ45 | AP45: =IFERROR(AO45-AQ45,"") | AQ45: =IF(D45="India",AO45,0) -> 0
C46: {=IFERROR(_xlfn.IFS(B46="Onshore",$G$16,B46="Offshore","India"),"")} | L46: =IFERROR(INDEX(Bill_Rates!$L:$L,MATCH('MS Pricing'!$AD46,Bill_Rates!$J:$J,0)),"") | N46: =IFERROR(L46+M46,"") | O46: =IFERROR(INDEX(Bill_Rates!$O:$O,MATCH($AE46,Bill_Rates!$J:$J,0)),"") | P46: =IFERROR(N46*J46,"") | Q46: =IFERROR((J46+K46)*O46,"") | R46: =IFERROR(P46-Q46,"") | S46: =IFERROR(R46/P46,"") | AB46: =IF(OR(G46="Change Management",G46="Enablement",G46="Strategy"),G46,"") | AC46: =E46 -> 0 | AD46: =G$16&C46&AA46&F46&AB46&H46&E46 -> UK | AE46: =G$16&D46&H46&E46 -> UK | AF46: =IFERROR(L46*J46,"") | AG46: =IFERROR(AF46-AH46,"") | AH46: =IF(D46="India",AF46,0) -> 0 | AI46: =IFERROR(P46+P46/$P$58*$P$59,"") | AJ46: =IFERROR(Q46+Q46/$Q$58*$Q$59,"") | AK46: =IFERROR(P46/$P$58*$P$60,"") | AL46: =IFERROR(AI46+AK46,"") | AM46: =IFERROR(AL46-AN46,"") | AN46: =IF(D46="India",AL46,0) -> 0 | AO46: =AJ46 | AP46: =IFERROR(AO46-AQ46,"") | AQ46: =IF(D46="India",AO46,0) -> 0
C47: {=IFERROR(_xlfn.IFS(B47="Onshore",$G$16,B47="Offshore","India"),"")} | L47: =IFERROR(INDEX(Bill_Rates!$L:$L,MATCH('MS Pricing'!$AD47,Bill_Rates!$J:$J,0)),"") | N47: =IFERROR(L47+M47,"") | O47: =IFERROR(INDEX(Bill_Rates!$O:$O,MATCH($AE47,Bill_Rates!$J:$J,0)),"") | P47: =IFERROR(N47*J47,"") | Q47: =IFERROR((J47+K47)*O47,"") | R47: =IFERROR(P47-Q47,"") | S47: =IFERROR(R47/P47,"") | AB47: =IF(OR(G47="Change Management",G47="Enablement",G47="Strategy"),G47,"") | AC47: =E47 -> 0 | AD47: =G$16&C47&AA47&F47&AB47&H47&E47 -> UK | AE47: =G$16&D47&H47&E47 -> UK | AF47: =IFERROR(L47*J47,"") | AG47: =IFERROR(AF47-AH47,"") | AH47: =IF(D47="India",AF47,0) -> 0 | AI47: =IFERROR(P47+P47/$P$58*$P$59,"") | AJ47: =IFERROR(Q47+Q47/$Q$58*$Q$59,"") | AK47: =IFERROR(P47/$P$58*$P$60,"") | AL47: =IFERROR(AI47+AK47,"") | AM47: =IFERROR(AL47-AN47,"") | AN47: =IF(D47="India",AL47,0) -> 0 | AO47: =AJ47 | AP47: =IFERROR(AO47-AQ47,"") | AQ47: =IF(D47="India",AO47,0) -> 0
C48: {=IFERROR(_xlfn.IFS(B48="Onshore",$G$16,B48="Offshore","India"),"")} | L48: =IFERROR(INDEX(Bill_Rates!$L:$L,MATCH('MS Pricing'!$AD48,Bill_Rates!$J:$J,0)),"") | N48: =IFERROR(L48+M48,"") | O48: =IFERROR(INDEX(Bill_Rates!$O:$O,MATCH($AE48,Bill_Rates!$J:$J,0)),"") | P48: =IFERROR(N48*J48,"") | Q48: =IFERROR((J48+K48)*O48,"") | R48: =IFERROR(P48-Q48,"") | S48: =IFERROR(R48/P48,"") | AB48: =IF(OR(G48="Change Management",G48="Enablement",G48="Strategy"),G48,"") | AC48: =E48 -> 0 | AD48: =G$16&C48&AA48&F48&AB48&H48&E48 -> UK | AE48: =G$16&D48&H48&E48 -> UK | AF48: =IFERROR(L48*J48,"") | AG48: =IFERROR(AF48-AH48,"") | AH48: =IF(D48="India",AF48,0) -> 0 | AI48: =IFERROR(P48+P48/$P$58*$P$59,"") | AJ48: =IFERROR(Q48+Q48/$Q$58*$Q$59,"") | AK48: =IFERROR(P48/$P$58*$P$60,"") | AL48: =IFERROR(AI48+AK48,"") | AM48: =IFERROR(AL48-AN48,"") | AN48: =IF(D48="India",AL48,0) -> 0 | AO48: =AJ48 | AP48: =IFERROR(AO48-AQ48,"") | AQ48: =IF(D48="India",AO48,0) -> 0
C49: {=IFERROR(_xlfn.IFS(B49="Onshore",$G$16,B49="Offshore","India"),"")} | L49: =IFERROR(INDEX(Bill_Rates!$L:$L,MATCH('MS Pricing'!$AD49,Bill_Rates!$J:$J,0)),"") | N49: =IFERROR(L49+M49,"") | O49: =IFERROR(INDEX(Bill_Rates!$O:$O,MATCH($AE49,Bill_Rates!$J:$J,0)),"") | P49: =IFERROR(N49*J49,"") | Q49: =IFERROR((J49+K49)*O49,"") | R49: =IFERROR(P49-Q49,"") | S49: =IFERROR(R49/P49,"") | AB49: =IF(OR(G49="Change Management",G49="Enablement",G49="Strategy"),G49,"") | AC49: =E49 -> 0 | AD49: =G$16&C49&AA49&F49&AB49&H49&E49 -> UK | AE49: =G$16&D49&H49&E49 -> UK | AF49: =IFERROR(L49*J49,"") | AG49: =IFERROR(AF49-AH49,"") | AH49: =IF(D49="India",AF49,0) -> 0 | AI49: =IFERROR(P49+P49/$P$58*$P$59,"") | AJ49: =IFERROR(Q49+Q49/$Q$58*$Q$59,"") | AK49: =IFERROR(P49/$P$58*$P$60,"") | AL49: =IFERROR(AI49+AK49,"") | AM49: =IFERROR(AL49-AN49,"") | AN49: =IF(D49="India",AL49,0) -> 0 | AO49: =AJ49 | AP49: =IFERROR(AO49-AQ49,"") | AQ49: =IF(D49="India",AO49,0) -> 0
C50: {=IFERROR(_xlfn.IFS(B50="Onshore",$G$16,B50="Offshore","India"),"")} | L50: =IFERROR(INDEX(Bill_Rates!$L:$L,MATCH('MS Pricing'!$AD50,Bill_Rates!$J:$J,0)),"") | N50: =IFERROR(L50+M50,"") | O50: =IFERROR(INDEX(Bill_Rates!$O:$O,MATCH($AE50,Bill_Rates!$J:$J,0)),"") | P50: =IFERROR(N50*J50,"") | Q50: =IFERROR((J50+K50)*O50,"") | R50: =IFERROR(P50-Q50,"") | S50: =IFERROR(R50/P50,"") | AB50: =IF(OR(G50="Change Management",G50="Enablement",G50="Strategy"),G50,"") | AC50: =E50 -> 0 | AD50: =G$16&C50&AA50&F50&AB50&H50&E50 -> UK | AE50: =G$16&D50&H50&E50 -> UK | AF50: =IFERROR(L50*J50,"") | AG50: =IFERROR(AF50-AH50,"") | AH50: =IF(D50="India",AF50,0) -> 0 | AI50: =IFERROR(P50+P50/$P$58*$P$59,"") | AJ50: =IFERROR(Q50+Q50/$Q$58*$Q$59,"") | AK50: =IFERROR(P50/$P$58*$P$60,"") | AL50: =IFERROR(AI50+AK50,"") | AM50: =IFERROR(AL50-AN50,"") | AN50: =IF(D50="India",AL50,0) -> 0 | AO50: =AJ50 | AP50: =IFERROR(AO50-AQ50,"") | AQ50: =IF(D50="India",AO50,0) -> 0
C51: {=IFERROR(_xlfn.IFS(B51="Onshore",$G$16,B51="Offshore","India"),"")} | L51: =IFERROR(INDEX(Bill_Rates!$L:$L,MATCH('MS Pricing'!$AD51,Bill_Rates!$J:$J,0)),"") | N51: =IFERROR(L51+M51,"") | O51: =IFERROR(INDEX(Bill_Rates!$O:$O,MATCH($AE51,Bill_Rates!$J:$J,0)),"") | P51: =IFERROR(N51*J51,"") | Q51: =IFERROR((J51+K51)*O51,"") | R51: =IFERROR(P51-Q51,"") | S51: =IFERROR(R51/P51,"") | AB51: =IF(OR(G51="Change Management",G51="Enablement",G51="Strategy"),G51,"") | AC51: =E51 -> 0 | AD51: =G$16&C51&AA51&F51&AB51&H51&E51 -> UK | AE51: =G$16&D51&H51&E51 -> UK | AF51: =IFERROR(L51*J51,"") | AG51: =IFERROR(AF51-AH51,"") | AH51: =IF(D51="India",AF51,0) -> 0 | AI51: =IFERROR(P51+P51/$P$58*$P$59,"") | AJ51: =IFERROR(Q51+Q51/$Q$58*$Q$59,"") | AK51: =IFERROR(P51/$P$58*$P$60,"") | AL51: =IFERROR(AI51+AK51,"") | AM51: =IFERROR(AL51-AN51,"") | AN51: =IF(D51="India",AL51,0) -> 0 | AO51: =AJ51 | AP51: =IFERROR(AO51-AQ51,"") | AQ51: =IF(D51="India",AO51,0) -> 0
C52: {=IFERROR(_xlfn.IFS(B52="Onshore",$G$16,B52="Offshore","India"),"")} | L52: =IFERROR(INDEX(Bill_Rates!$L:$L,MATCH('MS Pricing'!$AD52,Bill_Rates!$J:$J,0)),"") | N52: =IFERROR(L52+M52,"") | O52: =IFERROR(INDEX(Bill_Rates!$O:$O,MATCH($AE52,Bill_Rates!$J:$J,0)),"") | P52: =IFERROR(N52*J52,"") | Q52: =IFERROR((J52+K52)*O52,"") | R52: =IFERROR(P52-Q52,"") | S52: =IFERROR(R52/P52,"") | AB52: =IF(OR(G52="Change Management",G52="Enablement",G52="Strategy"),G52,"") | AC52: =E52 -> 0 | AD52: =G$16&C52&AA52&F52&AB52&H52&E52 -> UK | AE52: =G$16&D52&H52&E52 -> UK | AF52: =IFERROR(L52*J52,"") | AG52: =IFERROR(AF52-AH52,"") | AH52: =IF(D52="India",AF52,0) -> 0 | AI52: =IFERROR(P52+P52/$P$58*$P$59,"") | AJ52: =IFERROR(Q52+Q52/$Q$58*$Q$59,"") | AK52: =IFERROR(P52/$P$58*$P$60,"") | AL52: =IFERROR(AI52+AK52,"") | AM52: =IFERROR(AL52-AN52,"") | AN52: =IF(D52="India",AL52,0) -> 0 | AO52: =AJ52 | AP52: =IFERROR(AO52-AQ52,"") | AQ52: =IF(D52="India",AO52,0) -> 0
... C57: {=IFERROR(_xlfn.IFS(B57="Onshore",$G$16,B57="Offshore","India"),"")} | L57: =IFERROR(INDEX(Bill_Rates!$L:$L,MATCH('MS Pricing'!$AD57,Bill_Rates!$J:$J,0)),"") | N57: =IFERROR(L57+M57,"") | O57: =IFERROR(INDEX(Bill_Rates!$O:$O,MATCH($AE57,Bill_Rates!$J:$J,0)),"") | P57: =IFERROR(N57*J57,"") | Q57: =IFERROR((J57+K57)*O57,"") | R57: =IFERROR(P57-Q57,"") | S57: =IFERROR(R57/P57,"") | AB57: =IF(OR(G57="Change Management",G57="Enablement",G57="Strategy"),G57,"") | AC57: =E57 -> 0 | AD57: =G$16&C57&AA57&F57&AB57&H57&E57 -> UK | AE57: =G$16&D57&H57&E57 -> UK | AF57: =IFERROR(L57*J57,"") | AG57: =IFERROR(AF57-AH57,"") | AH57: =IF(D57="India",AF57,0) -> 0 | AI57: =IFERROR(P57+P57/$P$58*$P$59,"") | AJ57: =IFERROR(Q57+Q57/$Q$58*$Q$59,"") | AK57: =IFERROR(P57/$P$58*$P$60,"") | AL57: =IFERROR(AI57+AK57,"") | AM57: =IFERROR(AL57-AN57,"") | AN57: =IF(D57="India",AL57,0) -> 0 | AO57: =AJ57 | AP57: =IFERROR(AO57-AQ57,"") | AQ57: =IF(D57="India",AO57,0) -> 0
C58: Subtotal | J58: =SUM(J33:J57) -> 1200 | P58: =SUM(P33:P57) -> 238800 | Q58: =SUM(Q33:Q57) -> 78088.67 | R58: =SUM(R33:R57) -> 160711.33 | S58: =IFERROR(R58/P58,"") -> 0.67299552 | AA58: =IF(C33="India","India","") | AB58: =F58&G58 | AF58: =SUM(AF33:AF57) -> 132600 | AG58: =SUM(AG33:AG57) -> 96456 | AH58: =SUM(AH33:AH57) -> 36144 | AI58: =SUM(AI33:AI57) -> 238800 | AJ58: =SUM(AJ33:AJ57) -> 78088.67 | AK58: =SUM(AK33:AK57) -> 0 | AL58: =SUM(AL33:AL57) -> 238800 | AM58: =SUM(AM33:AM57) -> 124176 | ... AQ58: =SUM(AQ33:AQ57) -> 9588.9406 | AR58: =J58 -> 1200 | AS58: =AR58-AT58 -> 624 | AT58: =SUMIF(D33:D57,"India",J33:J57) -> 576 | AU58: =AS58/AR58*J59 -> 0 | AV58: =AT58/AR58*J59 -> 0
C59: Contingency (for fixed-price only) | J59: =IFERROR(P59/(P58/J58),"") -> 0 | Q59: =IFERROR(P59*(1-S58),"") -> 0 | R59: =IFERROR(P59-Q59,"") -> 0 | S59: =IFERROR(R59/P59,"")
C60: One-time discount
B61: Total | J61: =IFERROR(J58+J59,"") -> 1200 | P61: =SUM(P58:P60) -> 238800 | Q61: =SUM(Q58:Q59) -> 78088.67 | R61: =P61-Q61 -> 160711.33 | S61: =IFERROR(R61/P61,"") -> 0.67299552
B64: Deal Review Questions
B65: What percentage of TCV will be invoiced upon SOW signature? | AA65: Note:
B66: Is there any restriction to using global delivery on this project? | J66: If yes, then explain: | AA66: Bill rate is based on client location, whether the resource is in India or not.
B67: What is the primary client delivery location? | AA67: Cost rate is based on billing location, resource location and resource.
B68: Is our proposal or SOW solution-based with defined scope and deliverables? | J68: If no, then engagement type:
B69: Are any specialized skills, including security clearances, required to deliver the project? | J69: If yes, then list skills:
B70: Have we successfully delivered this type of project previously? Do we have assumptions to mitigate any substantial risks?
B71: Are any of the standard SOW terms and conditions to be modified? | J71: If yes, then list modifications:
B72: If any fields in this Pricing Tool are highlighted in red, then provide reason(s).
B73: Will any NewRocket product licenses be included as part of this opportunity? | J73: If yes, then list products: | O73: Term (years): | Q73: Price per yr:
B74: Notes
D78: Account | F78: =G11 -> 0
D79: Practice | F79: =G9 -> Managed Services
D80: Opportunity Owner | F80: =G14 -> 0
D81: Client Location | F81: =G16 -> UK
D82: Change Order | F82: =G19 -> No
D83: Currency | F83: =G17 -> GBP
D84: TCV | F84: =P8 -> 238800
D85: CM% | F85: =P11 -> 0.67299552
D86: Avg Rate | F86: =P14 -> 199
D87: Rate discount | F87: =IFERROR(-P17,"") -> -0.80090498
D88: Pre-payment | F88: =I65 -> 0
D89: India Restriction | F89: =I66 -> 0
D90: India Hours | F90: =R13 -> 0.48

Sheet MS Lookups
A1: Role | B1: Operate | C1: Enhance | D1: Operate & Enhance | E1: Hypercare
A2: MS - Architect | B2: 0.1 | C2: 0.15 | D2: 0.15 | E2: 0.15
A3: MS - Engineer | B3: 0.1 | C3: 0.2 | D3: 0.25 | E3: 0.5
A4: MS - Engineer | B4: 0 | C4: 0.5 | D4: 0.3
A6: Project Manager | B6: 0.15 | C6: 0 | D6: 0
A7: Senior Project Manager or Program Manager | B7: 0 | C7: 0.15 | D7: 0.12 | E7: 0.15
A9: MS - Platform Analyst | B9: 0.65 | C9: 0 | D9: 0.18 | E9: 0.2
A11: Total | B11: =SUM(B2:B9) -> 1 | C11: =SUM(C2:C9) -> 1 | D11: =SUM(D2:D9) -> 1 | E11: =SUM(E2:E9) -> 1
B13: As of 6/19 the Operate changed to the new structure of adding more hours to the Analyst vs Engineer.
B34: References below from pricing files taken June 4th, 2024
B37: Operate
B38: Resource Location | C38: Practice | D38: Community | E38: Grade | F38: Role | G38: Hours | H38: Rack Bill Rate | I38: Discount or Premium | J38: Bill Rate | K38: Cost Rate | L38: Revenue | M38: Cost | N38: CM | O38: CM% | P38: Note
B39: India | C39: Managed Services | D39: Platform | E39: B - Staff | F39: Platform Administrator | G39: 210 | H39: 79 | I39: 66 | J39: 145 | K39: 12.61872 | L39: 30450 | M39: 2649.9312 | N39: 27800.069 | O39: 0.91297434 | P39: 0.35
B40: India | C40: Managed Services | D40: Engineering | E40: C - Senior | F40: Senior Engineer | G40: 240 | H40: 89 | I40: 56 | J40: 145 | K40: 18.40992 | L40: 34800 | M40: 4418.3808 | N40: 30381.619 | O40: 0.87303503 | P40: 0.4
B41: USA | C41: Managed Services | D41: Architecture | E41: D - Lead | F41: Lead Architect | G41: 60 | H41: 259 | I41: -114 | J41: 145 | K41: 115 | L41: 8700 | M41: 6900 | N41: 1800 | O41: 0.20689655 | P41: 0.1
B42: USA | C42: PMO | D42: Delivery Management | E42: C - Senior | F42: Project Manager | G42: 90 | H42: 219 | I42: -74 | J42: 145 | K42: 100 | L42: 13050 | M42: 9000 | N42: 4050 | O42: 0.31034483 | P42: 0.15
B46: Hypercare
B47: USA | C47: Managed Services | D47: Engineering | E47: C - Senior | F47: Senior Engineer | G47: 75 | H47: 219 | I47: -20 | J47: 199 | K47: 100 | L47: 14925 | M47: 7500 | N47: 7425 | O47: 0.49748744 | P47: 0.5
B48: USA | C48: Managed Services | D48: Architecture | E48: D - Lead | F48: Lead Architect | G48: 22.5 | H48: 259 | I48: -60 | J48: 199 | K48: 115 | L48: 4477.5 | M48: 2587.5 | N48: 1890 | O48: 0.42211055 | P48: 0.15
B49: USA | C49: PMO | D49: Delivery Management | E49: D - Lead | F49: Senior Project Manager or Program Manager | G49: 22.5 | H49: 259 | I49: -60 | J49: 199 | K49: 115 | L49: 4477.5 | M49: 2587.5 | N49: 1890 | O49: 0.42211055 | P49: 0.15
B50: India | C50: Managed Services | D50: Platform | E50: B - Staff | F50: Platform Administrator | G50: 30 | H50: 79 | I50: 120 | J50: 199 | K50: 12.61872 | L50: 5970 | M50: 378.5616 | N50: 5591.4384 | O50: 0.93658935 | P50: 0.2
B54: Operate & Enhance
B55: USA | C55: Managed Services | D55: Engineering | E55: C - Senior | F55: Senior Engineer | G55: 60 | H55: 219 | I55: -20 | J55: 199 | K55: 100 | L55: 11940 | M55: 6000 | N55: 5940 | O55: 0.49748744 | P55: 0.1
B56: India | C56: Managed Services | D56: Engineering | E56: C - Senior | F56: Senior Engineer | G56: 228 | H56: 89 | I56: 110 | J56: 199 | K56: 18.40992 | L56: 45372 | M56: 4197.4618 | N56: 41174.538 | O56: 0.90748784 | P56: 0.38
B57: USA | C57: Managed Services | D57: Architecture | E57: D - Lead | F57: Lead Architect | G57: 90 | H57: 259 | I57: -60 | J57: 199 | K57: 115 | L57: 17910 | M57: 10350 | N57: 7560 | O57: 0.42211055 | P57: 0.15
B58: USA | C58: PMO | D58: Delivery Management | E58: D - Lead | F58: Senior Project Manager or Program Manager | G58: 72 | H58: 259 | I58: -60 | J58: 199 | K58: 115 | L58: 14328 | M58: 8280 | N58: 6048 | O58: 0.42211055 | P58: 0.12
B60: India | C60: Managed Services | D60: Platform | E60: B - Staff | F60: Platform Administrator | G60: 150 | H60: 79 | I60: 120 | J60: 199 | K60: 12.61872 | L60: 29850 | M60: 1892.808 | N60: 27957.192 | O60: 0.93658935 | P60: 0.25
B63: Enhance
B64: USA | C64: Managed Services | D64: Engineering | E64: C - Senior | F64: Senior Engineer | G64: 120 | H64: 219 | I64: -20 | J64: 199 | K64: 100 | L64: 23880 | M64: 12000 | N64: 11880 | O64: 0.5 | P64: 0.2
B65: India | C65: Managed Services | D65: Engineering | E65: C - Senior | F65: Senior Engineer | G65: 300 | H65: 89 | I65: 110 | J65: 199 | K65: 18.41 | L65: 59700 | M65: 5523 | N65: 54177 | O65: 0.91 | P65: 0.5
B66: USA | C66: Managed Services | D66: Architecture | E66: D - Lead | F66: Lead Architect | G66: 90 | H66: 259 | I66: -60 | J66: 199 | K66: 115 | L66: 17910 | M66: 10350 | N66: 7560 | O66: 0.42 | P66: 0.15
B67: USA | C67: PMO | D67: Delivery Management | E67: D - Lead | F67: Senior Project Manager or Program Manager | G67: 90 | H67: 259 | I67: -60 | J67: 199 | K67: 115 | L67: 17910 | M67: 10350 | N67: 7560 | O67: 0.42 | P67: 0.15

Sheet Change Orders and Staff Aug -->
A1: Instructions
A2: Version 2.02
A3: Release Date: 2024-06-25
A5: 1. Copy this file from SharePoint and place in the Customer's Client Focus folder for this respective Opportunity/Project.
A6: 2. Fill out the roles on the Pricing tab.
A9: Role Mapping - Professional Services
A10: Old Role | B10: New Role | C10: Note
A11: Staff Architect, Senior Architect, Lead Architect | B11: Solution Architect
A12: Associate BA, Staff BA, Senior BA, Lead BA | B12: Business Process Consultant
A13: Principal BPA, Chief BPA, Principal Architect, Chief Architect | B13: Workflow/Practice Strategist
A14: Senior Advisor, Lead Advisor | B14: Advisory Consultant
A15: Project Coordinator | B15: Project Coordinator
A16: Project Manager | B16: Project Manager
A17: Senior Project Manager or Program Manager | B17: Senior Project Manager or Program Manager
A18: Associate Engineer, Staff Engineer | B18: Technical Consultant
A19: Senior Engineer, Lead Engineer | B19: Senior Technical Consultant
A20: Staff Tester, Senior Tester | B20: Tester
A21: Change Adoption Specialist | B21: Change Adoption Specialist
A22: Trainer | B22: Trainer
... A25: Principal Designer, Chief Designer, Principal Content Strategist, Principal Content Strategist | B25: Workflow/Practice Strategist
A26: N/A | B26: Solution Consultant | C26: This is presales
A29: Role Mapping - Managed Services
A30: Old Role | B30: New Role | C30: Note
A31: Staff Architect, Senior Architect, Lead Architect | B31: MS - Architect
A32: Staff Engineer, Senior Engineer, Lead Engineer | B32: MS - Engineer
A33: Platform Administrator | B33: MS - Platform Analyst

Sheet Manticore -->
A1: Instructions
A2: Version 2.0
A3: Release Date: 2024-06-10
A5: 1. Copy this file from SharePoint and place in the Customer's Client Focus folder for this respective Opportunity/Project.
A6: 2. Fill out the Opportunity Details Tab to the best of your ability
A7: 3. Fill out the roles, oversight and skills on the Pricing tab.
A8: 3. Fill out the Tasks and Estimates tab for your respective application deployments.
A9: 4. Review the T&E summary tab, and enter the schedule length and adjust to reduce fractionalization as much as possible.
A10: 5. Review the week by week breakout on the T&E Summary sheet (scroll down) to review projected hours a week by role.

Sheet Basic Pricing File
B2: NewRocket Basic Pricing Tool
B3: Internal Use Only
B6: Engagement Overview | O6: ="Financial Dashboard (" &G17& ")" -> Financial Dashboard (USD)
B7: Date | P7: Total | Q7: Onsite | R7: India
B8: Preparer's Name | O8: Revenue | P8: =AK52 -> 326376 | Q8: =AL52 -> 151656 | R8: =AM52 -> 174720
B9: Practice | G9: Technology | O9: Cost | P9: =AN52 -> 104489.78 | Q9: =AO52 -> 62337.078 | R9: =AP52 -> 42152.698
B10: Capability | G10: Technology: ITAM | O10: GM/GP | P10: =P8-P9 -> 221886.22 | Q10: =Q8-Q9 -> 89318.922 | R10: =R8-R9 -> 132567.3 | Z10: Minimum total CM% based on India leverage
B11: Account Name | O11: GM% | P11: =IFERROR(P10/P8,"") -> 0.67984847 | Q11: =IFERROR(Q10/Q8,"") -> 0.58895739 | R11: =IFERROR(R10/R8,"") -> 0.75874143 | Z11: =0.3125*R13^5-0.4276*R13^4+0.3734*R13^3-0.1274*R13^2+0.0669*R13+0.5 -> 0.56722553
B12: Partner | O12: Hours | P12: =IFERROR(J55,0) -> 2664 | Q12: =IFERROR(AR52+AT52,"") -> 744 | R12: =IFERROR(AS52+AU52,"") -> 1920
B13: Opportunity Name | O13: Hours % | P13: =IFERROR(P12/P12,"") -> 1 | Q13: =IFERROR(Q12/P12,"") -> 0.27927928 | R13: =IFERROR(R12/P12,"") -> 0.72072072
B14: Opportunity Owner | O14: Avg Rate | P14: =IFERROR(P8/P12,"") -> 122.51351 | Q14: =IFERROR(Q8/Q12,"") -> 203.83871 | R14: =IFERROR(R8/R12,"") -> 91
B15: Salesforce Opportunity Number | O15: Avg Rack | P15: =IFERROR(AE52/AQ52,"") -> 122.51351 | Q15: =IFERROR(AF52/AR52,"") -> 203.83871 | R15: =IFERROR(AG52/AS52,"") -> 91
B16: Client Location | G16: USA | O16: Variance | P16: =IFERROR(P14-P15,"") -> 0 | Q16: =IFERROR(Q14-Q15,"") -> 0 | R16: =IFERROR(R14-R15,"") -> 0 | Z16: Percentage for CM calculation
B17: Opportunity Currency | G17: =IFERROR(VLOOKUP(G16,'Lists (2)'!C2:D6,2),"") -> USD | O17: Variance % | P17: =IFERROR(P16/P15,"") -> 0 | Q17: =IFERROR(Q16/Q15,"") -> 0 | R17: =IFERROR(R16/R15,"") -> 0 | Z17: 0.25
B18: Contract Type | G18: Time & Materials | O18: CM% | P18: =IFERROR(P10/P8-($Z$17),"") -> 0.42984847 | Q18: =IFERROR(Q10/Q8-($Z$17),"") -> 0.33895739 | R18: =IFERROR(R10/R8-($Z$17),"") -> 0.50874143
B19: Change Order | G19: No
B21: If there are any staffing restrictions, enter them here:
B22: Notes
B25: Roles and Rates
B26: Bill Rate: Onshore/ Offshore | C26: Billing Location | D26: Resource Location (Margin) | E26: Role Name | J26: Billable Hours | K26: Non-Billable Hours | L26: Rack Bill Rate | M26: Discount or Premium | N26: Bill Rate | O26: Cost Rate | P26: Revenue | Q26: Cost | R26: GM/GP | S26: GM% | T26: Practice | U26: Skill #1 | V26: Skill #2 | W26: Skill #3 | X26: Note | Z26: India? | AA26: Advisory? | AB26: Role | AC26: Rack Bill Rate | AD26: Cost Rate | AE26: Total Revenue at Rack Rate | AF26: Onsite Revenue at Rack Rate | AG26: India Revenue at Rack Rate | AH26: Revenue w/ Contingency | AI26: Cost w/ Contingency | AJ26: One-Time Discount | AK26: Total Revenue | AL26: Onsite Revenue | AM26: India Revenue | AN26: Total Cost | AO26: Onsite Cost | AP26: India Cost | AQ26: Total Hours | AR26: Onsite Hours | AS26: India Hours | AT26: Onsite Contingency Hours | AU26: India Contingency Hours
B27: Offshore | C27: {=IFERROR(_xlfn.IFS(B27="Onshore",$G$16,B27="Offshore","India"),"")} -> India | D27: India | E27: Technical Consultant | J27: 1440 | L27: =IFERROR(INDEX(Bill_Rates!$L:$L,MATCH('Basic Pricing File'!$AC27,Bill_Rates!$J:$J,0)),"") -> 85 | N27: =IFERROR(L27+M27,"") -> 85 | O27: =IFERROR(INDEX(Bill_Rates!$O:$O,MATCH($AD27,Bill_Rates!$J:$J,0)),"") -> 15.57792 | P27: =IFERROR(N27*J27,"") -> 122400 | Q27: =IFERROR((J27+K27)*O27,"") -> 22432.205 | R27: =IFERROR(P27-Q27,"") -> 99967.795 | S27: =IFERROR(R27/P27,"") -> 0.81673035 | T27: Customer | AA27: =IF(OR(G27="Change Management",G27="Enablement",G27="Strategy"),G27,"") | AB27: =E27 -> Technical Consultant | AC27: =G$16&C27&Z27&F27&AA27&H27&E27 -> USAIndiaTechnical Consultant | AD27: =G$16&D27&H27&E27 -> USAIndiaTechnical Consultant | AE27: =IFERROR(L27*J27,"") -> 122400 | AF27: =IFERROR(AE27-AG27,"") -> 0 | AG27: =IF(D27="India",AE27,0) -> 122400 | AH27: =IFERROR(P27+P27/$P$52*$P$53,"") -> 122400 | AI27: =IFERROR(Q27+Q27/$Q$52*$Q$53,"") -> 22432.205 | AJ27: =IFERROR(P27/$P$52*$P$54,"") -> 0 | AK27: =IFERROR(AH27+AJ27,"") -> 122400 | AL27: =IFERROR(AK27-AM27,"") -> 0 | AM27: =IF(D27="India",AK27,0) -> 122400 | AN27: =AI27 -> 22432.205 | AO27: =IFERROR(AN27-AP27,"") -> 0 | AP27: =IF(D27="India",AN27,0) -> 22432.205
B28: Offshore | C28: {=IFERROR(_xlfn.IFS(B28="Onshore",$G$16,B28="Offshore","India"),"")} -> India | D28: India | E28: Solution Architect | J28: 480 | L28: =IFERROR(INDEX(Bill_Rates!$L:$L,MATCH('Basic Pricing File'!$AC28,Bill_Rates!$J:$J,0)),"") -> 109 | N28: =IFERROR(L28+M28,"") -> 109 | O28: =IFERROR(INDEX(Bill_Rates!$O:$O,MATCH($AD28,Bill_Rates!$J:$J,0)),"") -> 41.08436 | P28: =IFERROR(N28*J28,"") -> 52320 | Q28: =IFERROR((J28+K28)*O28,"") -> 19720.493 | R28: =IFERROR(P28-Q28,"") -> 32599.507 | S28: =IFERROR(R28/P28,"") -> 0.62307927 | T28: Customer | AA28: =IF(OR(G28="Change Management",G28="Enablement",G28="Strategy"),G28,"") | AB28: =E28 -> Solution Architect | AC28: =G$16&C28&Z28&F28&AA28&H28&E28 -> USAIndiaSolution Architect | AD28: =G$16&D28&H28&E28 -> USAIndiaSolution Architect | AE28: =IFERROR(L28*J28,"") -> 52320 | AF28: =IFERROR(AE28-AG28,"") -> 0 | AG28: =IF(D28="India",AE28,0) -> 52320 | AH28: =IFERROR(P28+P28/$P$52*$P$53,"") -> 52320 | AI28: =IFERROR(Q28+Q28/$Q$52*$Q$53,"") -> 19720.493 | AJ28: =IFERROR(P28/$P$52*$P$54,"") -> 0 | AK28: =IFERROR(AH28+AJ28,"") -> 52320 | AL28: =IFERROR(AK28-AM28,"") -> 0 | AM28: =IF(D28="India",AK28,0) -> 52320 | AN28: =AI28 -> 19720.493 | AO28: =IFERROR(AN28-AP28,"") -> 0 | AP28: =IF(D28="India",AN28,0) -> 19720.493
B29: Onshore | C29: {=IFERROR(_xlfn.IFS(B29="Onshore",$G$16,B29="Offshore","India"),"")} -> USA | D29: Canada | E29: Project Coordinator | J29: 384 | L29: =IFERROR(INDEX(Bill_Rates!$L:$L,MATCH('Basic Pricing File'!$AC29,Bill_Rates!$J:$J,0)),"") -> 199 | N29: =IFERROR(L29+M29,"") -> 199 | O29: =IFERROR(INDEX(Bill_Rates!$O:$O,MATCH($AD29,Bill_Rates!$J:$J,0)),"") -> 60.14864 | P29: =IFERROR(N29*J29,"") -> 76416 | Q29: =IFERROR((J29+K29)*O29,"") -> 23097.078 | R29: =IFERROR(P29-Q29,"") -> 53318.922 | S29: =IFERROR(R29/P29,"") -> 0.69774553 | AA29: =IF(OR(G29="Change Management",G29="Enablement",G29="Strategy"),G29,"") | AB29: =E29 -> Project Coordinator | AC29: =G$16&C29&Z29&F29&AA29&H29&E29 -> USAUSAProject Coordinator | AD29: =G$16&D29&H29&E29 -> USACanadaProject Coordinator | AE29: =IFERROR(L29*J29,"") -> 76416 | AF29: =IFERROR(AE29-AG29,"") -> 76416 | AG29: =IF(D29="India",AE29,0) -> 0 | AH29: =IFERROR(P29+P29/$P$52*$P$53,"") -> 76416 | AI29: =IFERROR(Q29+Q29/$Q$52*$Q$53,"") -> 23097.078 | AJ29: =IFERROR(P29/$P$52*$P$54,"") -> 0 | AK29: =IFERROR(AH29+AJ29,"") -> 76416 | AL29: =IFERROR(AK29-AM29,"") -> 76416 | AM29: =IF(D29="India",AK29,0) -> 0 | AN29: =AI29 -> 23097.078 | AO29: =IFERROR(AN29-AP29,"") -> 23097.078 | AP29: =IF(D29="India",AN29,0) -> 0
B30: Onshore | C30: {=IFERROR(_xlfn.IFS(B30="Onshore",$G$16,B30="Offshore","India"),"")} -> USA | D30: USA | E30: Technical Consultant | J30: 360 | L30: =IFERROR(INDEX(Bill_Rates!$L:$L,MATCH('Basic Pricing File'!$AC30,Bill_Rates!$J:$J,0)),"") -> 209 | N30: =IFERROR(L30+M30,"") -> 209 | O30: =IFERROR(INDEX(Bill_Rates!$O:$O,MATCH($AD30,Bill_Rates!$J:$J,0)),"") -> 109 | P30: =IFERROR(N30*J30,"") -> 75240 | Q30: =IFERROR((J30+K30)*O30,"") -> 39240 | R30: =IFERROR(P30-Q30,"") -> 36000 | S30: =IFERROR(R30/P30,"") -> 0.4784689 | AA30: =IF(OR(G30="Change Management",G30="Enablement",G30="Strategy"),G30,"") | AB30: =E30 -> Technical Consultant | AC30: =G$16&C30&Z30&F30&AA30&H30&E30 -> USAUSATechnical Consultant | AD30: =G$16&D30&H30&E30 -> USAUSATechnical Consultant | AE30: =IFERROR(L30*J30,"") -> 75240 | AF30: =IFERROR(AE30-AG30,"") -> 75240 | AG30: =IF(D30="India",AE30,0) -> 0 | AH30: =IFERROR(P30+P30/$P$52*$P$53,"") -> 75240 | AI30: =IFERROR(Q30+Q30/$Q$52*$Q$53,"") -> 39240 | AJ30: =IFERROR(P30/$P$52*$P$54,"") -> 0 | AK30: =IFERROR(AH30+AJ30,"") -> 75240 | AL30: =IFERROR(AK30-AM30,"") -> 75240 | AM30: =IF(D30="India",AK30,0) -> 0 | AN30: =AI30 -> 39240 | AO30: =IFERROR(AN30-AP30,"") -> 39240 | AP30: =IF(D30="India",AN30,0) -> 0
C31: {=IFERROR(_xlfn.IFS(B31="Onshore",$G$16,B31="Offshore","India"),"")} | L31: =IFERROR(INDEX(Bill_Rates!$L:$L,MATCH('Basic Pricing File'!$AC31,Bill_Rates!$J:$J,0)),"") | N31: =IFERROR(L31+M31,"") | O31: =IFERROR(INDEX(Bill_Rates!$O:$O,MATCH($AD31,Bill_Rates!$J:$J,0)),"") | P31: =IFERROR(N31*J31,"") | Q31: =IFERROR((J31+K31)*O31,"") | R31: =IFERROR(P31-Q31,"") | S31: =IFERROR(R31/P31,"") | AA31: =IF(OR(G31="Change Management",G31="Enablement",G31="Strategy"),G31,"") | AB31: =E31 -> 0 | AC31: =G$16&C31&Z31&F31&AA31&H31&E31 -> USA | AD31: =G$16&D31&H31&E31 -> USA | AE31: =IFERROR(L31*J31,"") | AF31: =IFERROR(AE31-AG31,"") | AG31: =IF(D31="India",AE31,0) -> 0 | AH31: =IFERROR(P31+P31/$P$52*$P$53,"") | AI31: =IFERROR(Q31+Q31/$Q$52*$Q$53,"") | AJ31: =IFERROR(P31/$P$52*$P$54,"") | AK31: =IFERROR(AH31+AJ31,"") | AL31: =IFERROR(AK31-AM31,"") | AM31: =IF(D31="India",AK31,0) -> 0 | AN31: =AI31 | AO31: =IFERROR(AN31-AP31,"") | AP31: =IF(D31="India",AN31,0) -> 0
C32: {=IFERROR(_xlfn.IFS(B32="Onshore",$G$16,B32="Offshore","India"),"")} | L32: =IFERROR(INDEX(Bill_Rates!$L:$L,MATCH('Basic Pricing File'!$AC32,Bill_Rates!$J:$J,0)),"") | N32: =IFERROR(L32+M32,"") | O32: =IFERROR(INDEX(Bill_Rates!$O:$O,MATCH($AD32,Bill_Rates!$J:$J,0)),"") | P32: =IFERROR(N32*J32,"") | Q32: =IFERROR((J32+K32)*O32,"") | R32: =IFERROR(P32-Q32,"") | S32: =IFERROR(R32/P32,"") | AA32: =IF(OR(G32="Change Management",G32="Enablement",G32="Strategy"),G32,"") | AB32: =E32 -> 0 | AC32: =G$16&C32&Z32&F32&AA32&H32&E32 -> USA | AD32: =G$16&D32&H32&E32 -> USA | AE32: =IFERROR(L32*J32,"") | AF32: =IFERROR(AE32-AG32,"") | AG32: =IF(D32="India",AE32,0) -> 0 | AH32: =IFERROR(P32+P32/$P$52*$P$53,"") | AI32: =IFERROR(Q32+Q32/$Q$52*$Q$53,"") | AJ32: =IFERROR(P32/$P$52*$P$54,"") | AK32: =IFERROR(AH32+AJ32,"") | AL32: =IFERROR(AK32-AM32,"") | AM32: =IF(D32="India",AK32,0) -> 0 | AN32: =AI32 | AO32: =IFERROR(AN32-AP32,"") | AP32: =IF(D32="India",AN32,0) -> 0
C33: {=IFERROR(_xlfn.IFS(B33="Onshore",$G$16,B33="Offshore","India"),"")} | L33: =IFERROR(INDEX(Bill_Rates!$L:$L,MATCH('Basic Pricing File'!$AC33,Bill_Rates!$J:$J,0)),"") | N33: =IFERROR(L33+M33,"") | O33: =IFERROR(INDEX(Bill_Rates!$O:$O,MATCH($AD33,Bill_Rates!$J:$J,0)),"") | P33: =IFERROR(N33*J33,"") | Q33: =IFERROR((J33+K33)*O33,"") | R33: =IFERROR(P33-Q33,"") | S33: =IFERROR(R33/P33,"") | AA33: =IF(OR(G33="Change Management",G33="Enablement",G33="Strategy"),G33,"") | AB33: =E33 -> 0 | AC33: =G$16&C33&Z33&F33&AA33&H33&E33 -> USA | AD33: =G$16&D33&H33&E33 -> USA | AE33: =IFERROR(L33*J33,"") | AF33: =IFERROR(AE33-AG33,"") | AG33: =IF(D33="India",AE33,0) -> 0 | AH33: =IFERROR(P33+P33/$P$52*$P$53,"") | AI33: =IFERROR(Q33+Q33/$Q$52*$Q$53,"") | AJ33: =IFERROR(P33/$P$52*$P$54,"") | AK33: =IFERROR(AH33+AJ33,"") | AL33: =IFERROR(AK33-AM33,"") | AM33: =IF(D33="India",AK33,0) -> 0 | AN33: =AI33 | AO33: =IFERROR(AN33-AP33,"") | AP33: =IF(D33="India",AN33,0) -> 0
C34: {=IFERROR(_xlfn.IFS(B34="Onshore",$G$16,B34="Offshore","India"),"")} | L34: =IFERROR(INDEX(Bill_Rates!$L:$L,MATCH('Basic Pricing File'!$AC34,Bill_Rates!$J:$J,0)),"") | N34: =IFERROR(L34+M34,"") | O34: =IFERROR(INDEX(Bill_Rates!$O:$O,MATCH($AD34,Bill_Rates!$J:$J,0)),"") | P34: =IFERROR(N34*J34,"") | Q34: =IFERROR((J34+K34)*O34,"") | R34: =IFERROR(P34-Q34,"") | S34: =IFERROR(R34/P34,"") | AA34: =IF(OR(G34="Change Management",G34="Enablement",G34="Strategy"),G34,"") | AB34: =E34 -> 0 | AC34: =G$16&C34&Z34&F34&AA34&H34&E34 -> USA | AD34: =G$16&D34&H34&E34 -> USA | AE34: =IFERROR(L34*J34,"") | AF34: =IFERROR(AE34-AG34,"") | AG34: =IF(D34="India",AE34,0) -> 0 | AH34: =IFERROR(P34+P34/$P$52*$P$53,"") | AI34: =IFERROR(Q34+Q34/$Q$52*$Q$53,"") | AJ34: =IFERROR(P34/$P$52*$P$54,"") | AK34: =IFERROR(AH34+AJ34,"") | AL34: =IFERROR(AK34-AM34,"") | AM34: =IF(D34="India",AK34,0) -> 0 | AN34: =AI34 | AO34: =IFERROR(AN34-AP34,"") | AP34: =IF(D34="India",AN34,0) -> 0
C35: {=IFERROR(_xlfn.IFS(B35="Onshore",$G$16,B35="Offshore","India"),"")} | L35: =IFERROR(INDEX(Bill_Rates!$L:$L,MATCH('Basic Pricing File'!$AC35,Bill_Rates!$J:$J,0)),"") | N35: =IFERROR(L35+M35,"") | O35: =IFERROR(INDEX(Bill_Rates!$O:$O,MATCH($AD35,Bill_Rates!$J:$J,0)),"") | P35: =IFERROR(N35*J35,"") | Q35: =IFERROR((J35+K35)*O35,"") | R35: =IFERROR(P35-Q35,"") | S35: =IFERROR(R35/P35,"") | AA35: =IF(OR(G35="Change Management",G35="Enablement",G35="Strategy"),G35,"") | AB35: =E35 -> 0 | AC35: =G$16&C35&Z35&F35&AA35&H35&E35 -> USA | AD35: =G$16&D35&H35&E35 -> USA | AE35: =IFERROR(L35*J35,"") | AF35: =IFERROR(AE35-AG35,"") | AG35: =IF(D35="India",AE35,0) -> 0 | AH35: =IFERROR(P35+P35/$P$52*$P$53,"") | AI35: =IFERROR(Q35+Q35/$Q$52*$Q$53,"") | AJ35: =IFERROR(P35/$P$52*$P$54,"") | AK35: =IFERROR(AH35+AJ35,"") | AL35: =IFERROR(AK35-AM35,"") | AM35: =IF(D35="India",AK35,0) -> 0 | AN35: =AI35 | AO35: =IFERROR(AN35-AP35,"") | AP35: =IF(D35="India",AN35,0) -> 0
C36: {=IFERROR(_xlfn.IFS(B36="Onshore",$G$16,B36="Offshore","India"),"")} | L36: =IFERROR(INDEX(Bill_Rates!$L:$L,MATCH('Basic Pricing File'!$AC36,Bill_Rates!$J:$J,0)),"") | N36: =IFERROR(L36+M36,"") | O36: =IFERROR(INDEX(Bill_Rates!$O:$O,MATCH($AD36,Bill_Rates!$J:$J,0)),"") | P36: =IFERROR(N36*J36,"") | Q36: =IFERROR((J36+K36)*O36,"") | R36: =IFERROR(P36-Q36,"") | S36: =IFERROR(R36/P36,"") | AA36: =IF(OR(G36="Change Management",G36="Enablement",G36="Strategy"),G36,"") | AB36: =E36 -> 0 | AC36: =G$16&C36&Z36&F36&AA36&H36&E36 -> USA | AD36: =G$16&D36&H36&E36 -> USA | AE36: =IFERROR(L36*J36,"") | AF36: =IFERROR(AE36-AG36,"") | AG36: =IF(D36="India",AE36,0) -> 0 | AH36: =IFERROR(P36+P36/$P$52*$P$53,"") | AI36: =IFERROR(Q36+Q36/$Q$52*$Q$53,"") | AJ36: =IFERROR(P36/$P$52*$P$54,"") | AK36: =IFERROR(AH36+AJ36,"") | AL36: =IFERROR(AK36-AM36,"") | AM36: =IF(D36="India",AK36,0) -> 0 | AN36: =AI36 | AO36: =IFERROR(AN36-AP36,"") | AP36: =IF(D36="India",AN36,0) -> 0
C37: {=IFERROR(_xlfn.IFS(B37="Onshore",$G$16,B37="Offshore","India"),"")} | L37: =IFERROR(INDEX(Bill_Rates!$L:$L,MATCH('Basic Pricing File'!$AC37,Bill_Rates!$J:$J,0)),"") | N37: =IFERROR(L37+M37,"") | O37: =IFERROR(INDEX(Bill_Rates!$O:$O,MATCH($AD37,Bill_Rates!$J:$J,0)),"") | P37: =IFERROR(N37*J37,"") | Q37: =IFERROR((J37+K37)*O37,"") | R37: =IFERROR(P37-Q37,"") | S37: =IFERROR(R37/P37,"") | AA37: =IF(OR(G37="Change Management",G37="Enablement",G37="Strategy"),G37,"") | AB37: =E37 -> 0 | AC37: =G$16&C37&Z37&F37&AA37&H37&E37 -> USA | AD37: =G$16&D37&H37&E37 -> USA | AE37: =IFERROR(L37*J37,"") | AF37: =IFERROR(AE37-AG37,"") | AG37: =IF(D37="India",AE37,0) -> 0 | AH37: =IFERROR(P37+P37/$P$52*$P$53,"") | AI37: =IFERROR(Q37+Q37/$Q$52*$Q$53,"") | AJ37: =IFERROR(P37/$P$52*$P$54,"") | AK37: =IFERROR(AH37+AJ37,"") | AL37: =IFERROR(AK37-AM37,"") | AM37: =IF(D37="India",AK37,0) -> 0 | AN37: =AI37 | AO37: =IFERROR(AN37-AP37,"") | AP37: =IF(D37="India",AN37,0) -> 0
C38: {=IFERROR(_xlfn.IFS(B38="Onshore",$G$16,B38="Offshore","India"),"")} | L38: =IFERROR(INDEX(Bill_Rates!$L:$L,MATCH('Basic Pricing File'!$AC38,Bill_Rates!$J:$J,0)),"") | N38: =IFERROR(L38+M38,"") | O38: =IFERROR(INDEX(Bill_Rates!$O:$O,MATCH($AD38,Bill_Rates!$J:$J,0)),"") | P38: =IFERROR(N38*J38,"") | Q38: =IFERROR((J38+K38)*O38,"") | R38: =IFERROR(P38-Q38,"") | S38: =IFERROR(R38/P38,"") | AA38: =IF(OR(G38="Change Management",G38="Enablement",G38="Strategy"),G38,"") | AB38: =E38 -> 0 | AC38: =G$16&C38&Z38&F38&AA38&H38&E38 -> USA | AD38: =G$16&D38&H38&E38 -> USA | AE38: =IFERROR(L38*J38,"") | AF38: =IFERROR(AE38-AG38,"") | AG38: =IF(D38="India",AE38,0) -> 0 | AH38: =IFERROR(P38+P38/$P$52*$P$53,"") | AI38: =IFERROR(Q38+Q38/$Q$52*$Q$53,"") | AJ38: =IFERROR(P38/$P$52*$P$54,"") | AK38: =IFERROR(AH38+AJ38,"") | AL38: =IFERROR(AK38-AM38,"") | AM38: =IF(D38="India",AK38,0) -> 0 | AN38: =AI38 | AO38: =IFERROR(AN38-AP38,"") | AP38: =IF(D38="India",AN38,0) -> 0
C39: {=IFERROR(_xlfn.IFS(B39="Onshore",$G$16,B39="Offshore","India"),"")} | L39: =IFERROR(INDEX(Bill_Rates!$L:$L,MATCH('Basic Pricing File'!$AC39,Bill_Rates!$J:$J,0)),"") | N39: =IFERROR(L39+M39,"") | O39: =IFERROR(INDEX(Bill_Rates!$O:$O,MATCH($AD39,Bill_Rates!$J:$J,0)),"") | P39: =IFERROR(N39*J39,"") | Q39: =IFERROR((J39+K39)*O39,"") | R39: =IFERROR(P39-Q39,"") | S39: =IFERROR(R39/P39,"") | AA39: =IF(OR(G39="Change Management",G39="Enablement",G39="Strategy"),G39,"") | AB39: =E39 -> 0 | AC39: =G$16&C39&Z39&F39&AA39&H39&E39 -> USA | AD39: =G$16&D39&H39&E39 -> USA | AE39: =IFERROR(L39*J39,"") | AF39: =IFERROR(AE39-AG39,"") | AG39: =IF(D39="India",AE39,0) -> 0 | AH39: =IFERROR(P39+P39/$P$52*$P$53,"") | AI39: =IFERROR(Q39+Q39/$Q$52*$Q$53,"") | AJ39: =IFERROR(P39/$P$52*$P$54,"") | AK39: =IFERROR(AH39+AJ39,"") | AL39: =IFERROR(AK39-AM39,"") | AM39: =IF(D39="India",AK39,0) -> 0 | AN39: =AI39 | AO39: =IFERROR(AN39-AP39,"") | AP39: =IF(D39="India",AN39,0) -> 0
C40: {=IFERROR(_xlfn.IFS(B40="Onshore",$G$16,B40="Offshore","India"),"")} | L40: =IFERROR(INDEX(Bill_Rates!$L:$L,MATCH('Basic Pricing File'!$AC40,Bill_Rates!$J:$J,0)),"") | N40: =IFERROR(L40+M40,"") | O40: =IFERROR(INDEX(Bill_Rates!$O:$O,MATCH($AD40,Bill_Rates!$J:$J,0)),"") | P40: =IFERROR(N40*J40,"") | Q40: =IFERROR((J40+K40)*O40,"") | R40: =IFERROR(P40-Q40,"") | S40: =IFERROR(R40/P40,"") | AA40: =IF(OR(G40="Change Management",G40="Enablement",G40="Strategy"),G40,"") | AB40: =E40 -> 0 | AC40: =G$16&C40&Z40&F40&AA40&H40&E40 -> USA | AD40: =G$16&D40&H40&E40 -> USA | AE40: =IFERROR(L40*J40,"") | AF40: =IFERROR(AE40-AG40,"") | AG40: =IF(D40="India",AE40,0) -> 0 | AH40: =IFERROR(P40+P40/$P$52*$P$53,"") | AI40: =IFERROR(Q40+Q40/$Q$52*$Q$53,"") | AJ40: =IFERROR(P40/$P$52*$P$54,"") | AK40: =IFERROR(AH40+AJ40,"") | AL40: =IFERROR(AK40-AM40,"") | AM40: =IF(D40="India",AK40,0) -> 0 | AN40: =AI40 | AO40: =IFERROR(AN40-AP40,"") | AP40: =IF(D40="India",AN40,0) -> 0
C41: {=IFERROR(_xlfn.IFS(B41="Onshore",$G$16,B41="Offshore","India"),"")} | L41: =IFERROR(INDEX(Bill_Rates!$L:$L,MATCH('Basic Pricing File'!$AC41,Bill_Rates!$J:$J,0)),"") | N41: =IFERROR(L41+M41,"") | O41: =IFERROR(INDEX(Bill_Rates!$O:$O,MATCH($AD41,Bill_Rates!$J:$J,0)),"") | P41: =IFERROR(N41*J41,"") | Q41: =IFERROR((J41+K41)*O41,"") | R41: =IFERROR(P41-Q41,"") | S41: =IFERROR(R41/P41,"") | AA41: =IF(OR(G41="Change Management",G41="Enablement",G41="Strategy"),G41,"") | AB41: =E41 -> 0 | AC41: =G$16&C41&Z41&F41&AA41&H41&E41 -> USA | AD41: =G$16&D41&H41&E41 -> USA | AE41: =IFERROR(L41*J41,"") | AF41: =IFERROR(AE41-AG41,"") | AG41: =IF(D41="India",AE41,0) -> 0 | AH41: =IFERROR(P41+P41/$P$52*$P$53,"") | AI41: =IFERROR(Q41+Q41/$Q$52*$Q$53,"") | AJ41: =IFERROR(P41/$P$52*$P$54,"") | AK41: =IFERROR(AH41+AJ41,"") | AL41: =IFERROR(AK41-AM41,"") | AM41: =IF(D41="India",AK41,0) -> 0 | AN41: =AI41 | AO41: =IFERROR(AN41-AP41,"") | AP41: =IF(D41="India",AN41,0) -> 0
C42: {=IFERROR(_xlfn.IFS(B42="Onshore",$G$16,B42="Offshore","India"),"")} | L42: =IFERROR(INDEX(Bill_Rates!$L:$L,MATCH('Basic Pricing File'!$AC42,Bill_Rates!$J:$J,0)),"") | N42: =IFERROR(L42+M42,"") | O42: =IFERROR(INDEX(Bill_Rates!$O:$O,MATCH($AD42,Bill_Rates!$J:$J,0)),"") | P42: =IFERROR(N42*J42,"") | Q42: =IFERROR((J42+K42)*O42,"") | R42: =IFERROR(P42-Q42,"") | S42: =IFERROR(R42/P42,"") | AA42: =IF(OR(G42="Change Management",G42="Enablement",G42="Strategy"),G42,"") | AB42: =E42 -> 0 | AC42: =G$16&C42&Z42&F42&AA42&H42&E42 -> USA | AD42: =G$16&D42&H42&E42 -> USA | AE42: =IFERROR(L42*J42,"") | AF42: =IFERROR(AE42-AG42,"") | AG42: =IF(D42="India",AE42,0) -> 0 | AH42: =IFERROR(P42+P42/$P$52*$P$53,"") | AI42: =IFERROR(Q42+Q42/$Q$52*$Q$53,"") | AJ42: =IFERROR(P42/$P$52*$P$54,"") | AK42: =IFERROR(AH42+AJ42,"") | AL42: =IFERROR(AK42-AM42,"") | AM42: =IF(D42="India",AK42,0) -> 0 | AN42: =AI42 | AO42: =IFERROR(AN42-AP42,"") | AP42: =IF(D42="India",AN42,0) -> 0
... C51: {=IFERROR(_xlfn.IFS(B51="Onshore",$G$16,B51="Offshore","India"),"")} | L51: =IFERROR(INDEX(Bill_Rates!$L:$L,MATCH('Basic Pricing File'!$AC51,Bill_Rates!$J:$J,0)),"") | N51: =IFERROR(L51+M51,"") | O51: =IFERROR(INDEX(Bill_Rates!$O:$O,MATCH($AD51,Bill_Rates!$J:$J,0)),"") | P51: =IFERROR(N51*J51,"") | Q51: =IFERROR((J51+K51)*O51,"") | R51: =IFERROR(P51-Q51,"") | S51: =IFERROR(R51/P51,"") | AA51: =IF(OR(G51="Change Management",G51="Enablement",G51="Strategy"),G51,"") | AB51: =E51 -> 0 | AC51: =G$16&C51&Z51&F51&AA51&H51&E51 -> USA | AD51: =G$16&D51&H51&E51 -> USA | AE51: =IFERROR(L51*J51,"") | AF51: =IFERROR(AE51-AG51,"") | AG51: =IF(D51="India",AE51,0) -> 0 | AH51: =IFERROR(P51+P51/$P$52*$P$53,"") | AI51: =IFERROR(Q51+Q51/$Q$52*$Q$53,"") | AJ51: =IFERROR(P51/$P$52*$P$54,"") | AK51: =IFERROR(AH51+AJ51,"") | AL51: =IFERROR(AK51-AM51,"") | AM51: =IF(D51="India",AK51,0) -> 0 | AN51: =AI51 | AO51: =IFERROR(AN51-AP51,"") | AP51: =IF(D51="India",AN51,0) -> 0
B52: Subtotal | J52: =SUM(J27:J51) -> 2664 | K52: =SUM(K27:K51) -> 0 | P52: =SUM(P27:P51) -> 326376 | Q52: =SUM(Q27:Q51) -> 104489.78 | R52: =SUM(R27:R51) -> 221886.22 | S52: =IFERROR(R52/P52,"") -> 0.67984847 | Z52: =IF(C27="India","India","") -> India | AA52: =F52&G52 | AE52: =SUM(AE27:AE51) -> 326376 | AF52: =SUM(AF27:AF51) -> 151656 | AG52: =SUM(AG27:AG51) -> 174720 | AH52: =SUM(AH27:AH51) -> 326376 | AI52: =SUM(AI27:AI51) -> 104489.78 | AJ52: =SUM(AJ27:AJ51) -> 0 | AK52: =SUM(AK27:AK51) -> 326376 | AL52: =SUM(AL27:AL51) -> 151656 | ... AP52: =SUM(AP27:AP51) -> 42152.698 | AQ52: =J52 -> 2664 | AR52: =AQ52-AS52 -> 744 | AS52: =SUMIF(D27:D51,"India",J27:J51) -> 1920 | AT52: =AR52/AQ52*J53 -> 0 | AU52: =AS52/AQ52*J53 -> 0
B53: Contingency (for fixed-price only) | J53: =IFERROR(P53/(P52/J52),"") -> 0 | P53: =IF($G$18="Fixed Price", $P$52*0.15,0) -> 0 | Q53: =IFERROR(P53*(1-S52),"") -> 0 | R53: =IFERROR(P53-Q53,"") -> 0 | S53: =IFERROR(R53/P53,"")
B54: One-time discount
B55: Total | J55: =IFERROR(J52+J53,"") -> 2664 | K55: =IFERROR(K52+K53,"") -> 0 | P55: =SUM(P52:P54) -> 326376 | Q55: =SUM(Q52:Q53) -> 104489.78 | R55: =P55-Q55 -> 221886.22 | S55: =IFERROR(R55/P55,"") -> 0.67984847
B58: Deal Review Questions
B59: What percentage of TCV will be invoiced upon SOW signature? | Z59: Note:
B60: Is there any restriction to using global delivery on this project? | I60: No | J60: If yes, then explain: | Z60: Bill rate is based on client location, whether the resource is in India or not.
B61: What is the primary client delivery location? | Z61: Cost rate is based on billing location, resource location and resource.
B62: Is our proposal or SOW solution-based with defined scope and deliverables? | J62: If no, then engagement type:
B63: Are any specialized skills, including security clearances, required to deliver the project? | J63: If yes, then list skills:
B64: Have we successfully delivered this type of project previously? Do we have assumptions to mitigate any substantial risks?
B65: Are any of the standard SOW terms and conditions to be modified? | J65: If yes, then list modifications:
B66: If any fields in this Pricing Tool are highlighted in red, then provide reason(s).
B67: Will any NewRocket product licenses be included as part of this opportunity? | J67: If yes, then list products: | O67: Term (years): | Q67: Price per yr:
B68: Notes
D72: Account | F72: =G11 -> 0
D73: Practice | F73: =G9 -> Technology
D74: Opportunity Owner | F74: =G14 -> 0
D75: Client Location | F75: =G16 -> USA
D76: Change Order | F76: =G19 -> No
D77: Currency | F77: =G17 -> USD
D78: TCV | F78: =P8 -> 326376
D79: CM% | F79: =P11 -> 0.67984847
D80: Avg Rate | F80: =P14 -> 122.51351
D81: Rate discount | F81: =IFERROR(-P17,"") -> 0
D82: Pre-payment | F82: =I59 -> 0
D83: India Restriction | F83: =I60 -> No
D84: India Hours | F84: =R13 -> 0.72072072

Sheet Deal Review Guidance
B6: Items that should be reviewed
B7: Right resources are tied to the scope (e.g., architect, BA, PM, engineer vs senior engineer)
B8: Read the SOW and ensure the scope makes sense, what business issues we are trying to solve will be met with the solution
B9: Review deliverables that are in scope
B10: Make sure the assumptions, out of scope, in scope look accurate
B11: Review and adjust project Timeline (not based on resource availability but more in terms of is the timeline accurate to get the work done) - we cannot add more weeks and therefore hours because we don't have the resources, that is a TA problem they will need to solve for otherwise we lose the deal on price.
B12: Review that the architect and BA are on the project for the correct phases (e.g., if there is a potential ability to reduce roles needed then lets shift the hours - for instance if its an integration project and the SC scoped in BA time for Execute/Deliver/Close, perhaps that can be done by the SA).
B13: Oversight is accurately accounted for on this scope (look at week by week breakdown, not percentages)
B14: Try to identify areas to reduce fractionalization (e.g., shifting some engineer hours to architect if it cuts down on timeline).

Sheet Oversight Guidance
B3: The following is guidance for hours for each oversight role based on phases of the engagement (per week). This covers things like internal and external status calls, testing of code, story refinement throughout delivery, etc. This does not cover the oversight roles doing engineering tasks.
G9: More complex go to 20 hours a week
L10: Schumacher or Lorelai Haggan or Candace
C11: Phase | D11: ITSM | E11: ITOM | F11: HRSD | G11: CSM | H11: FSM | I11: Domain Separation | J11: SR&R | K11: Experience | L11: FSO
B12: Business Consulting | C12: Initiate (2 weeks) | D12: 2 | E12: 2 | F12: 2 | G12: 2 | H12: 2 | I12: 2 | J12: 2 | K12: 2 | L12: 2
C13: Execute | D13: 12 | E13: 8 | F13: 10 | G13: 16 | H13: 16 | I13: 16 | J13: 8 | K13: 2 | L13: 20
C14: Deliver | D14: 8 | E14: 8 | F14: 10 | G14: 16 | H14: 16 | I14: 16 | J14: 4 | K14: 0 | L14: 20
C15: Close | D15: 2 | E15: 2 | F15: 4 | G15: 4 | H15: 4 | I15: 4 | J15: 2 | K15: 0 | L15: 4
B17: Architecture | C17: Initiate (2 weeks) | D17: 2 | E17: 2 | F17: 2 | G17: 2 | H17: 2 | I17: 2 | J17: 2 | K17: 2 | L17: 2
C18: Execute | D18: 12 | E18: 12 | F18: 12 | G18: 16 | H18: 16 | I18: 16 | J18: 12 | K18: 5 | L18: 20
C19: Deliver | D19: 8 | E19: 12 | F19: 12 | G19: 16 | H19: 16 | I19: 16 | J19: 8 | K19: 5 | L19: 20
C20: Close | D20: 2 | E20: 8 | F20: 4 | G20: 8 | H20: 8 | I20: 8 | J20: 4 | K20: 3 | L20: 8
B22: Project Management | C22: Initiate (2 weeks) | D22: 10 | E22: 10 | F22: 10 | G22: 10 | H22: 10 | I22: 10 | J22: 10 | K22: 10 | L22: 10
C23: Plan | D23: 20 | E23: 20 | F23: 20 | G23: 20 | H23: 20 | I23: 20 | J23: 20 | K23: 20 | L23: 20
C24: Execute | D24: 20 | E24: 20 | F24: 20 | G24: 20 | H24: 20 | I24: 20 | J24: 20 | K24: 20 | L24: 20
C25: Deliver | D25: 20 | E25: 20 | F25: 20 | G25: 20 | H25: 20 | I25: 20 | J25: 20 | K25: 20 | L25: 20
C26: Close | D26: 10 | E26: 10 | F26: 10 | G26: 10 | H26: 10 | I26: 10 | J26: 10 | K26: 10 | L26: 10
B28: Advisor | C28: Plan | L28: Every workshop
C29: Execute | L29: 5
C30: Deliver | L30: 5
C31: Close | L31: 2
K32: ADD MORE ROLES PHIL :)
H34: CSM is more BPA vs BA. More consultative
H35: 20 hours a week for Plan to not overcommit on timelines
C37: Engineering Guidance
C38: For Engineering the Deliver should be 40 hours per week per engineer. On average the Deliver phase should be 2 to 3 weeks.
C39: For Engineering for the Close phase it should be 20 hours or 40 hours per week for at least 1 engineer

Sheet Opportunity Details
A1: Opportunity Details
A2: Salesforce Opportunity URL
A3: Salesforce Opportunity Number | D3: Date
A4: Opportunity Name | C4: Acme Opportunity
A5: Change Order | C5: No
A7: Account Name | C7: Boeing ITSM Now Assist AI POC
A8: Opportunity Owner | C8: Harry Tomczyk
A9: Pre-Sales Lead (Preparer's Name) | C9: Jason Hagen
A10: Delivery Lead | C10: Sean Iannuzzi
A11: Practice | C11: Technology
A12: Capability | C12: Technology: ITSM
A14: Client Location | C14: USA | D14: Contract Type | F14: Fixed Price
A15: Platform | C15: ServiceNow | D15: Partner
A16: Restriction from using global delivery? | C16: No | D16: Agile Project?
A18: Opportunity Close Date | D18: Expected Project Start Date | F18: =IF(ISBLANK(C19),IF(ISBLANK(Exp_Opp_Close),"",Exp_Opp_Close+30),C19) -> 44495
A19: Override Expected Project Start Date | C19: 44495
A20: Background | C20: ITSM Pro Plus Now Assist POC
A21: Challenges to solve | C21: These are the challenges they're trying to solve.
A22: Targeted business benefits | C22: These are the business benefits.

Sheet Pricing
B2: NewRocket Manticore
B3: Internal Use Only
B6: Engagement Overview | O6: ="Financial Dashboard (" &E17& ")" -> Financial Dashboard (USD)
B7: Date | E7: =IF(ISBLANK(Date),"",Date) | P7: Total | Q7: Onsite | R7: India
B8: Preparer's Name | E8: =IF(ISBLANK(Pre_Sales_Lead),"",Pre_Sales_Lead) -> Jason Hagen | O8: Revenue | P8: =AU42 -> 125000 | Q8: =AV42 -> 108712.45 | R8: =AW42 -> 16287.552
B9: Practice | E9: =IF(ISBLANK(Practice),"",Practice) -> Technology | O9: Cost | P9: =AX42 -> 63504.874 | Q9: =AY42 -> 59011.1 | R9: =AZ42 -> 4493.7744
B10: Capability | E10: =IF(ISBLANK(Practice_Capability),"",Practice_Capability) -> Technology: ITSM | O10: GM/GP | P10: =P8-P9 -> 61495.126 | Q10: =Q8-Q9 -> 49701.348 | R10: =R8-R9 -> 11793.777 | AJ10: Minimum total CM% based on India leverage
B11: Account Name | E11: =IF(ISBLANK(Client),"",Client) -> Boeing ITSM Now Assist AI POC | O11: GM% | P11: =IFERROR(P10/P8,"") -> 0.49196101 | Q11: =IFERROR(Q10/Q8,"") -> 0.45718176 | R11: =IFERROR(R10/R8,"") -> 0.72409761 | AJ11: =0.3125*R13^5-0.4276*R13^4+0.3734*R13^3-0.1274*R13^2+0.0669*R13+0.5 -> 0.51701364
B12: Partner | E12: =IF(ISBLANK(Partner),"",Partner) | O12: Hours | P12: =IFERROR(J45+K45,0) -> 557.75 | Q12: =IFERROR(BB42+BD42,"") -> 380.65 | R12: =IFERROR(BC42+BE42,"") -> 177.1 | AJ12: 0.55
B13: Opportunity Name | E13: =IF(ISBLANK(Engagement_Title),"",Engagement_Title) -> Acme Opportunity | O13: Hours % | P13: =IFERROR(P12/P12,"") -> 1 | Q13: =IFERROR(Q12/P12,"") -> 0.68247423 | R13: =IFERROR(R12/P12,"") -> 0.31752577 | AJ13: Global % of hours for PS deal
B14: Opportunity Owner | E14: =IF(ISBLANK(Sales_Lead),"",Sales_Lead) -> Harry Tomczyk | O14: Avg Rate | P14: =IFERROR(P8/P12,"") -> 224.11475 | Q14: =IFERROR(Q8/Q12,"") -> 285.59687 | R14: =IFERROR(R8/R12,"") -> 91.968106 | AJ14: 0.5
B15: Salesforce Opportunity Number | E15: =IF(ISBLANK(SF_ID),"",SF_ID) | O15: Avg Rack | P15: =IFERROR(AO42/BA42,"") -> 221.21443 | Q15: =IFERROR(AP42/BB42,"") -> 279.93656 | R15: =IFERROR(AQ42/BC42,"") -> 95
B16: Client Location | E16: =Client_Location -> USA | O16: Variance | P16: =IFERROR(P14-P15,"") -> 2.9003138 | Q16: =IFERROR(Q14-Q15,"") -> 5.6603138 | R16: =IFERROR(R14-R15,"") -> -3.0318942 | AJ16: Percentage for CM calculation
B17: Opportunity Currency | E17: =IFERROR(VLOOKUP(E16,'Lists (2)'!C2:D6,2),"") -> USD | O17: Variance % | P17: =IFERROR(P16/P15,"") -> 0.01311087 | Q17: =IFERROR(Q16/Q15,"") -> 0.020219988 | R17: =IFERROR(R16/R15,"") -> -0.031914675 | AJ17: 0.25
B18: Contract Type | E18: =IF(ISBLANK(Contract_Type),"",Contract_Type) -> Fixed Price | O18: CM% | P18: =IFERROR(P10/P8-$AJ$17,"") -> 0.24196101 | Q18: =IFERROR(Q10/Q8-$AJ$17,"") -> 0.20718176 | R18: =IFERROR(R10/R8-$AJ$17,"") -> 0.47409761
B19: Change Order | E19: =IF(ISBLANK('Opportunity Details'!C5),"",'Opportunity Details'!C5) -> No
B21: If there are any staffing restrictions, enter them here:
B22: Notes | E22: This is a Proof of Concept for Boeing using ITSM Now Assist (50 licenses). It is designed to deliver rapid value for AI evaluation by Boeing.
B25: Roles and Rates
B26: Bill Rate: Onshore/ Offshore | C26: Billing Location | D26: Resource Location (Margin) | E26: Role Name | J26: Hours | K26: Non-Billable Hours | L26: Rack Bill Rate | M26: Discount or Premium | N26: Bill Rate | O26: Cost Rate | P26: Revenue | Q26: Cost | R26: GM/GP | S26: GM% | T26: Practice | U26: Skill #1 | V26: Skill #2 | W26: Skill #3 | X26: =CONCATENATE("Initiate Hours", " - ", Initiate_Length, " weeks") -> Initiate Hours - 1 weeks | Y26: =CONCATENATE("Plan Hours", " - ", Plan_Length, " weeks") -> Plan Hours - 1 weeks | Z26: =CONCATENATE("Execute Hours", " - ", Execute_Length, " weeks") -> Execute Hours - 4 weeks | AA26: =CONCATENATE("Deliver Hours", " - ", Deliver_Length, " weeks") -> Deliver Hours - 1 weeks | AB26: =CONCATENATE("Close Hours", " - ", Close_Length, " weeks") -> Close Hours - 1 weeks | AC26: =CONCATENATE("Initiate Hours", " - ", Initiate_Length, " weeks") -> Initiate Hours - 1 weeks | AD26: =CONCATENATE("Plan Hours", " - ", Plan_Length, " weeks") -> Plan Hours - 1 weeks | AE26: =CONCATENATE("Execute Hours", " - ", Execute_Length, " weeks") -> Execute Hours - 4 weeks | AF26: =CONCATENATE("Deliver Hours", " - ", Deliver_Length, " weeks") -> Deliver Hours - 1 weeks | AG26: =CONCATENATE("Close Hours", " - ", Close_Length, " weeks") -> Close Hours - 1 weeks | AH26: Note | AJ26: India? | AK26: Advisory? | AL26: Role | AM26: Rack Bill Rate | AN26: Cost Rate | AO26: Total Revenue at Rack Rate | AP26: Onsite Revenue at Rack Rate | AQ26: India Revenue at Rack Rate | AR26: Revenue w/ Contingency | AS26: Cost w/ Contingency | AT26: One-Time Discount | AU26: Total Revenue | AV26: Onsite Revenue | AW26: India Revenue | AX26: Total Cost | AY26: Onsite Cost | AZ26: India Cost | BA26: Total Hours | BB26: Onsite Hours | BC26: India Hours | BD26: Onsite Contingency Hours | BE26: India Contingency Hours
B27: Onshore | C27: USA | D27: USA | E27: Project Manager | J27: =SUMIF(TandE[Billable/ Non-Billable],"Billable*",TandE[Role 1])+SUM(Role2_OvSight) -> 80 | K27: =SUMIF(TandE[Billable/ Non-Billable],"Non-Billable*",TandE[Role 1]) -> 0 | L27: =IFERROR(INDEX(Bill_Rates!$L:$L,MATCH(Pricing!$AM27,Bill_Rates!$J:$J,0)),"") -> 219 | N27: =IFERROR(L27+M27,"") -> 219 | O27: =IFERROR(INDEX(Bill_Rates!$O:$O,MATCH($AN27,Bill_Rates!$J:$J,0)),"") -> 123 | P27: =IFERROR(N27*J27,"") -> 17520 | Q27: =IFERROR((J27+K27)*O27,"") -> 9840 | R27: =IFERROR(P27-Q27,"") -> 7680 | S27: =IFERROR(R27/P27,"") -> 0.43835616 | T27: PMO | X27: 10 | Y27: 10 | Z27: 10 | AA27: 10 | AB27: 10 | AC27: ='T&E Summary'!D11 -> 10 | AD27: ='T&E Summary'!E11 -> 10 | AE27: ='T&E Summary'!F11 -> 40 | AF27: ='T&E Summary'!G11 -> 10 | AG27: ='T&E Summary'!H11 -> 10 | AH27: 10 hrs per week | AK27: =IF(OR(G27="Change Management",G27="Enablement",G27="Strategy"),G27,"") | AL27: =E27 -> Project Manager | AM27: =E$16&C27&AJ27&F27&AK27&H27&E27 -> USAUSAProject Manager | AN27: =E$16&D27&H27&E27 -> USAUSAProject Manager | AO27: =IFERROR(L27*J27,"") -> 17520 | AP27: =IFERROR(AO27-AQ27,"") -> 17520 | AQ27: =IF(D27="India",AO27,0) -> 0 | AR27: =IFERROR(P27+P27/$P$42*$P$43,"") -> 20148 | AS27: =IFERROR(Q27+Q27/$Q$42*$Q$43,"") -> 11316 | AT27: =IFERROR(P27/$P$42*$P$44,"") -> -643.01688 | AU27: =IFERROR(AR27+AT27,"") -> 19504.983 | AV27: =IFERROR(AU27-AW27,"") -> 19504.983 | AW27: =IF(D27="India",AU27,0) -> 0 | AX27: =AS27 -> 11316 | AY27: =IFERROR(AX27-AZ27,"") -> 11316 | AZ27: =IF(D27="India",AX27,0) -> 0
B28: Onshore | C28: {=IFERROR(_xlfn.IFS(B28="Onshore",$E$16,B28="Offshore","India"),"")} -> USA | D28: USA | E28: Solution Architect | J28: =SUMIF(TandE[Billable/ Non-Billable],"Billable*",TandE[Role 2])+SUM(Role2_OvSight) -> 79 | K28: =SUMIF(TandE[Billable/ Non-Billable],"Non-Billable*",TandE[Role 2]) -> 0 | L28: =IFERROR(INDEX(Bill_Rates!$L:$L,MATCH(Pricing!$AM28,Bill_Rates!$J:$J,0)),"") -> 289 | M28: 50 | N28: =IFERROR(L28+M28,"") -> 339 | O28: =IFERROR(INDEX(Bill_Rates!$O:$O,MATCH($AN28,Bill_Rates!$J:$J,0)),"") -> 178 | P28: =IFERROR(N28*J28,"") -> 26781 | Q28: =IFERROR((J28+K28)*O28,"") -> 14062 | R28: =IFERROR(P28-Q28,"") -> 12719 | S28: =IFERROR(R28/P28,"") -> 0.47492625 | T28: Technology | U28: AI Now Assist ITSM | X28: 2 | Z28: 8 | AA28: 8 | AB28: 2 | AC28: ='T&E Summary'!D12 -> 2 | AD28: ='T&E Summary'!E12 -> 31 | AE28: ='T&E Summary'!F12 -> 36 | AF28: ='T&E Summary'!G12 -> 8 | AG28: ='T&E Summary'!H12 -> 2 | AK28: =IF(OR(G28="Change Management",G28="Enablement",G28="Strategy"),G28,"") | AL28: =E28 -> Solution Architect | AM28: =E$16&C28&AJ28&F28&AK28&H28&E28 -> USAUSASolution Architect | AN28: =E$16&D28&H28&E28 -> USAUSASolution Architect | AO28: =IFERROR(L28*J28,"") -> 22831 | AP28: =IFERROR(AO28-AQ28,"") -> 22831 | AQ28: =IF(D28="India",AO28,0) -> 0 | AR28: =IFERROR(P28+P28/$P$42*$P$43,"") -> 30798.15 | AS28: =IFERROR(Q28+Q28/$Q$42*$Q$43,"") -> 16171.3 | AT28: =IFERROR(P28/$P$42*$P$44,"") -> -982.91296 | AU28: =IFERROR(AR28+AT28,"") -> 29815.237 | AV28: =IFERROR(AU28-AW28,"") -> 29815.237 | AW28: =IF(D28="India",AU28,0) -> 0 | AX28: =AS28 -> 16171.3 | AY28: =IFERROR(AX28-AZ28,"") -> 16171.3 | AZ28: =IF(D28="India",AX28,0) -> 0
B29: Onshore | C29: {=IFERROR(_xlfn.IFS(B29="Onshore",$E$16,B29="Offshore","India"),"")} -> USA | D29: USA | E29: Business Process Consultant | J29: =SUMIF(TandE[Billable/ Non-Billable],"Billable*",TandE[Role 3])+SUM(Role3_OvSight) -> 120 | K29: =SUMIF(TandE[Billable/ Non-Billable],"Non-Billable*",TandE[Role 3]) -> 0 | L29: =IFERROR(INDEX(Bill_Rates!$L:$L,MATCH(Pricing!$AM29,Bill_Rates!$J:$J,0)),"") -> 289 | N29: =IFERROR(L29+M29,"") -> 289 | O29: =IFERROR(INDEX(Bill_Rates!$O:$O,MATCH($AN29,Bill_Rates!$J:$J,0)),"") -> 137 | P29: =IFERROR(N29*J29,"") -> 34680 | Q29: =IFERROR((J29+K29)*O29,"") -> 16440 | R29: =IFERROR(P29-Q29,"") -> 18240 | S29: =IFERROR(R29/P29,"") -> 0.52595156 | T29: Technology | U29: AI Now Assist ITSM | X29: 2 | Z29: 8 | AA29: 4 | AB29: 2 | AC29: ='T&E Summary'!D13 -> 2 | AD29: ='T&E Summary'!E13 -> 40 | AE29: ='T&E Summary'!F13 -> 72 | AF29: ='T&E Summary'!G13 -> 4 | AG29: ='T&E Summary'!H13 -> 2 | AK29: =IF(OR(G29="Change Management",G29="Enablement",G29="Strategy"),G29,"") | AL29: =E29 -> Business Process Consultant | AM29: =E$16&C29&AJ29&F29&AK29&H29&E29 -> USAUSABusiness Process Consultant | AN29: =E$16&D29&H29&E29 -> USAUSABusiness Process Consultant | AO29: =IFERROR(L29*J29,"") -> 34680 | AP29: =IFERROR(AO29-AQ29,"") -> 34680 | AQ29: =IF(D29="India",AO29,0) -> 0 | AR29: =IFERROR(P29+P29/$P$42*$P$43,"") -> 39882 | AS29: =IFERROR(Q29+Q29/$Q$42*$Q$43,"") -> 18906 | AT29: =IFERROR(P29/$P$42*$P$44,"") -> -1272.8211 | AU29: =IFERROR(AR29+AT29,"") -> 38609.179 | AV29: =IFERROR(AU29-AW29,"") -> 38609.179 | AW29: =IF(D29="India",AU29,0) -> 0 | AX29: =AS29 -> 18906 | AY29: =IFERROR(AX29-AZ29,"") -> 18906 | AZ29: =IF(D29="India",AX29,0) -> 0
B30: Offshore | C30: {=IFERROR(_xlfn.IFS(B30="Onshore",$E$16,B30="Offshore","India"),"")} -> India | D30: India | E30: Senior Technical Consultant | J30: =SUMIF(TandE[Billable/ Non-Billable],"Billable*",TandE[Role 4])+SUM(Role4_OvSight) -> 154 | K30: =SUMIF(TandE[Billable/ Non-Billable],"Non-Billable*",TandE[Role 4]) -> 0 | L30: =IFERROR(INDEX(Bill_Rates!$L:$L,MATCH(Pricing!$AM30,Bill_Rates!$J:$J,0)),"") -> 95 | N30: =IFERROR(L30+M30,"") -> 95 | O30: =IFERROR(INDEX(Bill_Rates!$O:$O,MATCH($AN30,Bill_Rates!$J:$J,0)),"") -> 25.37422 | P30: =IFERROR(N30*J30,"") -> 14630 | Q30: =IFERROR((J30+K30)*O30,"") -> 3907.6299 | R30: =IFERROR(P30-Q30,"") -> 10722.37 | S30: =IFERROR(R30/P30,"") -> 0.73290295 | T30: Technology | U30: AI Now Assist ITSM | AA30: 20 | AB30: 10 | AC30: ='T&E Summary'!D14 -> 0 | AD30: ='T&E Summary'!E14 -> 0 | AE30: ='T&E Summary'!F14 -> 124 | AF30: ='T&E Summary'!G14 -> 20 | AG30: ='T&E Summary'!H14 -> 10 | AK30: =IF(OR(G30="Change Management",G30="Enablement",G30="Strategy"),G30,"") | AL30: =E30 -> Senior Technical Consultant | AM30: =E$16&C30&AJ30&F30&AK30&H30&E30 -> USAIndiaSenior Technical Consultant | AN30: =E$16&D30&H30&E30 -> USAIndiaSenior Technical Consultant | AO30: =IFERROR(L30*J30,"") -> 14630 | AP30: =IFERROR(AO30-AQ30,"") -> 0 | AQ30: =IF(D30="India",AO30,0) -> 14630 | AR30: =IFERROR(P30+P30/$P$42*$P$43,"") -> 16824.5 | AS30: =IFERROR(Q30+Q30/$Q$42*$Q$43,"") -> 4493.7744 | AT30: =IFERROR(P30/$P$42*$P$44,"") -> -536.94845 | AU30: =IFERROR(AR30+AT30,"") -> 16287.552 | AV30: =IFERROR(AU30-AW30,"") -> 0 | AW30: =IF(D30="India",AU30,0) -> 16287.552 | AX30: =AS30 -> 4493.7744 | AY30: =IFERROR(AX30-AZ30,"") -> 0 | AZ30: =IF(D30="India",AX30,0) -> 4493.7744
B31: Onshore | C31: {=IFERROR(_xlfn.IFS(B31="Onshore",$E$16,B31="Offshore","India"),"")} -> USA | D31: USA | E31: Workflow/Practice Strategist | J31: =SUMIF(TandE[Billable/ Non-Billable],"Billable*",TandE[Role 5])+SUM(Role5_OvSight) -> 52 | K31: =SUMIF(TandE[Billable/ Non-Billable],"Non-Billable*",TandE[Role 5]) -> 0 | L31: =IFERROR(INDEX(Bill_Rates!$L:$L,MATCH(Pricing!$AM31,Bill_Rates!$J:$J,0)),"") -> 339 | M31: 20 | N31: =IFERROR(L31+M31,"") -> 359 | O31: =IFERROR(INDEX(Bill_Rates!$O:$O,MATCH($AN31,Bill_Rates!$J:$J,0)),"") -> 211 | P31: =IFERROR(N31*J31,"") -> 18668 | Q31: =IFERROR((J31+K31)*O31,"") -> 10972 | R31: =IFERROR(P31-Q31,"") -> 7696 | S31: =IFERROR(R31/P31,"") -> 0.41225627 | T31: Technology | U31: AI Now Assist ITSM | X31: 2 | Y31: 2 | Z31: 2 | AA31: 2 | AB31: 2 | AC31: ='T&E Summary'!D15 -> 2 | AD31: ='T&E Summary'!E15 -> 38 | AE31: ='T&E Summary'!F15 -> 8 | AF31: ='T&E Summary'!G15 -> 2 | AG31: ='T&E Summary'!H15 -> 2 | AH31: Anusha DasFedele | AK31: =IF(OR(G31="Change Management",G31="Enablement",G31="Strategy"),G31,"") | AL31: =E31 -> Workflow/Practice Strategist | AM31: =E$16&C31&AJ31&F31&AK31&H31&E31 -> USAUSAWorkflow/Practice Strategist | AN31: =E$16&D31&H31&E31 -> USAUSAWorkflow/Practice Strategist | AO31: =IFERROR(L31*J31,"") -> 17628 | AP31: =IFERROR(AO31-AQ31,"") -> 17628 | AQ31: =IF(D31="India",AO31,0) -> 0 | AR31: =IFERROR(P31+P31/$P$42*$P$43,"") -> 21468.2 | AS31: =IFERROR(Q31+Q31/$Q$42*$Q$43,"") -> 12617.8 | AT31: =IFERROR(P31/$P$42*$P$44,"") -> -685.15063 | AU31: =IFERROR(AR31+AT31,"") -> 20783.049 | AV31: =IFERROR(AU31-AW31,"") -> 20783.049 | AW31: =IF(D31="India",AU31,0) -> 0 | AX31: =AS31 -> 12617.8 | AY31: =IFERROR(AX31-AZ31,"") -> 12617.8 | AZ31: =IF(D31="India",AX31,0) -> 0
B32: Offshore | C32: {=IFERROR(_xlfn.IFS(B32="Onshore",$E$16,B32="Offshore","India"),"")} -> India | J32: =SUMIF(TandE[Billable/ Non-Billable],"Billable*",TandE[Role 6])+SUM(Role6_OvSight) -> 0 | K32: =SUMIF(TandE[Billable/ Non-Billable],"Non-Billable*",TandE[Role 6]) -> 0 | L32: =IFERROR(INDEX(Bill_Rates!$L:$L,MATCH(Pricing!$AM32,Bill_Rates!$J:$J,0)),"") | N32: =IFERROR(L32+M32,"") | O32: =IFERROR(INDEX(Bill_Rates!$O:$O,MATCH($AN32,Bill_Rates!$J:$J,0)),"") | P32: =IFERROR(N32*J32,"") | Q32: =IFERROR((J32+K32)*O32,"") | R32: =IFERROR(P32-Q32,"") | S32: =IFERROR(R32/P32,"") | AC32: ='T&E Summary'!D16 -> 0 | AD32: ='T&E Summary'!E16 -> 0 | AE32: ='T&E Summary'!F16 -> 0 | AF32: ='T&E Summary'!G16 -> 0 | AG32: ='T&E Summary'!H16 -> 0 | AK32: =IF(OR(G32="Change Management",G32="Enablement",G32="Strategy"),G32,"") | AL32: =E32 -> 0 | AM32: =E$16&C32&AJ32&F32&AK32&H32&E32 -> USAIndia | AN32: =E$16&D32&H32&E32 -> USA | AO32: =IFERROR(L32*J32,"") | AP32: =IFERROR(AO32-AQ32,"") | AQ32: =IF(D32="India",AO32,0) -> 0 | AR32: =IFERROR(P32+P32/$P$42*$P$43,"") | AS32: =IFERROR(Q32+Q32/$Q$42*$Q$43,"") | AT32: =IFERROR(P32/$P$42*$P$44,"") | AU32: =IFERROR(AR32+AT32,"") | AV32: =IFERROR(AU32-AW32,"") | AW32: =IF(D32="India",AU32,0) -> 0 | AX32: =AS32 | AY32: =IFERROR(AX32-AZ32,"") | AZ32: =IF(D32="India",AX32,0) -> 0
B33: Offshore | C33: {=IFERROR(_xlfn.IFS(B33="Onshore",$E$16,B33="Offshore","India"),"")} -> India | J33: =SUMIF(TandE[Billable/ Non-Billable],"Billable*",TandE[Role 7])+SUM(Role7_OvSight) -> 0 | K33: =SUMIF(TandE[Billable/ Non-Billable],"Non-Billable*",TandE[Role 7]) -> 0 | L33: =IFERROR(INDEX(Bill_Rates!$L:$L,MATCH(Pricing!$AM33,Bill_Rates!$J:$J,0)),"") | N33: =IFERROR(L33+M33,"") | O33: =IFERROR(INDEX(Bill_Rates!$O:$O,MATCH($AN33,Bill_Rates!$J:$J,0)),"") | P33: =IFERROR(N33*J33,"") | Q33: =IFERROR((J33+K33)*O33,"") | R33: =IFERROR(P33-Q33,"") | S33: =IFERROR(R33/P33,"") | AC33: ='T&E Summary'!D17 -> 0 | AD33: ='T&E Summary'!E17 -> 0 | AE33: ='T&E Summary'!F17 -> 0 | AF33: ='T&E Summary'!G17 -> 0 | AG33: ='T&E Summary'!H17 -> 0 | AK33: =IF(OR(G33="Change Management",G33="Enablement",G33="Strategy"),G33,"") | AL33: =E33 -> 0 | AM33: =E$16&C33&AJ33&F33&AK33&H33&E33 -> USAIndia | AN33: =E$16&D33&H33&E33 -> USA | AO33: =IFERROR(L33*J33,"") | AP33: =IFERROR(AO33-AQ33,"") | AQ33: =IF(D33="India",AO33,0) -> 0 | AR33: =IFERROR(P33+P33/$P$42*$P$43,"") | AS33: =IFERROR(Q33+Q33/$Q$42*$Q$43,"") | AT33: =IFERROR(P33/$P$42*$P$44,"") | AU33: =IFERROR(AR33+AT33,"") | AV33: =IFERROR(AU33-AW33,"") | AW33: =IF(D33="India",AU33,0) -> 0 | AX33: =AS33 | AY33: =IFERROR(AX33-AZ33,"") | AZ33: =IF(D33="India",AX33,0) -> 0
B34: Onshore | C34: {=IFERROR(_xlfn.IFS(B34="Onshore",$E$16,B34="Offshore","India"),"")} -> USA | J34: =SUMIF(TandE[Billable/ Non-Billable],"Billable*",TandE[Role 8])+SUM(Role8_OvSight) -> 0 | K34: =SUMIF(TandE[Billable/ Non-Billable],"Non-Billable*",TandE[Role 8]) -> 0 | L34: =IFERROR(INDEX(Bill_Rates!$L:$L,MATCH(Pricing!$AM34,Bill_Rates!$J:$J,0)),"") | N34: =IFERROR(L34+M34,"") | O34: =IFERROR(INDEX(Bill_Rates!$O:$O,MATCH($AN34,Bill_Rates!$J:$J,0)),"") | P34: =IFERROR(N34*J34,"") | Q34: =IFERROR((J34+K34)*O34,"") | R34: =IFERROR(P34-Q34,"") | S34: =IFERROR(R34/P34,"") | AC34: ='T&E Summary'!D18 -> 0 | AD34: ='T&E Summary'!E18 -> 0 | AE34: ='T&E Summary'!F18 -> 0 | AF34: ='T&E Summary'!G18 -> 0 | AG34: ='T&E Summary'!H18 -> 0 | AK34: =IF(OR(G34="Change Management",G34="Enablement",G34="Strategy"),G34,"") | AL34: =E34 -> 0 | AM34: =E$16&C34&AJ34&F34&AK34&H34&E34 -> USAUSA | AN34: =E$16&D34&H34&E34 -> USA | AO34: =IFERROR(L34*J34,"") | AP34: =IFERROR(AO34-AQ34,"") | AQ34: =IF(D34="India",AO34,0) -> 0 | AR34: =IFERROR(P34+P34/$P$42*$P$43,"") | AS34: =IFERROR(Q34+Q34/$Q$42*$Q$43,"") | AT34: =IFERROR(P34/$P$42*$P$44,"") | AU34: =IFERROR(AR34+AT34,"") | AV34: =IFERROR(AU34-AW34,"") | AW34: =IF(D34="India",AU34,0) -> 0 | AX34: =AS34 | AY34: =IFERROR(AX34-AZ34,"") | AZ34: =IF(D34="India",AX34,0) -> 0
B35: Onshore | C35: {=IFERROR(_xlfn.IFS(B35="Onshore",$E$16,B35="Offshore","India"),"")} -> USA | J35: =SUMIF(TandE[Billable/ Non-Billable],"Billable*",TandE[Role 9])+SUM(Role9_OvSight) -> 0 | K35: =SUMIF(TandE[Billable/ Non-Billable],"Non-Billable*",TandE[Role 9]) -> 0 | L35: =IFERROR(INDEX(Bill_Rates!$L:$L,MATCH(Pricing!$AM35,Bill_Rates!$J:$J,0)),"") | N35: =IFERROR(L35+M35,"") | O35: =IFERROR(INDEX(Bill_Rates!$O:$O,MATCH($AN35,Bill_Rates!$J:$J,0)),"") | P35: =IFERROR(N35*J35,"") | Q35: =IFERROR((J35+K35)*O35,"") | R35: =IFERROR(P35-Q35,"") | S35: =IFERROR(R35/P35,"") | AC35: ='T&E Summary'!D19 -> 0 | AD35: ='T&E Summary'!E19 -> 0 | AE35: ='T&E Summary'!F19 -> 0 | AF35: ='T&E Summary'!G19 -> 0 | AG35: ='T&E Summary'!H19 -> 0 | AK35: =IF(OR(G35="Change Management",G35="Enablement",G35="Strategy"),G35,"") | AL35: =E35 -> 0 | AM35: =E$16&C35&AJ35&F35&AK35&H35&E35 -> USAUSA | AN35: =E$16&D35&H35&E35 -> USA | AO35: =IFERROR(L35*J35,"") | AP35: =IFERROR(AO35-AQ35,"") | AQ35: =IF(D35="India",AO35,0) -> 0 | AR35: =IFERROR(P35+P35/$P$42*$P$43,"") | AS35: =IFERROR(Q35+Q35/$Q$42*$Q$43,"") | AT35: =IFERROR(P35/$P$42*$P$44,"") | AU35: =IFERROR(AR35+AT35,"") | AV35: =IFERROR(AU35-AW35,"") | AW35: =IF(D35="India",AU35,0) -> 0 | AX35: =AS35 | AY35: =IFERROR(AX35-AZ35,"") | AZ35: =IF(D35="India",AX35,0) -> 0
B36: Onshore | C36: {=IFERROR(_xlfn.IFS(B36="Onshore",$E$16,B36="Offshore","India"),"")} -> USA | J36: =SUMIF(TandE[Billable/ Non-Billable],"Billable*",TandE[Role 10])+SUM(Role10_OvSight) -> 0 | K36: =SUMIF(TandE[Billable/ Non-Billable],"Non-Billable*",TandE[Role 10]) -> 0 | L36: =IFERROR(INDEX(Bill_Rates!$L:$L,MATCH(Pricing!$AM36,Bill_Rates!$J:$J,0)),"") | N36: =IFERROR(L36+M36,"") | O36: =IFERROR(INDEX(Bill_Rates!$O:$O,MATCH($AN36,Bill_Rates!$J:$J,0)),"") | P36: =IFERROR(N36*J36,"") | Q36: =IFERROR((J36+K36)*O36,"") | R36: =IFERROR(P36-Q36,"") | S36: =IFERROR(R36/P36,"") | AC36: ='T&E Summary'!D20 -> 0 | AD36: ='T&E Summary'!E20 -> 0 | AE36: ='T&E Summary'!F20 -> 0 | AF36: ='T&E Summary'!G20 -> 0 | AG36: ='T&E Summary'!H20 -> 0 | AK36: =IF(OR(G36="Change Management",G36="Enablement",G36="Strategy"),G36,"") | AL36: =E36 -> 0 | AM36: =E$16&C36&AJ36&F36&AK36&H36&E36 -> USAUSA | AN36: =E$16&D36&H36&E36 -> USA | AO36: =IFERROR(L36*J36,"") | AP36: =IFERROR(AO36-AQ36,"") | AQ36: =IF(D36="India",AO36,0) -> 0 | AR36: =IFERROR(P36+P36/$P$42*$P$43,"") | AS36: =IFERROR(Q36+Q36/$Q$42*$Q$43,"") | AT36: =IFERROR(P36/$P$42*$P$44,"") | AU36: =IFERROR(AR36+AT36,"") | AV36: =IFERROR(AU36-AW36,"") | AW36: =IF(D36="India",AU36,0) -> 0 | AX36: =AS36 | AY36: =IFERROR(AX36-AZ36,"") | AZ36: =IF(D36="India",AX36,0) -> 0
B37: Onshore | C37: {=IFERROR(_xlfn.IFS(B37="Onshore",$E$16,B37="Offshore","India"),"")} -> USA | J37: =SUMIF(TandE[Billable/ Non-Billable],"Billable*",TandE[Role 11])+SUM(Role11_OvSight) -> 0 | K37: =SUMIF(TandE[Billable/ Non-Billable],"Non-Billable*",TandE[Role 11]) -> 0 | L37: =IFERROR(INDEX(Bill_Rates!$L:$L,MATCH(Pricing!$AM37,Bill_Rates!$J:$J,0)),"") | N37: =IFERROR(L37+M37,"") | O37: =IFERROR(INDEX(Bill_Rates!$O:$O,MATCH($AN37,Bill_Rates!$J:$J,0)),"") | P37: =IFERROR(N37*J37,"") | Q37: =IFERROR((J37+K37)*O37,"") | R37: =IFERROR(P37-Q37,"") | S37: =IFERROR(R37/P37,"") | AC37: ='T&E Summary'!D21 -> 0 | AD37: ='T&E Summary'!E21 -> 0 | AE37: ='T&E Summary'!F21 -> 0 | AF37: ='T&E Summary'!G21 -> 0 | AG37: ='T&E Summary'!H21 -> 0 | AK37: =IF(OR(G37="Change Management",G37="Enablement",G37="Strategy"),G37,"") | AL37: =E37 -> 0 | AM37: =E$16&C37&AJ37&F37&AK37&H37&E37 -> USAUSA | AN37: =E$16&D37&H37&E37 -> USA | AO37: =IFERROR(L37*J37,"") | AP37: =IFERROR(AO37-AQ37,"") | AQ37: =IF(D37="India",AO37,0) -> 0 | AR37: =IFERROR(P37+P37/$P$42*$P$43,"") | AS37: =IFERROR(Q37+Q37/$Q$42*$Q$43,"") | AT37: =IFERROR(P37/$P$42*$P$44,"") | AU37: =IFERROR(AR37+AT37,"") | AV37: =IFERROR(AU37-AW37,"") | AW37: =IF(D37="India",AU37,0) -> 0 | AX37: =AS37 | AY37: =IFERROR(AX37-AZ37,"") | AZ37: =IF(D37="India",AX37,0) -> 0
B38: Onshore | C38: {=IFERROR(_xlfn.IFS(B38="Onshore",$E$16,B38="Offshore","India"),"")} -> USA | J38: =SUMIF(TandE[Billable/ Non-Billable],"Billable*",TandE[Role 12])+SUM(Role12_OvSight) -> 0 | K38: =SUMIF(TandE[Billable/ Non-Billable],"Non-Billable*",TandE[Role 12]) -> 0 | L38: =IFERROR(INDEX(Bill_Rates!$L:$L,MATCH(Pricing!$AM38,Bill_Rates!$J:$J,0)),"") | N38: =IFERROR(L38+M38,"") | O38: =IFERROR(INDEX(Bill_Rates!$O:$O,MATCH($AN38,Bill_Rates!$J:$J,0)),"") | P38: =IFERROR(N38*J38,"") | Q38: =IFERROR((J38+K38)*O38,"") | R38: =IFERROR(P38-Q38,"") | S38: =IFERROR(R38/P38,"") | AC38: ='T&E Summary'!D22 -> 0 | AD38: ='T&E Summary'!E22 -> 0 | AE38: ='T&E Summary'!F22 -> 0 | AF38: ='T&E Summary'!G22 -> 0 | AG38: ='T&E Summary'!H22 -> 0 | AK38: =IF(OR(G38="Change Management",G38="Enablement",G38="Strategy"),G38,"") | AL38: =E38 -> 0 | AM38: =E$16&C38&AJ38&F38&AK38&H38&E38 -> USAUSA | AN38: =E$16&D38&H38&E38 -> USA | AO38: =IFERROR(L38*J38,"") | AP38: =IFERROR(AO38-AQ38,"") | AQ38: =IF(D38="India",AO38,0) -> 0 | AR38: =IFERROR(P38+P38/$P$42*$P$43,"") | AS38: =IFERROR(Q38+Q38/$Q$42*$Q$43,"") | AT38: =IFERROR(P38/$P$42*$P$44,"") | AU38: =IFERROR(AR38+AT38,"") | AV38: =IFERROR(AU38-AW38,"") | AW38: =IF(D38="India",AU38,0) -> 0 | AX38: =AS38 | AY38: =IFERROR(AX38-AZ38,"") | AZ38: =IF(D38="India",AX38,0) -> 0
B39: Onshore | C39: {=IFERROR(_xlfn.IFS(B39="Onshore",$E$16,B39="Offshore","India"),"")} -> USA | J39: =SUMIF(TandE[Billable/ Non-Billable],"Billable*",TandE[Role 13])+SUM(Role13_OvSight) -> 0 | K39: =SUMIF(TandE[Billable/ Non-Billable],"Non-Billable*",TandE[Role 13]) -> 0 | L39: =IFERROR(INDEX(Bill_Rates!$L:$L,MATCH(Pricing!$AM39,Bill_Rates!$J:$J,0)),"") | N39: =IFERROR(L39+M39,"") | O39: =IFERROR(INDEX(Bill_Rates!$O:$O,MATCH($AN39,Bill_Rates!$J:$J,0)),"") | P39: =IFERROR(N39*J39,"") | Q39: =IFERROR((J39+K39)*O39,"") | R39: =IFERROR(P39-Q39,"") | S39: =IFERROR(R39/P39,"") | AC39: ='T&E Summary'!D23 -> 0 | AD39: ='T&E Summary'!E23 -> 0 | AE39: ='T&E Summary'!F23 -> 0 | AF39: ='T&E Summary'!G23 -> 0 | AG39: ='T&E Summary'!H23 -> 0 | AK39: =IF(OR(G39="Change Management",G39="Enablement",G39="Strategy"),G39,"") | AL39: =E39 -> 0 | AM39: =E$16&C39&AJ39&F39&AK39&H39&E39 -> USAUSA | AN39: =E$16&D39&H39&E39 -> USA | AO39: =IFERROR(L39*J39,"") | AP39: =IFERROR(AO39-AQ39,"") | AQ39: =IF(D39="India",AO39,0) -> 0 | AR39: =IFERROR(P39+P39/$P$42*$P$43,"") | AS39: =IFERROR(Q39+Q39/$Q$42*$Q$43,"") | AT39: =IFERROR(P39/$P$42*$P$44,"") | AU39: =IFERROR(AR39+AT39,"") | AV39: =IFERROR(AU39-AW39,"") | AW39: =IF(D39="India",AU39,0) -> 0 | AX39: =AS39 | AY39: =IFERROR(AX39-AZ39,"") | AZ39: =IF(D39="India",AX39,0) -> 0
B40: Onshore | C40: {=IFERROR(_xlfn.IFS(B40="Onshore",$E$16,B40="Offshore","India"),"")} -> USA | J40: =SUMIF(TandE[Billable/ Non-Billable],"Billable*",TandE[Role 14])+SUM(Role14_OvSight) -> 0 | K40: =SUMIF(TandE[Billable/ Non-Billable],"Non-Billable*",TandE[Role 14]) -> 0 | L40: =IFERROR(INDEX(Bill_Rates!$L:$L,MATCH(Pricing!$AM40,Bill_Rates!$J:$J,0)),"") | N40: =IFERROR(L40+M40,"") | O40: =IFERROR(INDEX(Bill_Rates!$O:$O,MATCH($AN40,Bill_Rates!$J:$J,0)),"") | P40: =IFERROR(N40*J40,"") | Q40: =IFERROR((J40+K40)*O40,"") | R40: =IFERROR(P40-Q40,"") | S40: =IFERROR(R40/P40,"") | AC40: ='T&E Summary'!D24 -> 0 | AD40: ='T&E Summary'!E24 -> 0 | AE40: ='T&E Summary'!F24 -> 0 | AF40: ='T&E Summary'!G24 -> 0 | AG40: ='T&E Summary'!H24 -> 0 | AK40: =IF(OR(G40="Change Management",G40="Enablement",G40="Strategy"),G40,"") | AL40: =E40 -> 0 | AM40: =E$16&C40&AJ40&F40&AK40&H40&E40 -> USAUSA | AN40: =E$16&D40&H40&E40 -> USA | AO40: =IFERROR(L40*J40,"") | AP40: =IFERROR(AO40-AQ40,"") | AQ40: =IF(D40="India",AO40,0) -> 0 | AR40: =IFERROR(P40+P40/$P$42*$P$43,"") | AS40: =IFERROR(Q40+Q40/$Q$42*$Q$43,"") | AT40: =IFERROR(P40/$P$42*$P$44,"") | AU40: =IFERROR(AR40+AT40,"") | AV40: =IFERROR(AU40-AW40,"") | AW40: =IF(D40="India",AU40,0) -> 0 | AX40: =AS40 | AY40: =IFERROR(AX40-AZ40,"") | AZ40: =IF(D40="India",AX40,0) -> 0
B41: Offshore | C41: {=IFERROR(_xlfn.IFS(B41="Onshore",$E$16,B41="Offshore","India"),"")} -> India | J41: =SUMIF(TandE[Billable/ Non-Billable],"Billable*",TandE[Role 15])+SUM(Role15_OvSight) -> 0 | K41: =SUMIF(TandE[Billable/ Non-Billable],"Non-Billable*",TandE[Role 15]) -> 0 | L41: =IFERROR(INDEX(Bill_Rates!$L:$L,MATCH(Pricing!$AM41,Bill_Rates!$J:$J,0)),"") | N41: =IFERROR(L41+M41,"") | O41: =IFERROR(INDEX(Bill_Rates!$O:$O,MATCH($AN41,Bill_Rates!$J:$J,0)),"") | P41: =IFERROR(N41*J41,"") | Q41: =IFERROR((J41+K41)*O41,"") | R41: =IFERROR(P41-Q41,"") | S41: =IFERROR(R41/P41,"") | AC41: ='T&E Summary'!D25 -> 0 | AD41: ='T&E Summary'!E25 -> 0 | AE41: ='T&E Summary'!F25 -> 0 | AF41: ='T&E Summary'!G25 -> 0 | AG41: ='T&E Summary'!H25 -> 0 | AK41: =IF(OR(G41="Change Management",G41="Enablement",G41="Strategy"),G41,"") | AL41: =E41 -> 0 | AM41: =E$16&C41&AJ41&F41&AK41&H41&E41 -> USAIndia | AN41: =E$16&D41&H41&E41 -> USA | AO41: =IFERROR(L41*J41,"") | AP41: =IFERROR(AO41-AQ41,"") | AQ41: =IF(D41="India",AO41,0) -> 0 | AR41: =IFERROR(P41+P41/$P$42*$P$43,"") | AS41: =IFERROR(Q41+Q41/$Q$42*$Q$43,"") | AT41: =IFERROR(P41/$P$42*$P$44,"") | AU41: =IFERROR(AR41+AT41,"") | AV41: =IFERROR(AU41-AW41,"") | AW41: =IF(D41="India",AU41,0) -> 0 | AX41: =AS41 | AY41: =IFERROR(AX41-AZ41,"") | AZ41: =IF(D41="India",AX41,0) -> 0
B42: Subtotal | J42: =SUM(J27:J41) -> 485 | K42: =SUM(K27:K41) -> 0 | P42: =SUM(P27:P41) -> 112279 | Q42: =SUM(Q27:Q41) -> 55221.63 | R42: =SUM(R27:R41) -> 57057.37 | S42: =IFERROR(R42/P42,"") -> 0.5081749 | AJ42: =IF(C27="India","India","") | AK42: =F42&G42 | AO42: =SUM(AO27:AO41) -> 107289 | AP42: =SUM(AP27:AP41) -> 92659 | AQ42: =SUM(AQ27:AQ41) -> 14630 | AR42: =SUM(AR27:AR41) -> 129120.85 | AS42: =SUM(AS27:AS41) -> 63504.874 | AT42: =SUM(AT27:AT41) -> -4120.85 | AU42: =SUM(AU27:AU41) -> 125000 | AV42: =SUM(AV27:AV41) -> 108712.45 | ... AZ42: =SUM(AZ27:AZ41) -> 4493.7744 | BA42: =J42 -> 485 | BB42: =BA42-BC42 -> 331 | BC42: =SUMIF(D27:D41,"India",J27:J41) -> 154 | BD42: =BB42/BA42*J43 -> 49.65 | BE42: =BC42/BA42*J43 -> 23.1
B43: Contingency (for fixed-price only) | J43: =IFERROR(P43/(P42/J42),"") -> 72.75 | K43: =IFERROR(P43/(P42/K42),"") | P43: =IF($E$18="Fixed Price", $P$42*0.15,0) -> 16841.85 | Q43: =IFERROR(P43*(1-S42),"") -> 8283.2445 | R43: =IFERROR(P43-Q43,"") -> 8558.6055 | S43: =IFERROR(R43/P43,"") -> 0.5081749
B44: One-time discount | P44: -4120.85
B45: Total | J45: =IFERROR(J42+J43,"") -> 557.75 | K45: =IFERROR(K42+K43,0) -> 0 | P45: =SUM(P42:P44) -> 125000 | Q45: =SUM(Q42:Q43) -> 63504.874 | R45: =P45-Q45 -> 61495.126 | S45: =IFERROR(R45/P45,"") -> 0.49196101
B48: Deal Review Questions
B49: What percentage of TCV will be invoiced upon SOW signature? | AJ49: Note:
B50: Is there any restriction to using global delivery on this project? | I50: =India_Leverage -> No | J50: If yes, then explain: | AJ50: Bill rate is based on client location, whether the resource is in India or not.
B51: What is the primary client delivery location? | AJ51: Cost rate is based on billing location, resource location and resource.
B52: Is our proposal or SOW solution-based with defined scope and deliverables? | J52: If no, then engagement type:
B53: Are any specialized skills, including security clearances, required to deliver the project? | J53: If yes, then list skills:
B54: Have we successfully delivered this type of project previously? Do we have assumptions to mitigate any substantial risks?
B55: Are any of the standard SOW terms and conditions to be modified? | J55: If yes, then list modifications:
B56: If any fields in this Pricing Tool are highlighted in red, then provide reason(s).
B57: Will any NewRocket product licenses be included as part of this opportunity? | J57: If yes, then list products: | O57: Term (years): | Q57: Price per yr:
B58: Notes
D62: Account | E62: =E11 -> Boeing ITSM Now Assist AI POC
D63: Practice | E63: =E9 -> Technology
D64: Opportunity Owner | E64: =E14 -> Harry Tomczyk
D65: Client Location | E65: =E16 -> USA
D66: Change Order | E66: =E19 -> No
D67: Currency | E67: =E17 -> USD
D68: TCV | E68: =P8 -> 125000
D69: CM% | E69: =P11 -> 0.49196101
D70: Avg Rate | E70: =P14 -> 224.11475
D71: Rate discount | E71: =IFERROR(-P17,"") -> -0.01311087
D72: Pre-payment | E72: =I49 -> 0
D73: India Restriction | E73: =I50 -> No
D74: India Hours | E74: =R13 -> 0.31752577

Sheet Tasks and Estimates
B1: Phase | C1: Start Week | D1: End Week | E1: Task | F1: Description | G1: Assumption | H1: Hide Row from SOW | I1: Practice | J1: Presales Notes (Internal) | K1: Billable/ Non-Billable | L1: Role 1 | M1: Role 2 | N1: Role 3 | O1: Role 4 | P1: Role 5 | Q1: Role 6 | R1: Role 7 | S1: Role 8 | T1: Role 9 | U1: Role 10 | V1: Role 11 | W1: Role 12 | X1: Role 13 | Y1: Role 14 | Z1: Role 15
A2: Roles | B2: Intentionally left blank. | C2: Intentionally left blank. | D2: Intentionally left blank. | E2: Intentionally left blank. | F2: Intentionally left blank. | G2: Intentionally left blank. | H2: Intentionally left blank. | I2: Intentionally left blank. | J2: Intentionally left blank. | K2: Roles | L2: =Role_1 -> Project Manager-PMO | M2: =Role_2 -> Solution Architect-Technology | N2: =Role_3 -> Business Process Consultant-Technology | O2: =Role_4 -> Senior Technical Consultant-Technology | P2: =Role_5 -> Workflow/Practice Strategist-Technology | Q2: =Role_6 -> - | R2: =Role_7 -> - | S2: =Role_8 -> - | T2: =Role_9 -> - | U2: =Role_10 -> - | V2: =Role_11 -> - | W2: =Role_12 -> - | X2: =Role_13 -> - | Y2: =Role_14 -> - | Z2: =Role_15 -> -
A3: Initiate | B3: Initiate | C3: 1 | D3: =INITIATE_END -> 1 | K3: Billable
B4: Initiate | C4: 1 | D4: =INITIATE_END -> 1 | K4: Billable
B5: Initiate | C5: 1 | D5: =INITIATE_END -> 1 | K5: Billable
B6: Initiate | C6: 1 | D6: =INITIATE_END -> 1 | K6: Billable
B7: Initiate | C7: 1 | D7: =INITIATE_END -> 1 | K7: Billable
B8: Initiate | C8: 1 | D8: =INITIATE_END -> 1 | K8: Billable
B9: Initiate | C9: 1 | D9: =INITIATE_END -> 1 | K9: Billable
B10: Initiate | C10: 1 | D10: =INITIATE_END -> 1 | K10: Billable
B11: Initiate | C11: 1 | D11: =INITIATE_END -> 1 | K11: Billable
B12: Initiate | C12: 1 | D12: =INITIATE_END -> 1 | K12: Billable
B13: Initiate | C13: 1 | D13: =INITIATE_END -> 1 | E13: Initiate Oversight & Calculated Hours | F13: The calculated hours in the Initiate cover the project setup, onboarding of resources. It also covers an internal team kick-off, setting up the base project plan and conducting a formal project initiation with the customer to review goals, objectives, scope and other engagement information. | K13: Billable | L13: =ROUND(Pricing!$X27*Initiate_Length,0) -> 10 | M13: =ROUND(Pricing!$X28*Initiate_Length,0) -> 2 | N13: =ROUND(Pricing!$X29*Initiate_Length,0) -> 2 | O13: =ROUND(Pricing!$X30*Initiate_Length,0) -> 0 | P13: =ROUND(Pricing!$X31*Initiate_Length,0) -> 2 | Q13: =ROUND(Pricing!$X32*Initiate_Length,0) -> 0 | R13: =ROUND(Pricing!$X33*Initiate_Length,0) -> 0 | S13: =ROUND(Pricing!$X34*Initiate_Length,0) -> 0 | T13: =ROUND(Pricing!$X35*Initiate_Length,0) -> 0 | U13: =ROUND(Pricing!$X36*Initiate_Length,0) -> 0 | V13: =ROUND(Pricing!$X37*Initiate_Length,0) -> 0 | W13: =ROUND(Pricing!$X38*Initiate_Length,0) -> 0 | X13: =ROUND(Pricing!$X39*Initiate_Length,0) -> 0 | Y13: =ROUND(Pricing!$X40*Initiate_Length,0) -> 0 | Z13: =ROUND(Pricing!$X41*Initiate_Length,0) -> 0
A14: Plan | B14: Plan | C14: =PLAN_START -> 2 | D14: =PLAN_END -> 2 | E14: Now Assist Agentic AI Workshop | K14: Billable | M14: 4 | N14: 4 | P14: 4
B15: Plan | C15: =PLAN_START -> 2 | D15: =PLAN_END -> 2 | E15: Use Case Development | G15: Time based, implementation is limited to up to 3 use cases | K15: Billable | M15: 4 | N15: 4 | P15: 4
B16: Plan | C16: =PLAN_START -> 2 | D16: =PLAN_END -> 2 | E16: Story Development and Review | K16: Billable | M16: 5 | N16: 10
B17: Plan | C17: =PLAN_START -> 2 | D17: =PLAN_END -> 2 | E17: Business Process Map Workshop (Use-Case Based) | G17: Limited to the single use case identified from Use Case Dev above | K17: Billable | N17: 4 | P17: 4
B18: Plan | C18: =PLAN_START -> 2 | D18: =PLAN_END -> 2 | E18: Now Assist Agentic AI Accelerator Pack | K18: Billable
B19: Plan | C19: =PLAN_START -> 2 | D19: =PLAN_END -> 2 | E19: Boeing AI Roadmap Maturation Workshops | F19: Review and update existing customer AI roadmap, including integration recommendations for 3rd party systems (moveworks for example) | K19: Billable | M19: 8 | N19: 8 | P19: 10
B20: Plan | C20: =PLAN_START -> 2 | D20: =PLAN_END -> 2 | E20: Value Realization Dashboard Workshop | F20: Value realization dashboard use case development in support of AI Roadmap | K20: Billable | M20: 4 | N20: 4 | P20: 8
B21: Plan | C21: =PLAN_START -> 2 | D21: =PLAN_END -> 2 | E21: Integrations Evaluation and Recommendations Workshop | F21: Review of existing Boeing 3rd party systems, such as Moveworks, and develop integration recommendations | K21: Billable | M21: 4 | N21: 4 | P21: 4
B22: Plan | C22: =PLAN_START -> 2 | D22: =PLAN_END -> 2 | E22: AI Governance Memo | F22: Governance framework memo for AI | G22: deliverable | K22: Billable | M22: 2 | N22: 2 | P22: 2
B23: Plan | C23: =PLAN_START -> 2 | D23: =PLAN_END -> 2 | K23: Billable
B24: Plan | C24: =PLAN_START -> 2 | D24: =PLAN_END -> 2 | K24: Billable
B25: Plan | C25: =PLAN_START -> 2 | D25: =PLAN_END -> 2 | K25: Billable
B26: Plan | C26: =PLAN_START -> 2 | D26: =PLAN_END -> 2 | K26: Billable
B27: Plan | C27: =PLAN_START -> 2 | D27: =PLAN_END -> 2 | K27: Billable
B28: Plan | C28: =PLAN_START -> 2 | D28: =PLAN_END -> 2 | K28: Billable
B29: Plan | C29: =PLAN_START -> 2 | D29: =PLAN_END -> 2 | K29: Billable
B30: Plan | C30: =PLAN_START -> 2 | D30: =PLAN_END -> 2 | K30: Billable
B31: Plan | C31: =PLAN_START -> 2 | D31: =PLAN_END -> 2 | K31: Billable
B32: Plan | C32: =PLAN_START -> 2 | D32: =PLAN_END -> 2 | K32: Billable
B33: Plan | C33: =PLAN_START -> 2 | D33: =PLAN_END -> 2 | K33: Billable
B34: Plan | C34: =PLAN_START -> 2 | D34: =PLAN_END -> 2 | K34: Billable
... B58: Plan | C58: =PLAN_START -> 2 | D58: =PLAN_END -> 2 | K58: Billable
B59: Plan | C59: =PLAN_START -> 2 | D59: =PLAN_END -> 2 | E59: Plan Oversight & Calculated Hours | F59: This covers any oversight necessary during the plan phase to coordinate meetings, schedule workshops, updating project plan, etc. In addition for the PM it covers the finalization of the Project Plan. | K59: Billable | L59: =ROUND(Pricing!$Y27*Plan_Length,0) -> 10 | M59: =ROUND(Pricing!$Y28*Plan_Length,0) -> 0 | N59: =ROUND(Pricing!$Y29*Plan_Length,0) -> 0 | O59: =ROUND(Pricing!$Y30*Plan_Length,0) -> 0 | P59: =ROUND(Pricing!$Y31*Plan_Length,0) -> 2 | Q59: =ROUND(Pricing!$Y32*Plan_Length,0) -> 0 | R59: =ROUND(Pricing!$Y33*Plan_Length,0) -> 0 | S59: =ROUND(Pricing!$Y34*Plan_Length,0) -> 0 | T59: =ROUND(Pricing!$Y35*Plan_Length,0) -> 0 | U59: =ROUND(Pricing!$Y36*Plan_Length,0) -> 0 | V59: =ROUND(Pricing!$Y37*Plan_Length,0) -> 0 | W59: =ROUND(Pricing!$Y38*Plan_Length,0) -> 0 | X59: =ROUND(Pricing!$Y39*Plan_Length,0) -> 0 | Y59: =ROUND(Pricing!$Y40*Plan_Length,0) -> 0 | Z59: =ROUND(Pricing!$Y41*Plan_Length,0) -> 0
B60: Plan | C60: =PLAN_END -> 2 | D60: =PLAN_END -> 2 | E60: Workshop for Testing and Test Plan Document Creation | J60: Remove this if the Testing package is not being sold | K60: Billable | Z60: =20*0 -> 0
A61: Execute | B61: Execute | C61: =EXECUTE_START -> 3 | D61: =EXECUTE_END -> 6 | E61: Now Assist Implementation - up to 3 use cases | F61: Portal to include enhanced widgets, layout and functionality as determined during the design phase. Standard out of the box pages / functionality will be implemented for anything that was not enhanced during the design phase. | G61: Limited to ITSM based on 50 licenses purchased for POC, halftime TC - 3 sprints | K61: Billable | O61: 120
B62: Execute | C62: =EXECUTE_START -> 3 | D62: =EXECUTE_END -> 6 | E62: Use Case Documentation | F62: Business Case, ROI documentation creation | K62: Billable | N62: 40
B63: Execute | C63: =EXECUTE_START -> 3 | D63: =EXECUTE_END -> 6 | E63: Configuration Runbook Creation | F63: Creation of configurations document to capture existin Now Assist config changes and NR AI Agent product configurations | K63: Billable | M63: 4 | O63: 4
B64: Execute | C64: =EXECUTE_START -> 3 | D64: =EXECUTE_END -> 6 | K64: Billable
B65: Execute | C65: =EXECUTE_START -> 3 | D65: =EXECUTE_END -> 6 | K65: Billable
B66: Execute | C66: =EXECUTE_START -> 3 | D66: =EXECUTE_END -> 6 | K66: Billable
B67: Execute | C67: =EXECUTE_START -> 3 | D67: =EXECUTE_END -> 6 | K67: Billable
B68: Execute | C68: =EXECUTE_START -> 3 | D68: =EXECUTE_END -> 6 | K68: Billable
B69: Execute | C69: =EXECUTE_START -> 3 | D69: =EXECUTE_END -> 6 | K69: Billable
B70: Execute | C70: =EXECUTE_START -> 3 | D70: =EXECUTE_END -> 6 | K70: Billable
B71: Execute | C71: =EXECUTE_START -> 3 | D71: =EXECUTE_END -> 6 | K71: Billable
B72: Execute | C72: =EXECUTE_START -> 3 | D72: =EXECUTE_END -> 6 | K72: Billable
B73: Execute | C73: =EXECUTE_START -> 3 | D73: =EXECUTE_END -> 6 | K73: Billable
B74: Execute | C74: =EXECUTE_START -> 3 | D74: =EXECUTE_END -> 6 | K74: Billable
B75: Execute | C75: =EXECUTE_START -> 3 | D75: =EXECUTE_END -> 6 | K75: Billable
... B122: Execute | C122: =EXECUTE_START -> 3 | D122: =EXECUTE_END -> 6 | K122: Billable
B123: Execute | C123: =EXECUTE_START -> 3 | D123: =EXECUTE_END -> 6 | E123: Execute Oversight & Calculated Hours | F123: This covers the hours for the BA and/or SA to do the sprint demos, unit testing. Then for the PM it covers the oversight to manage the project during the Execute phase. | K123: Billable | L123: =ROUND(Pricing!$Z27*Execute_Length,0) -> 40 | M123: =ROUND(Pricing!$Z28*Execute_Length,0) -> 32 | N123: =ROUND(Pricing!$Z29*Execute_Length,0) -> 32 | O123: =ROUND(Pricing!$Z30*Execute_Length,0) -> 0 | P123: =ROUND(Pricing!$Z31*Execute_Length,0) -> 8 | Q123: =ROUND(Pricing!$Z32*Execute_Length,0) -> 0 | R123: =ROUND(Pricing!$Z33*Execute_Length,0) -> 0 | S123: =ROUND(Pricing!$Z34*Execute_Length,0) -> 0 | T123: =ROUND(Pricing!$Z35*Execute_Length,0) -> 0 | U123: =ROUND(Pricing!$Z36*Execute_Length,0) -> 0 | V123: =ROUND(Pricing!$Z37*Execute_Length,0) -> 0 | W123: =ROUND(Pricing!$Z38*Execute_Length,0) -> 0 | X123: =ROUND(Pricing!$Z39*Execute_Length,0) -> 0 | Y123: =ROUND(Pricing!$Z40*Execute_Length,0) -> 0 | Z123: =ROUND(Pricing!$Z41*Execute_Length,0) -> 0
B124: Execute | C124: =EXECUTE_START -> 3 | D124: =EXECUTE_END -> 6 | E124: Create System Test Cases & System Test Execution Report | F124: Develop test cases as per agreed Test plan document. Execute system test cases E2E which showcase test execution status of each requirement. | J124: Remove if not selling testing package. If you are keeping, make srue Agile for practice is set. | K124: Billable | Z124: =(Execute_Length*40)*0.5*0 -> 0
B125: Deliver | C125: =DELIVER_START -> 7 | D125: =DELIVER_END -> 7 | E125: Smoke test of UAT Environment & UAT Support | F125: E2E Smoke test of code migrated to UAT environment. Includes Customer User support & Defect Management | J125: Remove if not selling testing package. | K125: Billable | Z125: =(Deliver_Length*40)*0.3*0 -> 0
B126: Deliver | C126: =DELIVER_START -> 7 | D126: =DELIVER_END -> 7 | E126: Training Preparation | F126: Review training scope and the final content to be included in training based on the Deploy stage configurations. | J126: Leave to 2 hours unless large engagement then increase to 4. | K126: Billable
B127: Deliver | C127: =DELIVER_START -> 7 | D127: =DELIVER_END -> 7 | E127: Create Training Materials | F127: Up to 1 Quick Reference Guide included - Now Assist ITSM | G127: • Training Materials will be limited to 1 Quick Reference Guide (QRG) • Training Materials will be in English and any other languages will be done by the Client | J127: Adjust based on notes in Description: QRGs are correctly scoped unless the customer has a specific template they want to use. Add two hours. Alternative is to list the QRG as 8 to 10 hours for 3 to 4 pages of content. The PPT presentation is per application. Depending on the application, PPTs may take between 12 and 16 hours to complete. The Full Guide option should say 16 hours per application. Example: Incident Management Training Guide = 16 hours, Incident and Change Management = 32 hours, a full ITSM suite = 48 hours. Will need to add Video Demonstrations. Each video demonstration will be between 2 minutes and 8 minutes in length and cover individual topics. One hour should be allotted for every 5 minutes of video demo created. | K127: Billable
B128: Deliver | C128: =DELIVER_START -> 7 | D128: =DELIVER_END -> 7 | E128: Training Sessions | F128: Perform Now Assist ITSm training for end-users. | G128: • Trainings will be limited to 2 training sessions for each module (6 total hours) • Trainings will be done via Train the Trainer Method • Training will be done remotely • Training will be provided in English | J128: Adjust based on notes in Description: PER APPLICATION: Onsite training up to 4 hours per application. Remote training up to 3 hours per application. | K128: Billable
B129: Deliver | C129: =DELIVER_START -> 7 | D129: =DELIVER_END -> 7 | K129: Billable
B130: Deliver | C130: =DELIVER_START -> 7 | D130: =DELIVER_END -> 7 | K130: Billable
B131: Deliver | C131: =DELIVER_START -> 7 | D131: =DELIVER_END -> 7 | K131: Billable
B132: Deliver | C132: =DELIVER_START -> 7 | D132: =DELIVER_END -> 7 | K132: Billable
B133: Deliver | C133: =DELIVER_START -> 7 | D133: =DELIVER_END -> 7 | K133: Billable
B134: Deliver | C134: =DELIVER_START -> 7 | D134: =DELIVER_END -> 7 | K134: Billable
B135: Deliver | C135: =DELIVER_START -> 7 | D135: =DELIVER_END -> 7 | K135: Billable
B136: Deliver | C136: =DELIVER_START -> 7 | D136: =DELIVER_END -> 7 | K136: Billable
B137: Deliver | C137: =DELIVER_START -> 7 | D137: =DELIVER_END -> 7 | K137: Billable
B138: Deliver | C138: =DELIVER_START -> 7 | D138: =DELIVER_END -> 7 | K138: Billable
B139: Deliver | C139: =DELIVER_START -> 7 | D139: =DELIVER_END -> 7 | E139: Deliver Oversight and UAT Support | F139: The calculated hours in the Deliver phase cover the updating of user stories to reflect high-lvel test steps to validate functionality. This also covers demoing of the functionaliy to Client testers ahead of UAT, and supporting the UAT as a whole. In addition this includes the time it takes to migrate to UAT, creating a rollout plan, migrate to Production, as well as updating configuration documentation. | K139: Billable | L139: =ROUND(Pricing!$AA27*Deliver_Length,0) -> 10 | M139: =ROUND(Pricing!$AA28*Deliver_Length,0) -> 8 | N139: =ROUND(Pricing!$AA29*Deliver_Length,0) -> 4 | O139: =ROUND(Pricing!$AA30*Deliver_Length,0) -> 20 | P139: =ROUND(Pricing!$AA31*Deliver_Length,0) -> 2 | Q139: =ROUND(Pricing!$AA32*Deliver_Length,0) -> 0 | R139: =ROUND(Pricing!$AA33*Deliver_Length,0) -> 0 | S139: =ROUND(Pricing!$AA34*Deliver_Length,0) -> 0 | T139: =ROUND(Pricing!$AA35*Deliver_Length,0) -> 0 | U139: =ROUND(Pricing!$AA36*Deliver_Length,0) -> 0 | V139: =ROUND(Pricing!$AA37*Deliver_Length,0) -> 0 | W139: =ROUND(Pricing!$AA38*Deliver_Length,0) -> 0 | X139: =ROUND(Pricing!$AA39*Deliver_Length,0) -> 0 | Y139: =ROUND(Pricing!$AA40*Deliver_Length,0) -> 0 | Z139: =ROUND(Pricing!$AA41*Deliver_Length,0) -> 0
A140: Close | B140: Close | C140: =CLOSE_START -> 8 | D140: =CLOSE_END -> 8 | K140: Billable
B141: Close | C141: =CLOSE_START -> 8 | D141: =CLOSE_END -> 8 | K141: Billable
B142: Close | C142: =CLOSE_START -> 8 | D142: =CLOSE_END -> 8 | K142: Billable
B143: Close | C143: =CLOSE_START -> 8 | D143: =CLOSE_END -> 8 | K143: Billable
B144: Close | C144: =CLOSE_START -> 8 | D144: =CLOSE_END -> 8 | K144: Billable
B145: Close | C145: =CLOSE_START -> 8 | D145: =CLOSE_END -> 8 | K145: Billable
B146: Close | C146: =CLOSE_START -> 8 | D146: =CLOSE_END -> 8 | E146: Close Oversight & Calculated Hours | F146: The calculated hours in the Close phase cover the post-live support in a part-time capacity unless stated otherwise. It also covers a technical knowledge transfer session with the customer, a closeout meeting and the sending of the CSAT survey and updating of the deployment record. | K146: Billable | L146: =ROUND(Pricing!$AB27*Close_Length,0) -> 10 | M146: =ROUND(Pricing!$AB28*Close_Length,0) -> 2 | N146: =ROUND(Pricing!$AB29*Close_Length,0) -> 2 | O146: =ROUND(Pricing!$AB30*Close_Length,0) -> 10 | P146: =ROUND(Pricing!$AB31*Close_Length,0) -> 2 | Q146: =ROUND(Pricing!$AB32*Close_Length,0) -> 0 | R146: =ROUND(Pricing!$AB33*Close_Length,0) -> 0 | S146: =ROUND(Pricing!$AB34*Close_Length,0) -> 0 | T146: =ROUND(Pricing!$AB35*Close_Length,0) -> 0 | U146: =ROUND(Pricing!$AB36*Close_Length,0) -> 0 | V146: =ROUND(Pricing!$AB37*Close_Length,0) -> 0 | W146: =ROUND(Pricing!$AB38*Close_Length,0) -> 0 | X146: =ROUND(Pricing!$AB39*Close_Length,0) -> 0 | Y146: =ROUND(Pricing!$AB40*Close_Length,0) -> 0 | Z146: =ROUND(Pricing!$AB41*Close_Length,0) -> 0
A147: Minimums | B147: Initiate | C147: 1 | D147: =INITIATE_END -> 1 | E147: Calculated Padding for minimums | H147: Yes | I147: Padding | K147: Billable | L147: {=IFERROR(IF(AND((SUM(_xlfn._xlws.FILTER(TandE[Role 1], (TandE[[Practice]:[Practice]]<>"Padding")*(TandE[[Phase]:[Phase]]=TandE[[#This Row],[Phase]:[Phase]])))) >0,(SUM(_xlfn._xlws.FILTER(TandE[Role 1], (TandE[[Practice]:[Practice]]<>"Padding")*(TandE[[Phase]:[Phase]]=TandE[[#This Row],[Phase]:[Phase]])))) / INDIRECT(TandE[[#This Row],[Phase]:[Phase]]& "_Length") < SUM(_xlfn._xlws.FILTER(AllocationMinimums[[Min]:[Min]], (AllocationMinimums[[Role]:[Role]]= LEFT(L$2,FIND("-",L$2)-1))*(AllocationMinimums[[Phase]:[Phase]]= TandE[[#This Row],[Phase]:[Phase]])))), (SUM(_xlfn._xlws.FILTER(AllocationMinimums[[Min]:[Min]], (AllocationMinimums[[Role]:[Role]] = LEFT(L$2,FIND("-",L$2)-1))*(AllocationMinimums[[Phase]:[Phase]]= TandE[[#This Row],[Phase]:[Phase]]))) - (SUM(_xlfn._xlws.FILTER(TandE[Role 1], (TandE[[Practice]:[Practice]] <>"Padding")*(TandE[[Phase]:[Phase]]=TandE[[#This Row],[Phase]:[Phase]])))) / INDIRECT(TandE[[#This Row],[Phase]:[Phase]]&"_Length")) *INDIRECT(TandE[[#This Row],[Phase]:[Phase]]&"_Length"), 0), 0)} -> 0 | M147: {=IFERROR(IF(AND((SUM(_xlfn._xlws.FILTER(TandE[Role 2], (TandE[[Practice]:[Practice]]<>"Padding")*(TandE[[Phase]:[Phase]]=TandE[[#This Row],[Phase]:[Phase]])))) >0,(SUM(_xlfn._xlws.FILTER(TandE[Role 2], (TandE[[Practice]:[Practice]]<>"Padding")*(TandE[[Phase]:[Phase]]=TandE[[#This Row],[Phase]:[Phase]])))) / INDIRECT(TandE[[#This Row],[Phase]:[Phase]]& "_Length") < SUM(_xlfn._xlws.FILTER(AllocationMinimums[[Min]:[Min]], (AllocationMinimums[[Role]:[Role]]= LEFT(M$2,FIND("-",M$2)-1))*(AllocationMinimums[[Phase]:[Phase]]= TandE[[#This Row],[Phase]:[Phase]])))), (SUM(_xlfn._xlws.FILTER(AllocationMinimums[[Min]:[Min]], (AllocationMinimums[[Role]:[Role]] = LEFT(M$2,FIND("-",M$2)-1))*(AllocationMinimums[[Phase]:[Phase]]= TandE[[#This Row],[Phase]:[Phase]]))) - (SUM(_xlfn._xlws.FILTER(TandE[Role 2], (TandE[[Practice]:[Practice]] <>"Padding")*(TandE[[Phase]:[Phase]]=TandE[[#This Row],[Phase]:[Phase]])))) / INDIRECT(TandE[[#This Row],[Phase]:[Phase]]&"_Length")) *INDIRECT(TandE[[#This Row],[Phase]:[Phase]]&"_Length"), 0), 0)} -> 0 | N147: {=IFERROR(IF(AND((SUM(_xlfn._xlws.FILTER(TandE[Role 3], (TandE[[Practice]:[Practice]]<>"Padding")*(TandE[[Phase]:[Phase]]=TandE[[#This Row],[Phase]:[Phase]])))) >0,(SUM(_xlfn._xlws.FILTER(TandE[Role 3], (TandE[[Practice]:[Practice]]<>"Padding")*(TandE[[Phase]:[Phase]]=TandE[[#This Row],[Phase]:[Phase]])))) / INDIRECT(TandE[[#This Row],[Phase]:[Phase]]& "_Length") < SUM(_xlfn._xlws.FILTER(AllocationMinimums[[Min]:[Min]], (AllocationMinimums[[Role]:[Role]]= LEFT(N$2,FIND("-",N$2)-1))*(AllocationMinimums[[Phase]:[Phase]]= TandE[[#This Row],[Phase]:[Phase]])))), (SUM(_xlfn._xlws.FILTER(AllocationMinimums[[Min]:[Min]], (AllocationMinimums[[Role]:[Role]] = LEFT(N$2,FIND("-",N$2)-1))*(AllocationMinimums[[Phase]:[Phase]]= TandE[[#This Row],[Phase]:[Phase]]))) - (SUM(_xlfn._xlws.FILTER(TandE[Role 3], (TandE[[Practice]:[Practice]] <>"Padding")*(TandE[[Phase]:[Phase]]=TandE[[#This Row],[Phase]:[Phase]])))) / INDIRECT(TandE[[#This Row],[Phase]:[Phase]]&"_Length")) *INDIRECT(TandE[[#This Row],[Phase]:[Phase]]&"_Length"), 0), 0)} -> 0 | O147: {=IFERROR(IF(AND((SUM(_xlfn._xlws.FILTER(TandE[Role 4], (TandE[[Practice]:[Practice]]<>"Padding")*(TandE[[Phase]:[Phase]]=TandE[[#This Row],[Phase]:[Phase]])))) >0,(SUM(_xlfn._xlws.FILTER(TandE[Role 4], (TandE[[Practice]:[Practice]]<>"Padding")*(TandE[[Phase]:[Phase]]=TandE[[#This Row],[Phase]:[Phase]])))) / INDIRECT(TandE[[#This Row],[Phase]:[Phase]]& "_Length") < SUM(_xlfn._xlws.FILTER(AllocationMinimums[[Min]:[Min]], (AllocationMinimums[[Role]:[Role]]= LEFT(O$2,FIND("-",O$2)-1))*(AllocationMinimums[[Phase]:[Phase]]= TandE[[#This Row],[Phase]:[Phase]])))), (SUM(_xlfn._xlws.FILTER(AllocationMinimums[[Min]:[Min]], (AllocationMinimums[[Role]:[Role]] = LEFT(O$2,FIND("-",O$2)-1))*(AllocationMinimums[[Phase]:[Phase]]= TandE[[#This Row],[Phase]:[Phase]]))) - (SUM(_xlfn._xlws.FILTER(TandE[Role 4], (TandE[[Practice]:[Practice]] <>"Padding")*(TandE[[Phase]:[Phase]]=TandE[[#This Row],[Phase]:[Phase]])))) / INDIRECT(TandE[[#This Row],[Phase]:[Phase]]&"_Length")) *INDIRECT(TandE[[#This Row],[Phase]:[Phase]]&"_Length"), 0), 0)} -> 0 | P147: {=IFERROR(IF(AND((SUM(_xlfn._xlws.FILTER(TandE[Role 5], (TandE[[Practice]:[Practice]]<>"Padding")*(TandE[[Phase]:[Phase]]=TandE[[#This Row],[Phase]:[Phase]])))) >0,(SUM(_xlfn._xlws.FILTER(TandE[Role 5], (TandE[[Practice]:[Practice]]<>"Padding")*(TandE[[Phase]:[Phase]]=TandE[[#This Row],[Phase]:[Phase]])))) / INDIRECT(TandE[[#This Row],[Phase]:[Phase]]& "_Length") < SUM(_xlfn._xlws.FILTER(AllocationMinimums[[Min]:[Min]], (AllocationMinimums[[Role]:[Role]]= LEFT(P$2,FIND("-",P$2)-1))*(AllocationMinimums[[Phase]:[Phase]]= TandE[[#This Row],[Phase]:[Phase]])))), (SUM(_xlfn._xlws.FILTER(AllocationMinimums[[Min]:[Min]], (AllocationMinimums[[Role]:[Role]] = LEFT(P$2,FIND("-",P$2)-1))*(AllocationMinimums[[Phase]:[Phase]]= TandE[[#This Row],[Phase]:[Phase]]))) - (SUM(_xlfn._xlws.FILTER(TandE[Role 5], (TandE[[Practice]:[Practice]] <>"Padding")*(TandE[[Phase]:[Phase]]=TandE[[#This Row],[Phase]:[Phase]])))) / INDIRECT(TandE[[#This Row],[Phase]:[Phase]]&"_Length")) *INDIRECT(TandE[[#This Row],[Phase]:[Phase]]&"_Length"), 0), 0)} -> 0 | Q147: {=IFERROR(IF(AND((SUM(_xlfn._xlws.FILTER(TandE[Role 6], (TandE[[Practice]:[Practice]]<>"Padding")*(TandE[[Phase]:[Phase]]=TandE[[#This Row],[Phase]:[Phase]])))) >0,(SUM(_xlfn._xlws.FILTER(TandE[Role 6], (TandE[[Practice]:[Practice]]<>"Padding")*(TandE[[Phase]:[Phase]]=TandE[[#This Row],[Phase]:[Phase]])))) / INDIRECT(TandE[[#This Row],[Phase]:[Phase]]& "_Length") < SUM(_xlfn._xlws.FILTER(AllocationMinimums[[Min]:[Min]], (AllocationMinimums[[Role]:[Role]]= LEFT(Q$2,FIND("-",Q$2)-1))*(AllocationMinimums[[Phase]:[Phase]]= TandE[[#This Row],[Phase]:[Phase]])))), (SUM(_xlfn._xlws.FILTER(AllocationMinimums[[Min]:[Min]], (AllocationMinimums[[Role]:[Role]] = LEFT(Q$2,FIND("-",Q$2)-1))*(AllocationMinimums[[Phase]:[Phase]]= TandE[[#This Row],[Phase]:[Phase]]))) - (SUM(_xlfn._xlws.FILTER(TandE[Role 6], (TandE[[Practice]:[Practice]] <>"Padding")*(TandE[[Phase]:[Phase]]=TandE[[#This Row],[Phase]:[Phase]])))) / INDIRECT(TandE[[#This Row],[Phase]:[Phase]]&"_Length")) *INDIRECT(TandE[[#This Row],[Phase]:[Phase]]&"_Length"), 0), 0)} -> 0 | R147: {=IFERROR(IF(AND((SUM(_xlfn._xlws.FILTER(TandE[Role 7], (TandE[[Practice]:[Practice]]<>"Padding")*(TandE[[Phase]:[Phase]]=TandE[[#This Row],[Phase]:[Phase]])))) >0,(SUM(_xlfn._xlws.FILTER(TandE[Role 7], (TandE[[Practice]:[Practice]]<>"Padding")*(TandE[[Phase]:[Phase]]=TandE[[#This Row],[Phase]:[Phase]])))) / INDIRECT(TandE[[#This Row],[Phase]:[Phase]]& "_Length") < SUM(_xlfn._xlws.FILTER(AllocationMinimums[[Min]:[Min]], (AllocationMinimums[[Role]:[Role]]= LEFT(R$2,FIND("-",R$2)-1))*(AllocationMinimums[[Phase]:[Phase]]= TandE[[#This Row],[Phase]:[Phase]])))), (SUM(_xlfn._xlws.FILTER(AllocationMinimums[[Min]:[Min]], (AllocationMinimums[[Role]:[Role]] = LEFT(R$2,FIND("-",R$2)-1))*(AllocationMinimums[[Phase]:[Phase]]= TandE[[#This Row],[Phase]:[Phase]]))) - (SUM(_xlfn._xlws.FILTER(TandE[Role 7], (TandE[[Practice]:[Practice]] <>"Padding")*(TandE[[Phase]:[Phase]]=TandE[[#This Row],[Phase]:[Phase]])))) / INDIRECT(TandE[[#This Row],[Phase]:[Phase]]&"_Length")) *INDIRECT(TandE[[#This Row],[Phase]:[Phase]]&"_Length"), 0), 0)} -> 0 | S147: {=IFERROR(IF(AND((SUM(_xlfn._xlws.FILTER(TandE[Role 8], (TandE[[Practice]:[Practice]]<>"Padding")*(TandE[[Phase]:[Phase]]=TandE[[#This Row],[Phase]:[Phase]])))) >0,(SUM(_xlfn._xlws.FILTER(TandE[Role 8], (TandE[[Practice]:[Practice]]<>"Padding")*(TandE[[Phase]:[Phase]]=TandE[[#This Row],[Phase]:[Phase]])))) / INDIRECT(TandE[[#This Row],[Phase]:[Phase]]& "_Length") < SUM(_xlfn._xlws.FILTER(AllocationMinimums[[Min]:[Min]], (AllocationMinimums[[Role]:[Role]]= LEFT(S$2,FIND("-",S$2)-1))*(AllocationMinimums[[Phase]:[Phase]]= TandE[[#This Row],[Phase]:[Phase]])))), (SUM(_xlfn._xlws.FILTER(AllocationMinimums[[Min]:[Min]], (AllocationMinimums[[Role]:[Role]] = LEFT(S$2,FIND("-",S$2)-1))*(AllocationMinimums[[Phase]:[Phase]]= TandE[[#This Row],[Phase]:[Phase]]))) - (SUM(_xlfn._xlws.FILTER(TandE[Role 8], (TandE[[Practice]:[Practice]] <>"Padding")*(TandE[[Phase]:[Phase]]=TandE[[#This Row],[Phase]:[Phase]])))) / INDIRECT(TandE[[#This Row],[Phase]:[Phase]]&"_Length")) *INDIRECT(TandE[[#This Row],[Phase]:[Phase]]&"_Length"), 0), 0)} -> 0 | T147: {=IFERROR(IF(AND((SUM(_xlfn._xlws.FILTER(TandE[Role 9], (TandE[[Practice]:[Practice]]<>"Padding")*(TandE[[Phase]:[Phase]]=TandE[[#This Row],[Phase]:[Phase]])))) >0,(SUM(_xlfn._xlws.FILTER(TandE[Role 9], (TandE[[Practice]:[Practice]]<>"Padding")*(TandE[[Phase]:[Phase]]=TandE[[#This Row],[Phase]:[Phase]])))) / INDIRECT(TandE[[#This Row],[Phase]:[Phase]]& "_Length") < SUM(_xlfn._xlws.FILTER(AllocationMinimums[[Min]:[Min]], (AllocationMinimums[[Role]:[Role]]= LEFT(T$2,FIND("-",T$2)-1))*(AllocationMinimums[[Phase]:[Phase]]= TandE[[#This Row],[Phase]:[Phase]])))), (SUM(_xlfn._xlws.FILTER(AllocationMinimums[[Min]:[Min]], (AllocationMinimums[[Role]:[Role]] = LEFT(T$2,FIND("-",T$2)-1))*(AllocationMinimums[[Phase]:[Phase]]= TandE[[#This Row],[Phase]:[Phase]]))) - (SUM(_xlfn._xlws.FILTER(TandE[Role 9], (TandE[[Practice]:[Practice]] <>"Padding")*(TandE[[Phase]:[Phase]]=TandE[[#This Row],[Phase]:[Phase]])))) / INDIRECT(TandE[[#This Row],[Phase]:[Phase]]&"_Length")) *INDIRECT(TandE[[#This Row],[Phase]:[Phase]]&"_Length"), 0), 0)} -> 0 | U147: {=IFERROR(IF(AND((SUM(_xlfn._xlws.FILTER(TandE[Role 10], (TandE[[Practice]:[Practice]]<>"Padding")*(TandE[[Phase]:[Phase]]=TandE[[#This Row],[Phase]:[Phase]])))) >0,(SUM(_xlfn._xlws.FILTER(TandE[Role 10], (TandE[[Practice]:[Practice]]<>"Padding")*(TandE[[Phase]:[Phase]]=TandE[[#This Row],[Phase]:[Phase]])))) / INDIRECT(TandE[[#This Row],[Phase]:[Phase]]& "_Length") < SUM(_xlfn._xlws.FILTER(AllocationMinimums[[Min]:[Min]], (AllocationMinimums[[Role]:[Role]]= LEFT(U$2,FIND("-",U$2)-1))*(AllocationMinimums[[Phase]:[Phase]]= TandE[[#This Row],[Phase]:[Phase]])))), (SUM(_xlfn._xlws.FILTER(AllocationMinimums[[Min]:[Min]], (AllocationMinimums[[Role]:[Role]] = LEFT(U$2,FIND("-",U$2)-1))*(AllocationMinimums[[Phase]:[Phase]]= TandE[[#This Row],[Phase]:[Phase]]))) - (SUM(_xlfn._xlws.FILTER(TandE[Role 10], (TandE[[Practice]:[Practice]] <>"Padding")*(TandE[[Phase]:[Phase]]=TandE[[#This Row],[Phase]:[Phase]])))) / INDIRECT(TandE[[#This Row],[Phase]:[Phase]]&"_Length")) *INDIRECT(TandE[[#This Row],[Phase]:[Phase]]&"_Length"), 0), 0)} -> 0 | V147: {=IFERROR(IF(AND((SUM(_xlfn._xlws.FILTER(TandE[Role 11], (TandE[[Practice]:[Practice]]<>"Padding")*(TandE[[Phase]:[Phase]]=TandE[[#This Row],[Phase]:[Phase]])))) >0,(SUM(_xlfn._xlws.FILTER(TandE[Role 11], (TandE[[Practice]:[Practice]]<>"Padding")*(TandE[[Phase]:[Phase]]=TandE[[#This Row],[Phase]:[Phase]])))) / INDIRECT(TandE[[#This Row],[Phase]:[Phase]]& "_Length") < SUM(_xlfn._xlws.FILTER(AllocationMinimums[[Min]:[Min]], (AllocationMinimums[[Role]:[Role]]= LEFT(V$2,FIND("-",V$2)-1))*(AllocationMinimums[[Phase]:[Phase]]= TandE[[#This Row],[Phase]:[Phase]])))), (SUM(_xlfn._xlws.FILTER(AllocationMinimums[[Min]:[Min]], (AllocationMinimums[[Role]:[Role]] = LEFT(V$2,FIND("-",V$2)-1))*(AllocationMinimums[[Phase]:[Phase]]= TandE[[#This Row],[Phase]:[Phase]]))) - (SUM(_xlfn._xlws.FILTER(TandE[Role 11], (TandE[[Practice]:[Practice]] <>"Padding")*(TandE[[Phase]:[Phase]]=TandE[[#This Row],[Phase]:[Phase]])))) / INDIRECT(TandE[[#This Row],[Phase]:[Phase]]&"_Length")) *INDIRECT(TandE[[#This Row],[Phase]:[Phase]]&"_Length"), 0), 0)} -> 0 | W147: {=IFERROR(IF(AND((SUM(_xlfn._xlws.FILTER(TandE[Role 12], (TandE[[Practice]:[Practice]]<>"Padding")*(TandE[[Phase]:[Phase]]=TandE[[#This Row],[Phase]:[Phase]])))) >0,(SUM(_xlfn._xlws.FILTER(TandE[Role 12], (TandE[[Practice]:[Practice]]<>"Padding")*(TandE[[Phase]:[Phase]]=TandE[[#This Row],[Phase]:[Phase]])))) / INDIRECT(TandE[[#This Row],[Phase]:[Phase]]& "_Length") < SUM(_xlfn._xlws.FILTER(AllocationMinimums[[Min]:[Min]], (AllocationMinimums[[Role]:[Role]]= LEFT(W$2,FIND("-",W$2)-1))*(AllocationMinimums[[Phase]:[Phase]]= TandE[[#This Row],[Phase]:[Phase]])))), (SUM(_xlfn._xlws.FILTER(AllocationMinimums[[Min]:[Min]], (AllocationMinimums[[Role]:[Role]] = LEFT(W$2,FIND("-",W$2)-1))*(AllocationMinimums[[Phase]:[Phase]]= TandE[[#This Row],[Phase]:[Phase]]))) - (SUM(_xlfn._xlws.FILTER(TandE[Role 12], (TandE[[Practice]:[Practice]] <>"Padding")*(TandE[[Phase]:[Phase]]=TandE[[#This Row],[Phase]:[Phase]])))) / INDIRECT(TandE[[#This Row],[Phase]:[Phase]]&"_Length")) *INDIRECT(TandE[[#This Row],[Phase]:[Phase]]&"_Length"), 0), 0)} -> 0 | X147: {=IFERROR(IF(AND((SUM(_xlfn._xlws.FILTER(TandE[Role 13], (TandE[[Practice]:[Practice]]<>"Padding")*(TandE[[Phase]:[Phase]]=TandE[[#This Row],[Phase]:[Phase]])))) >0,(SUM(_xlfn._xlws.FILTER(TandE[Role 13], (TandE[[Practice]:[Practice]]<>"Padding")*(TandE[[Phase]:[Phase]]=TandE[[#This Row],[Phase]:[Phase]])))) / INDIRECT(TandE[[#This Row],[Phase]:[Phase]]& "_Length") < SUM(_xlfn._xlws.FILTER(AllocationMinimums[[Min]:[Min]], (AllocationMinimums[[Role]:[Role]]= LEFT(X$2,FIND("-",X$2)-1))*(AllocationMinimums[[Phase]:[Phase]]= TandE[[#This Row],[Phase]:[Phase]])))), (SUM(_xlfn._xlws.FILTER(AllocationMinimums[[Min]:[Min]], (AllocationMinimums[[Role]:[Role]] = LEFT(X$2,FIND("-",X$2)-1))*(AllocationMinimums[[Phase]:[Phase]]= TandE[[#This Row],[Phase]:[Phase]]))) - (SUM(_xlfn._xlws.FILTER(TandE[Role 13], (TandE[[Practice]:[Practice]] <>"Padding")*(TandE[[Phase]:[Phase]]=TandE[[#This Row],[Phase]:[Phase]])))) / INDIRECT(TandE[[#This Row],[Phase]:[Phase]]&"_Length")) *INDIRECT(TandE[[#This Row],[Phase]:[Phase]]&"_Length"), 0), 0)} -> 0 | Y147: {=IFERROR(IF(AND((SUM(_xlfn._xlws.FILTER(TandE[Role 14], (TandE[[Practice]:[Practice]]<>"Padding")*(TandE[[Phase]:[Phase]]=TandE[[#This Row],[Phase]:[Phase]])))) >0,(SUM(_xlfn._xlws.FILTER(TandE[Role 14], (TandE[[Practice]:[Practice]]<>"Padding")*(TandE[[Phase]:[Phase]]=TandE[[#This Row],[Phase]:[Phase]])))) / INDIRECT(TandE[[#This Row],[Phase]:[Phase]]& "_Length") < SUM(_xlfn._xlws.FILTER(AllocationMinimums[[Min]:[Min]], (AllocationMinimums[[Role]:[Role]]= LEFT(Y$2,FIND("-",Y$2)-1))*(AllocationMinimums[[Phase]:[Phase]]= TandE[[#This Row],[Phase]:[Phase]])))), (SUM(_xlfn._xlws.FILTER(AllocationMinimums[[Min]:[Min]], (AllocationMinimums[[Role]:[Role]] = LEFT(Y$2,FIND("-",Y$2)-1))*(AllocationMinimums[[Phase]:[Phase]]= TandE[[#This Row],[Phase]:[Phase]]))) - (SUM(_xlfn._xlws.FILTER(TandE[Role 14], (TandE[[Practice]:[Practice]] <>"Padding")*(TandE[[Phase]:[Phase]]=TandE[[#This Row],[Phase]:[Phase]])))) / INDIRECT(TandE[[#This Row],[Phase]:[Phase]]&"_Length")) *INDIRECT(TandE[[#This Row],[Phase]:[Phase]]&"_Length"), 0), 0)} -> 0 | Z147: {=IFERROR(IF(AND((SUM(_xlfn._xlws.FILTER(TandE[Role 15], (TandE[[Practice]:[Practice]]<>"Padding")*(TandE[[Phase]:[Phase]]=TandE[[#This Row],[Phase]:[Phase]])))) >0,(SUM(_xlfn._xlws.FILTER(TandE[Role 15], (TandE[[Practice]:[Practice]]<>"Padding")*(TandE[[Phase]:[Phase]]=TandE[[#This Row],[Phase]:[Phase]])))) / INDIRECT(TandE[[#This Row],[Phase]:[Phase]]& "_Length") < SUM(_xlfn._xlws.FILTER(AllocationMinimums[[Min]:[Min]], (AllocationMinimums[[Role]:[Role]]= LEFT(Z$2,FIND("-",Z$2)-1))*(AllocationMinimums[[Phase]:[Phase]]= TandE[[#This Row],[Phase]:[Phase]])))), (SUM(_xlfn._xlws.FILTER(AllocationMinimums[[Min]:[Min]], (AllocationMinimums[[Role]:[Role]] = LEFT(Z$2,FIND("-",Z$2)-1))*(AllocationMinimums[[Phase]:[Phase]]= TandE[[#This Row],[Phase]:[Phase]]))) - (SUM(_xlfn._xlws.FILTER(TandE[Role 15], (TandE[[Practice]:[Practice]] <>"Padding")*(TandE[[Phase]:[Phase]]=TandE[[#This Row],[Phase]:[Phase]])))) / INDIRECT(TandE[[#This Row],[Phase]:[Phase]]&"_Length")) *INDIRECT(TandE[[#This Row],[Phase]:[Phase]]&"_Length"), 0), 0)} -> 0
B148: Plan | C148: =PLAN_START -> 2 | D148: =PLAN_END -> 2 | E148: Calculated Padding for minimums | H148: Yes | I148: Padding | K148: Billable | M148: {=IFERROR(IF(AND((SUM(_xlfn._xlws.FILTER(TandE[Role 2], (TandE[[Practice]:[Practice]]<>"Padding")*(TandE[[Phase]:[Phase]]=TandE[[#This Row],[Phase]:[Phase]])))) >0,(SUM(_xlfn._xlws.FILTER(TandE[Role 2], (TandE[[Practice]:[Practice]]<>"Padding")*(TandE[[Phase]:[Phase]]=TandE[[#This Row],[Phase]:[Phase]])))) / INDIRECT(TandE[[#This Row],[Phase]:[Phase]]& "_Length") < SUM(_xlfn._xlws.FILTER(AllocationMinimums[[Min]:[Min]], (AllocationMinimums[[Role]:[Role]]= LEFT(M$2,FIND("-",M$2)-1))*(AllocationMinimums[[Phase]:[Phase]]= TandE[[#This Row],[Phase]:[Phase]])))), (SUM(_xlfn._xlws.FILTER(AllocationMinimums[[Min]:[Min]], (AllocationMinimums[[Role]:[Role]] = LEFT(M$2,FIND("-",M$2)-1))*(AllocationMinimums[[Phase]:[Phase]]= TandE[[#This Row],[Phase]:[Phase]]))) - (SUM(_xlfn._xlws.FILTER(TandE[Role 2], (TandE[[Practice]:[Practice]] <>"Padding")*(TandE[[Phase]:[Phase]]=TandE[[#This Row],[Phase]:[Phase]])))) / INDIRECT(TandE[[#This Row],[Phase]:[Phase]]&"_Length")) *INDIRECT(TandE[[#This Row],[Phase]:[Phase]]&"_Length"), 0), 0)} -> 0 | N148: {=IFERROR(IF(AND((SUM(_xlfn._xlws.FILTER(TandE[Role 3], (TandE[[Practice]:[Practice]]<>"Padding")*(TandE[[Phase]:[Phase]]=TandE[[#This Row],[Phase]:[Phase]])))) >0,(SUM(_xlfn._xlws.FILTER(TandE[Role 3], (TandE[[Practice]:[Practice]]<>"Padding")*(TandE[[Phase]:[Phase]]=TandE[[#This Row],[Phase]:[Phase]])))) / INDIRECT(TandE[[#This Row],[Phase]:[Phase]]& "_Length") < SUM(_xlfn._xlws.FILTER(AllocationMinimums[[Min]:[Min]], (AllocationMinimums[[Role]:[Role]]= LEFT(N$2,FIND("-",N$2)-1))*(AllocationMinimums[[Phase]:[Phase]]= TandE[[#This Row],[Phase]:[Phase]])))), (SUM(_xlfn._xlws.FILTER(AllocationMinimums[[Min]:[Min]], (AllocationMinimums[[Role]:[Role]] = LEFT(N$2,FIND("-",N$2)-1))*(AllocationMinimums[[Phase]:[Phase]]= TandE[[#This Row],[Phase]:[Phase]]))) - (SUM(_xlfn._xlws.FILTER(TandE[Role 3], (TandE[[Practice]:[Practice]] <>"Padding")*(TandE[[Phase]:[Phase]]=TandE[[#This Row],[Phase]:[Phase]])))) / INDIRECT(TandE[[#This Row],[Phase]:[Phase]]&"_Length")) *INDIRECT(TandE[[#This Row],[Phase]:[Phase]]&"_Length"), 0), 0)} -> 0 | O148: {=IFERROR(IF(AND((SUM(_xlfn._xlws.FILTER(TandE[Role 4], (TandE[[Practice]:[Practice]]<>"Padding")*(TandE[[Phase]:[Phase]]=TandE[[#This Row],[Phase]:[Phase]])))) >0,(SUM(_xlfn._xlws.FILTER(TandE[Role 4], (TandE[[Practice]:[Practice]]<>"Padding")*(TandE[[Phase]:[Phase]]=TandE[[#This Row],[Phase]:[Phase]])))) / INDIRECT(TandE[[#This Row],[Phase]:[Phase]]& "_Length") < SUM(_xlfn._xlws.FILTER(AllocationMinimums[[Min]:[Min]], (AllocationMinimums[[Role]:[Role]]= LEFT(O$2,FIND("-",O$2)-1))*(AllocationMinimums[[Phase]:[Phase]]= TandE[[#This Row],[Phase]:[Phase]])))), (SUM(_xlfn._xlws.FILTER(AllocationMinimums[[Min]:[Min]], (AllocationMinimums[[Role]:[Role]] = LEFT(O$2,FIND("-",O$2)-1))*(AllocationMinimums[[Phase]:[Phase]]= TandE[[#This Row],[Phase]:[Phase]]))) - (SUM(_xlfn._xlws.FILTER(TandE[Role 4], (TandE[[Practice]:[Practice]] <>"Padding")*(TandE[[Phase]:[Phase]]=TandE[[#This Row],[Phase]:[Phase]])))) / INDIRECT(TandE[[#This Row],[Phase]:[Phase]]&"_Length")) *INDIRECT(TandE[[#This Row],[Phase]:[Phase]]&"_Length"), 0), 0)} -> 0 | P148: {=IFERROR(IF(AND((SUM(_xlfn._xlws.FILTER(TandE[Role 5], (TandE[[Practice]:[Practice]]<>"Padding")*(TandE[[Phase]:[Phase]]=TandE[[#This Row],[Phase]:[Phase]])))) >0,(SUM(_xlfn._xlws.FILTER(TandE[Role 5], (TandE[[Practice]:[Practice]]<>"Padding")*(TandE[[Phase]:[Phase]]=TandE[[#This Row],[Phase]:[Phase]])))) / INDIRECT(TandE[[#This Row],[Phase]:[Phase]]& "_Length") < SUM(_xlfn._xlws.FILTER(AllocationMinimums[[Min]:[Min]], (AllocationMinimums[[Role]:[Role]]= LEFT(P$2,FIND("-",P$2)-1))*(AllocationMinimums[[Phase]:[Phase]]= TandE[[#This Row],[Phase]:[Phase]])))), (SUM(_xlfn._xlws.FILTER(AllocationMinimums[[Min]:[Min]], (AllocationMinimums[[Role]:[Role]] = LEFT(P$2,FIND("-",P$2)-1))*(AllocationMinimums[[Phase]:[Phase]]= TandE[[#This Row],[Phase]:[Phase]]))) - (SUM(_xlfn._xlws.FILTER(TandE[Role 5], (TandE[[Practice]:[Practice]] <>"Padding")*(TandE[[Phase]:[Phase]]=TandE[[#This Row],[Phase]:[Phase]])))) / INDIRECT(TandE[[#This Row],[Phase]:[Phase]]&"_Length")) *INDIRECT(TandE[[#This Row],[Phase]:[Phase]]&"_Length"), 0), 0)} -> 0 | Q148: {=IFERROR(IF(AND((SUM(_xlfn._xlws.FILTER(TandE[Role 6], (TandE[[Practice]:[Practice]]<>"Padding")*(TandE[[Phase]:[Phase]]=TandE[[#This Row],[Phase]:[Phase]])))) >0,(SUM(_xlfn._xlws.FILTER(TandE[Role 6], (TandE[[Practice]:[Practice]]<>"Padding")*(TandE[[Phase]:[Phase]]=TandE[[#This Row],[Phase]:[Phase]])))) / INDIRECT(TandE[[#This Row],[Phase]:[Phase]]& "_Length") < SUM(_xlfn._xlws.FILTER(AllocationMinimums[[Min]:[Min]], (AllocationMinimums[[Role]:[Role]]= LEFT(Q$2,FIND("-",Q$2)-1))*(AllocationMinimums[[Phase]:[Phase]]= TandE[[#This Row],[Phase]:[Phase]])))), (SUM(_xlfn._xlws.FILTER(AllocationMinimums[[Min]:[Min]], (AllocationMinimums[[Role]:[Role]] = LEFT(Q$2,FIND("-",Q$2)-1))*(AllocationMinimums[[Phase]:[Phase]]= TandE[[#This Row],[Phase]:[Phase]]))) - (SUM(_xlfn._xlws.FILTER(TandE[Role 6], (TandE[[Practice]:[Practice]] <>"Padding")*(TandE[[Phase]:[Phase]]=TandE[[#This Row],[Phase]:[Phase]])))) / INDIRECT(TandE[[#This Row],[Phase]:[Phase]]&"_Length")) *INDIRECT(TandE[[#This Row],[Phase]:[Phase]]&"_Length"), 0), 0)} -> 0 | R148: {=IFERROR(IF(AND((SUM(_xlfn._xlws.FILTER(TandE[Role 7], (TandE[[Practice]:[Practice]]<>"Padding")*(TandE[[Phase]:[Phase]]=TandE[[#This Row],[Phase]:[Phase]])))) >0,(SUM(_xlfn._xlws.FILTER(TandE[Role 7], (TandE[[Practice]:[Practice]]<>"Padding")*(TandE[[Phase]:[Phase]]=TandE[[#This Row],[Phase]:[Phase]])))) / INDIRECT(TandE[[#This Row],[Phase]:[Phase]]& "_Length") < SUM(_xlfn._xlws.FILTER(AllocationMinimums[[Min]:[Min]], (AllocationMinimums[[Role]:[Role]]= LEFT(R$2,FIND("-",R$2)-1))*(AllocationMinimums[[Phase]:[Phase]]= TandE[[#This Row],[Phase]:[Phase]])))), (SUM(_xlfn._xlws.FILTER(AllocationMinimums[[Min]:[Min]], (AllocationMinimums[[Role]:[Role]] = LEFT(R$2,FIND("-",R$2)-1))*(AllocationMinimums[[Phase]:[Phase]]= TandE[[#This Row],[Phase]:[Phase]]))) - (SUM(_xlfn._xlws.FILTER(TandE[Role 7], (TandE[[Practice]:[Practice]] <>"Padding")*(TandE[[Phase]:[Phase]]=TandE[[#This Row],[Phase]:[Phase]])))) / INDIRECT(TandE[[#This Row],[Phase]:[Phase]]&"_Length")) *INDIRECT(TandE[[#This Row],[Phase]:[Phase]]&"_Length"), 0), 0)} -> 0 | S148: {=IFERROR(IF(AND((SUM(_xlfn._xlws.FILTER(TandE[Role 8], (TandE[[Practice]:[Practice]]<>"Padding")*(TandE[[Phase]:[Phase]]=TandE[[#This Row],[Phase]:[Phase]])))) >0,(SUM(_xlfn._xlws.FILTER(TandE[Role 8], (TandE[[Practice]:[Practice]]<>"Padding")*(TandE[[Phase]:[Phase]]=TandE[[#This Row],[Phase]:[Phase]])))) / INDIRECT(TandE[[#This Row],[Phase]:[Phase]]& "_Length") < SUM(_xlfn._xlws.FILTER(AllocationMinimums[[Min]:[Min]], (AllocationMinimums[[Role]:[Role]]= LEFT(S$2,FIND("-",S$2)-1))*(AllocationMinimums[[Phase]:[Phase]]= TandE[[#This Row],[Phase]:[Phase]])))), (SUM(_xlfn._xlws.FILTER(AllocationMinimums[[Min]:[Min]], (AllocationMinimums[[Role]:[Role]] = LEFT(S$2,FIND("-",S$2)-1))*(AllocationMinimums[[Phase]:[Phase]]= TandE[[#This Row],[Phase]:[Phase]]))) - (SUM(_xlfn._xlws.FILTER(TandE[Role 8], (TandE[[Practice]:[Practice]] <>"Padding")*(TandE[[Phase]:[Phase]]=TandE[[#This Row],[Phase]:[Phase]])))) / INDIRECT(TandE[[#This Row],[Phase]:[Phase]]&"_Length")) *INDIRECT(TandE[[#This Row],[Phase]:[Phase]]&"_Length"), 0), 0)} -> 0 | T148: {=IFERROR(IF(AND((SUM(_xlfn._xlws.FILTER(TandE[Role 9], (TandE[[Practice]:[Practice]]<>"Padding")*(TandE[[Phase]:[Phase]]=TandE[[#This Row],[Phase]:[Phase]])))) >0,(SUM(_xlfn._xlws.FILTER(TandE[Role 9], (TandE[[Practice]:[Practice]]<>"Padding")*(TandE[[Phase]:[Phase]]=TandE[[#This Row],[Phase]:[Phase]])))) / INDIRECT(TandE[[#This Row],[Phase]:[Phase]]& "_Length") < SUM(_xlfn._xlws.FILTER(AllocationMinimums[[Min]:[Min]], (AllocationMinimums[[Role]:[Role]]= LEFT(T$2,FIND("-",T$2)-1))*(AllocationMinimums[[Phase]:[Phase]]= TandE[[#This Row],[Phase]:[Phase]])))), (SUM(_xlfn._xlws.FILTER(AllocationMinimums[[Min]:[Min]], (AllocationMinimums[[Role]:[Role]] = LEFT(T$2,FIND("-",T$2)-1))*(AllocationMinimums[[Phase]:[Phase]]= TandE[[#This Row],[Phase]:[Phase]]))) - (SUM(_xlfn._xlws.FILTER(TandE[Role 9], (TandE[[Practice]:[Practice]] <>"Padding")*(TandE[[Phase]:[Phase]]=TandE[[#This Row],[Phase]:[Phase]])))) / INDIRECT(TandE[[#This Row],[Phase]:[Phase]]&"_Length")) *INDIRECT(TandE[[#This Row],[Phase]:[Phase]]&"_Length"), 0), 0)} -> 0 | U148: {=IFERROR(IF(AND((SUM(_xlfn._xlws.FILTER(TandE[Role 10], (TandE[[Practice]:[Practice]]<>"Padding")*(TandE[[Phase]:[Phase]]=TandE[[#This Row],[Phase]:[Phase]])))) >0,(SUM(_xlfn._xlws.FILTER(TandE[Role 10], (TandE[[Practice]:[Practice]]<>"Padding")*(TandE[[Phase]:[Phase]]=TandE[[#This Row],[Phase]:[Phase]])))) / INDIRECT(TandE[[#This Row],[Phase]:[Phase]]& "_Length") < SUM(_xlfn._xlws.FILTER(AllocationMinimums[[Min]:[Min]], (AllocationMinimums[[Role]:[Role]]= LEFT(U$2,FIND("-",U$2)-1))*(AllocationMinimums[[Phase]:[Phase]]= TandE[[#This Row],[Phase]:[Phase]])))), (SUM(_xlfn._xlws.FILTER(AllocationMinimums[[Min]:[Min]], (AllocationMinimums[[Role]:[Role]] = LEFT(U$2,FIND("-",U$2)-1))*(AllocationMinimums[[Phase]:[Phase]]= TandE[[#This Row],[Phase]:[Phase]]))) - (SUM(_xlfn._xlws.FILTER(TandE[Role 10], (TandE[[Practice]:[Practice]] <>"Padding")*(TandE[[Phase]:[Phase]]=TandE[[#This Row],[Phase]:[Phase]])))) / INDIRECT(TandE[[#This Row],[Phase]:[Phase]]&"_Length")) *INDIRECT(TandE[[#This Row],[Phase]:[Phase]]&"_Length"), 0), 0)} -> 0 | V148: {=IFERROR(IF(AND((SUM(_xlfn._xlws.FILTER(TandE[Role 11], (TandE[[Practice]:[Practice]]<>"Padding")*(TandE[[Phase]:[Phase]]=TandE[[#This Row],[Phase]:[Phase]])))) >0,(SUM(_xlfn._xlws.FILTER(TandE[Role 11], (TandE[[Practice]:[Practice]]<>"Padding")*(TandE[[Phase]:[Phase]]=TandE[[#This Row],[Phase]:[Phase]])))) / INDIRECT(TandE[[#This Row],[Phase]:[Phase]]& "_Length") < SUM(_xlfn._xlws.FILTER(AllocationMinimums[[Min]:[Min]], (AllocationMinimums[[Role]:[Role]]= LEFT(V$2,FIND("-",V$2)-1))*(AllocationMinimums[[Phase]:[Phase]]= TandE[[#This Row],[Phase]:[Phase]])))), (SUM(_xlfn._xlws.FILTER(AllocationMinimums[[Min]:[Min]], (AllocationMinimums[[Role]:[Role]] = LEFT(V$2,FIND("-",V$2)-1))*(AllocationMinimums[[Phase]:[Phase]]= TandE[[#This Row],[Phase]:[Phase]]))) - (SUM(_xlfn._xlws.FILTER(TandE[Role 11], (TandE[[Practice]:[Practice]] <>"Padding")*(TandE[[Phase]:[Phase]]=TandE[[#This Row],[Phase]:[Phase]])))) / INDIRECT(TandE[[#This Row],[Phase]:[Phase]]&"_Length")) *INDIRECT(TandE[[#This Row],[Phase]:[Phase]]&"_Length"), 0), 0)} -> 0 | W148: {=IFERROR(IF(AND((SUM(_xlfn._xlws.FILTER(TandE[Role 12], (TandE[[Practice]:[Practice]]<>"Padding")*(TandE[[Phase]:[Phase]]=TandE[[#This Row],[Phase]:[Phase]])))) >0,(SUM(_xlfn._xlws.FILTER(TandE[Role 12], (TandE[[Practice]:[Practice]]<>"Padding")*(TandE[[Phase]:[Phase]]=TandE[[#This Row],[Phase]:[Phase]])))) / INDIRECT(TandE[[#This Row],[Phase]:[Phase]]& "_Length") < SUM(_xlfn._xlws.FILTER(AllocationMinimums[[Min]:[Min]], (AllocationMinimums[[Role]:[Role]]= LEFT(W$2,FIND("-",W$2)-1))*(AllocationMinimums[[Phase]:[Phase]]= TandE[[#This Row],[Phase]:[Phase]])))), (SUM(_xlfn._xlws.FILTER(AllocationMinimums[[Min]:[Min]], (AllocationMinimums[[Role]:[Role]] = LEFT(W$2,FIND("-",W$2)-1))*(AllocationMinimums[[Phase]:[Phase]]= TandE[[#This Row],[Phase]:[Phase]]))) - (SUM(_xlfn._xlws.FILTER(TandE[Role 12], (TandE[[Practice]:[Practice]] <>"Padding")*(TandE[[Phase]:[Phase]]=TandE[[#This Row],[Phase]:[Phase]])))) / INDIRECT(TandE[[#This Row],[Phase]:[Phase]]&"_Length")) *INDIRECT(TandE[[#This Row],[Phase]:[Phase]]&"_Length"), 0), 0)} -> 0 | X148: {=IFERROR(IF(AND((SUM(_xlfn._xlws.FILTER(TandE[Role 13], (TandE[[Practice]:[Practice]]<>"Padding")*(TandE[[Phase]:[Phase]]=TandE[[#This Row],[Phase]:[Phase]])))) >0,(SUM(_xlfn._xlws.FILTER(TandE[Role 13], (TandE[[Practice]:[Practice]]<>"Padding")*(TandE[[Phase]:[Phase]]=TandE[[#This Row],[Phase]:[Phase]])))) / INDIRECT(TandE[[#This Row],[Phase]:[Phase]]& "_Length") < SUM(_xlfn._xlws.FILTER(AllocationMinimums[[Min]:[Min]], (AllocationMinimums[[Role]:[Role]]= LEFT(X$2,FIND("-",X$2)-1))*(AllocationMinimums[[Phase]:[Phase]]= TandE[[#This Row],[Phase]:[Phase]])))), (SUM(_xlfn._xlws.FILTER(AllocationMinimums[[Min]:[Min]], (AllocationMinimums[[Role]:[Role]] = LEFT(X$2,FIND("-",X$2)-1))*(AllocationMinimums[[Phase]:[Phase]]= TandE[[#This Row],[Phase]:[Phase]]))) - (SUM(_xlfn._xlws.FILTER(TandE[Role 13], (TandE[[Practice]:[Practice]] <>"Padding")*(TandE[[Phase]:[Phase]]=TandE[[#This Row],[Phase]:[Phase]])))) / INDIRECT(TandE[[#This Row],[Phase]:[Phase]]&"_Length")) *INDIRECT(TandE[[#This Row],[Phase]:[Phase]]&"_Length"), 0), 0)} -> 0 | Y148: {=IFERROR(IF(AND((SUM(_xlfn._xlws.FILTER(TandE[Role 14], (TandE[[Practice]:[Practice]]<>"Padding")*(TandE[[Phase]:[Phase]]=TandE[[#This Row],[Phase]:[Phase]])))) >0,(SUM(_xlfn._xlws.FILTER(TandE[Role 14], (TandE[[Practice]:[Practice]]<>"Padding")*(TandE[[Phase]:[Phase]]=TandE[[#This Row],[Phase]:[Phase]])))) / INDIRECT(TandE[[#This Row],[Phase]:[Phase]]& "_Length") < SUM(_xlfn._xlws.FILTER(AllocationMinimums[[Min]:[Min]], (AllocationMinimums[[Role]:[Role]]= LEFT(Y$2,FIND("-",Y$2)-1))*(AllocationMinimums[[Phase]:[Phase]]= TandE[[#This Row],[Phase]:[Phase]])))), (SUM(_xlfn._xlws.FILTER(AllocationMinimums[[Min]:[Min]], (AllocationMinimums[[Role]:[Role]] = LEFT(Y$2,FIND("-",Y$2)-1))*(AllocationMinimums[[Phase]:[Phase]]= TandE[[#This Row],[Phase]:[Phase]]))) - (SUM(_xlfn._xlws.FILTER(TandE[Role 14], (TandE[[Practice]:[Practice]] <>"Padding")*(TandE[[Phase]:[Phase]]=TandE[[#This Row],[Phase]:[Phase]])))) / INDIRECT(TandE[[#This Row],[Phase]:[Phase]]&"_Length")) *INDIRECT(TandE[[#This Row],[Phase]:[Phase]]&"_Length"), 0), 0)} -> 0 | Z148: {=IFERROR(IF(AND((SUM(_xlfn._xlws.FILTER(TandE[Role 15], (TandE[[Practice]:[Practice]]<>"Padding")*(TandE[[Phase]:[Phase]]=TandE[[#This Row],[Phase]:[Phase]])))) >0,(SUM(_xlfn._xlws.FILTER(TandE[Role 15], (TandE[[Practice]:[Practice]]<>"Padding")*(TandE[[Phase]:[Phase]]=TandE[[#This Row],[Phase]:[Phase]])))) / INDIRECT(TandE[[#This Row],[Phase]:[Phase]]& "_Length") < SUM(_xlfn._xlws.FILTER(AllocationMinimums[[Min]:[Min]], (AllocationMinimums[[Role]:[Role]]= LEFT(Z$2,FIND("-",Z$2)-1))*(AllocationMinimums[[Phase]:[Phase]]= TandE[[#This Row],[Phase]:[Phase]])))), (SUM(_xlfn._xlws.FILTER(AllocationMinimums[[Min]:[Min]], (AllocationMinimums[[Role]:[Role]] = LEFT(Z$2,FIND("-",Z$2)-1))*(AllocationMinimums[[Phase]:[Phase]]= TandE[[#This Row],[Phase]:[Phase]]))) - (SUM(_xlfn._xlws.FILTER(TandE[Role 15], (TandE[[Practice]:[Practice]] <>"Padding")*(TandE[[Phase]:[Phase]]=TandE[[#This Row],[Phase]:[Phase]])))) / INDIRECT(TandE[[#This Row],[Phase]:[Phase]]&"_Length")) *INDIRECT(TandE[[#This Row],[Phase]:[Phase]]&"_Length"), 0), 0)} -> 0
